Workbook

Sheet gameModeMap_header
A1: Index | B1: Key | C1: Value | D1: DirectlyImport? | E1: Flexible | F1: OutputOrder
A2: 0 | B2: key | C2: 主键 | D2: √ | F2: 0
A3: 1 | B3: mModeName | C3: 模式代号 | D3: √ | F3: 1
A4: 2 | B4: Configs | C4: 模式基础信息目录 | D4: √ | E4: √ | F4: 4
A5: 3 | B5: ConfigsClient | C5: 客户端配置目录 | D5: √ | F5: 5
A6: 4 | B6: mChampionLists | C6: 英雄列表 | D6: √ | E6: √ | F6: 11
A7: 5 | B7: itemLists | C7: 装备目录 | D7: √ | F7: 13
A8: 6 | B8: {dc2bc473} | C8: 模式特定装备目录 | D8: √ | E8: √ | F8: 14
A9: 7 | B9: mItemShopData | C9: 商店数据 | D9: √ | F9: 12
A10: 8 | B10: AdditionalPropertyDataPaths | C10: 附加说明文件路径 | D10: √ | F10: 28
A11: 9 | B11: AnnouncementsMapping | C11: 通告映射 | D11: √ | F11: 22
A12: 10 | B12: mRelativeColorization | C12: 采用相对着色法 | D12: √ | F12: 23
A13: 11 | B13: mCursorConfig | C13: 指针配置文件 | D13: √ | F13: 25
A14: 12 | B14: mCursorConfigUpdate | C14: 新版指针配置文件 | D14: √ | F14: 26
A15: 13 | B15: mStatsUiData | C15: 属性面板数据 | D15: √ | F15: 10
A16: 14 | B16: mChampionIndicatorEnabled | C16: 英雄指示器可用性 | D16: √ | E16: √ | F16: 24
A17: 15 | B17: JungleRecommendationMapInformation | C17: 推荐打野路线信息 | D17: √ | E17: √ | F17: 18
A18: 16 | B18: DefaultJunglePathRecommendation | C18: 默认打野路线 | D18: √ | E18: √ | F18: 19
A19: 17 | B19: StartupCheats | C19: 启动指令 | D19: √ | E19: √ | F19: 9
A20: 18 | B20: mExperienceCurveData | C20: 经验曲线算法 | D20: √ | F20: 6
A21: 19 | B21: mExperienceModData | C21: 经验获取调整 | D21: √ | F21: 7
A22: 20 | B22: mDeathTimes | C22: 复活计时器 | D22: √ | F22: 8
A23: 21 | B23: mMapLocators | C23: 地图物件坐标 | D23: √ | F23: 16
A24: 22 | B24: mPerkReplacements | C24: 符文替换信息 | D24: √ | E24: √ | F24: 20
A25: 23 | B25: mGameModeConstants | C25: 游戏模式常数 | D25: √ | F25: 2
A26: 24 | B26: DefaultRespawnPoints | C26: 默认重生位置 | D26: √ | E26: √ | F26: 17
A27: 25 | B27: mGameplayConfig | C27: 游戏玩法信息 | D27: √ | F27: 3
A28: 26 | B28: mSurrenderSettings | C28: 投降设置 | D28: √ | F28: 21
A29: 27 | B29: mAutoItemPurchasingConfig | C29: 装备构件购买信息 | D29: √ | F29: 15
A30: 28 | B30: LevelControllers | C30: 荣誉等级管理 | D30: √ | E30: √ | F30: 27
A31: 29 | B31: Configs SmartPingData {5aa830e8} | D31: √
A32: 30 | B32: Configs SmartPingData {aa8eb438} | D32: √
A33: 31 | B33: Configs SmartPingData {1e98bb0e} | D33: √
A34: 32 | B34: Configs CharacterQuestListConfig {6f7129e6} | D34: √
A35: 33 | B35: Configs CharacterQuestListConfig {702d99a3} | D35: √
A36: 34 | B36: Configs CharacterQuestListConfig CharacterQuestList | C36: 英雄彩蛋列表 | D36: √
A37: 35 | B37: Configs CharacterQuestListConfig CharacterQuestDefinitionsList | C37: 英雄彩蛋定义 | D37: √
A38: 36 | B38: Configs ReciprocityConfig throttleLimit | D38: √
A39: 37 | B39: Configs ReciprocityConfig {8e26fcb2} | D39: √
A40: 38 | B40: Configs {6b91544a} BlurTextures | C40: 启用模糊纹理 | D40: √
A41: 39 | B41: Configs {6b91544a} UpscaleTextures | C41: 启用放大纹理 | D41: √
A42: 40 | B42: Configs {6b91544a} {46edf5aa} | D42: √
A43: 41 | B43: Configs {6b91544a} VfxSystems | C43: 视觉特效系统 | D43: √
A44: 42 | B44: Configs {9f30b8a6} BaseGold | C44: 击杀基础金币 | D44: √
A45: 43 | B45: Configs {9f30b8a6} FirstBloodBonus | C45: 第一滴血额外金币 | D45: √ | E45: √
A46: 44 | B46: Configs {9f30b8a6} AssistDurationOverride | C46: 助攻窗口时间 | D46: √
A47: 45 | B47: Configs {9f30b8a6} {11f10a40} | D47: √
A48: 46 | B48: Configs {9f30b8a6} {937cc95a} | D48: √
A49: 47 | B49: Configs {9f30b8a6} {08c1b120} | D49: √
A50: 48 | B50: Configs {9f30b8a6} {1eacb90a} | D50: √
A51: 49 | B51: Configs {9f30b8a6} {ce073fe8} | D51: √
A52: 50 | B52: Configs {9f30b8a6} {fd43d59f} | D52: √
A53: 51 | B53: Configs {9f30b8a6} {3cf326fa} | D53: √
A54: 52 | B54: Configs {9f30b8a6} {907442e7} | D54: √
A55: 53 | B55: Configs {9f30b8a6} {fe1b406e} | D55: √
A56: 54 | B56: Configs {9f30b8a6} {d1f9fb6a} | D56: √
A57: 55 | B57: Configs {9f30b8a6} {54ccd262} | D57: √
A58: 56 | B58: Configs {9f30b8a6} {c29d06b9} | D58: √
... A64: 62 | B64: Configs {9f30b8a6} {a7e2cc37} | D64: √
A65: 63 | B65: Configs {9f30b8a6} {a966473c} | C65: 正悬赏信息 | D65: √
A66: 64 | B66: Configs {9f30b8a6} ObjectiveBountyConfig | C66: 战略点悬赏信息 | D66: √
A67: 65 | B67: Configs {9f30b8a6} NegativeBountyConfig | C67: 负悬赏信息 | D67: √
A68: 66 | B68: Configs {1ff0e246} {5ba4ad0f} | D68: √
A69: 67 | B69: Configs {1ff0e246} {960dcbff} | D69: √
A70: 68 | B70: Configs {1ff0e246} {e999961a} | D70: √
A71: 69 | B71: Configs {1ff0e246} {f39f8571} | D71: √
A72: 70 | B72: Configs {1ff0e246} {d1e56ce4} | D72: √
A73: 71 | B73: Configs {1ff0e246} {f34f5793} | D73: √
A74: 72 | B74: Configs {90f7282b} {116cb40d} | D74: √
A75: 73 | B75: ConfigsClient {60e2ec74} LoadScreenTipConfiguration | C75: 加载界面提示信息 | D75: √
A76: 74 | B76: ConfigsClient {60e2ec74} LoadingScreenBackground | C76: 加载界面背景 | D76: √
A77: 75 | B77: ConfigsClient {60e2ec74} LoadingScreenBackgroundOverride | C77: 加载界面背景重载 | D77: √
A78: 76 | B78: ConfigsClient {60e2ec74} MutatorControlledLoadingScreenBackgrounds | C78: 特殊模式加载界面背景 | D78: √ | E78: √
A79: 77 | B79: ConfigsClient {85bf79cf} {07aa36d0} | D79: √
A80: 78 | B80: ConfigsClient {85bf79cf} {c5b58261} | D80: √
A81: 79 | B81: itemLists GameModeItemList mItems | C81: 游戏模式装备目录 | D81: √
A82: 80 | B82: mItemShopData ItemShopGameModeData RecOverrideSmiteStartingItems | C82: 惩戒强制购买初始装备 | D82: √
A83: 81 | B83: mItemShopData ItemShopGameModeData PurchasedItemExclusionItems | C83: 不可购买的装备 | D83: √
A84: 82 | B84: mItemShopData ItemShopGameModeData CompletedItems | C84: 成装 | D84: √
A85: 83 | B85: mItemShopData ItemShopGameModeData RecFallbackMapId | C85: 推荐回退地图序号 | D85: √
A86: 84 | B86: mItemShopData ItemShopGameModeData RecFallbackModeName | C86: 推荐回退模式 | D86: √
A87: 85 | B87: mItemShopData ItemShopGameModeData ConsumablesQuickBuyData | C87: 消耗品 | D87: √
A88: 86 | B88: mItemShopData ItemShopGameModeData BootsQuickBuyData | C88: 鞋子 | D88: √
A89: 87 | B89: mItemShopData ItemShopGameModeData RecItemsSwaps | C89: 装备替换 | D89: √
A90: 88 | B90: mItemShopData ItemShopGameModeData AllItemGroupDefinitionsOverride | C90: 装备分组重定义信息 | D90: √
A91: 89 | B91: mItemShopData ItemShopGameModeData RecRoleSwaps | C91: 角色定位替换 | D91: √
A92: 90 | B92: AnnouncementsMapping AnnouncementMap ParentList | C92: 通告父级列表引用 | D92: √
... A121: 119 | B121: mStatsUiData GlobalStatsUIData NewStatUiData | C121: 新版界面 | D121: √
A122: 120 | B122: mExperienceCurveData ExperienceCurveData mExperienceRequiredPerLevel | C122: 升级所需经验 | D122: √ | E122: √
A123: 121 | B123: mExperienceCurveData ExperienceCurveData mExperienceGrantedForKillPerLevel | C123: 击杀经验 | D123: √ | E123: √
A124: 122 | B124: mExperienceCurveData ExperienceCurveData mExperienceGrantedMultForSharedKillPerLevel | C124: 共享击杀经验倍率 | D124: √ | E124: √
A125: 123 | B125: mExperienceCurveData ExperienceCurveData LevelDifferenceExperienceMultiplierPerLevel | C125: 等级差异经验倍率 | D125: √ | E125: √
A126: 124 | B126: mExperienceCurveData ExperienceCurveData mBaseExperienceMultiplier | C126: 基础经验倍率 | D126: √ | E126: √
A127: 125 | B127: mExperienceCurveData ExperienceCurveData mMinimumExperienceMultiplier | C127: 最小经验倍率 | D127: √ | E127: √
A128: 126 | B128: mExperienceCurveData ExperienceCurveData DefaultMaxLevel | C128: 默认最大等级 | D128: √
A129: 127 | B129: mExperienceModData ExperienceModData mPlayerMinionSplitXp | C129: 小兵经验分配倍率 | D129: √
A130: 128 | B130: mDeathTimes DeathTimes mTimeDeadPerLevel | C130: 基础复活时间 | D130: √
A131: 129 | B131: mDeathTimes DeathTimes mScalingStartTime | C131: 游戏时长产生影响的时间 | D131: √
A132: 130 | B132: mDeathTimes DeathTimes mScalingIncrementTime | C132: 游戏时长缩放间隔 | D132: √
A133: 131 | B133: mDeathTimes DeathTimes mScalingPercentIncrease | C133: 游戏时长缩放百分比增量 | D133: √
...

Sheet cheatset_header
A1: Index | B1: Key | C1: Value | D1: DirectlyImport? | E1: Flexible | F1: defaultValue | G1: OutputOrder
A2: 0 | B2: key | C2: 主键 | D2: √ | G2: 0
A3: 1 | B3: mName | C3: 代码 | D3: √ | G3: 1
A4: 2 | B4: mIsPlayerFacing | C4: 可见性 | D4: √ | E4: √ | G4: 2
A5: 3 | B5: mGameModeName | C5: 游戏模式 | D5: √ | E5: √ | G5: 4
A6: 4 | B6: mGameMutator | C6: 子模式 | D6: √ | E6: √ | G6: 5
A7: 5 | B7: AssociatedChampions | C7: 相关英雄 | D7: √ | E7: √ | G7: 6
A8: 6 | B8: {bd50bdef} | C8: 指令列表 | D8: √ | E8: √ | G8: 7
A9: 7 | B9: mIsUIAlwaysShown | C9: 总是呈现 | D9: √ | E9: √ | G9: 3

Sheet cheat_header
A1: Index | B1: Key | C1: Value | D1: DirectlyImport? | E1: Flexible | F1: defaultValue | G1: OutputOrder
A2: 0 | B2: key | C2: 主键 | D2: √ | G2: 0
A3: 1 | B3: mName | C3: 代码 | D3: √ | G3: 3
A4: 2 | B4: mIsPlayerFacing | C4: 可见性 | D4: √ | E4: √ | F4: FALSE | G4: 5
A5: 3 | B5: mRecastFrequency | C5: 施法频率 | D5: √ | E5: √ | G5: 19
A6: 4 | B6: mTarget | C6: 作用目标 | D6: √ | E6: √ | G6: 20
A7: 5 | B7: UseTargetAsCaster | C7: 目标作为施法者 | D7: √ | E7: √ | F7: FALSE | G7: 21
A8: 6 | B8: UseTargetAsSource | C8: 目标作为来源 | D8: √ | E8: √ | F8: FALSE | G8: 22
A9: 7 | B9: mTimerValue | C9: 计时器取值 | D9: √ | E9: √ | G9: 23
A10: 8 | B10: mDamageAmount | C10: 伤害数额（百分比） | D10: √ | G10: 24
A11: 9 | B11: mScriptCallback | C11: 调用方法 | D11: √ | G11: 7
A12: 10 | B12: {30ce16ae} | C12: 作用野怪类型 | D12: √ | G12: 25
A13: 11 | B13: mKillExistingMinions | C13: 击杀存活小兵 | D13: √ | E13: √ | F13: FALSE | G13: 26
A14: 12 | B14: mKillWards | C14: 摧毁守卫 | D14: √ | E14: √ | F14: FALSE | G14: 27
A15: 13 | B15: mStartingItemIds | C15: 起始装备序号列表 | D15: √ | G15: 28
A16: 14 | B16: mGoldAmount | C16: 金币数额 | D16: √ | G16: 29
A17: 15 | B17: mFlags | C17: 旗标 | D17: √ | G17: 30
A18: 16 | B18: mTeam | C18: 阵营代号 | D18: √ | G18: 31
A19: 17 | B19: mPlayerName | C19: 玩家代码 | D19: √ | G19: 32
A20: 18 | B20: mMinionName | C20: 小兵代码 | D20: √ | G20: 33
A21: 19 | B21: mCharacterName | C21: 角色名称 | D21: √ | G21: 34
A22: 20 | B22: mAmount | C22: 数额 | D22: √ | G22: 35
A23: 21 | B23: mSpeedDown | C23: 减速 | D23: √ | E23: √ | F23: FALSE | G23: 36
A24: 22 | B24: mSpeedUp | C24: 加速 | D24: √ | E24: √ | F24: FALSE | G24: 37
A25: 23 | B25: ResetToBaseSpeed | C25: 重置为基础移动速度 | D25: √ | F25: FALSE | G25: 38
A26: 24 | B26: MoveDelta | C26: 移动速度增量 | D26: √ | G26: 39
A27: 25 | B27: mToggleHP | C27: 启用/禁用生命回复 | D27: √ | E27: √ | F27: FALSE | G27: 40
A28: 26 | B28: mTogglePAR | C28: 启用/禁用施法资源回复 | D28: √ | E28: √ | F28: FALSE | G28: 41
A29: 27 | B29: mGiveMaxLevel | C29: 提供最大等级 | D29: √ | G29: 42
A30: 28 | B30: mOnlyOnePointEach | C30: 即点即杀 | D30: √ | F30: FALSE | G30: 43
A31: 29 | B31: __type | C31: 对象数据类型 | D31: √ | G31: 1
A32: 30 | B32: mDisplayName | C32: 显示名 | G32: 4
A33: 31 | B33: mFloatingTextDisplayName | C33: 标题键 | D33: √ | E33: √ | G33: 8
A34: 32 | B34: mTooltipText | C34: 说明键 | D34: √ | E34: √ | G34: 11
A35: 33 | B35: mDynamicTooltipText | C35: 详细信息键 | D35: √ | E35: √ | G35: 14
A36: 34 | B36: mHotkey | C36: 快捷键代码 | D36: √ | E36: √ | G36: 17
A37: 35 | B37: mHotkeys | C37: 可用快捷键代码 | D37: √ | E37: √ | G37: 18
A38: 36 | B38: mIsToggleCheat | C38: 开关型 | D38: √ | E38: √ | F38: FALSE | G38: 6
A39: 37 | B39: mCheatMenuUIDataType | C39: 指令菜单数据类型 | D39: √ | E39: √
A40: 38 | B40: mFloatingTextDisplayName_content_zh | C40: 标题（中文） | E40: √ | G40: 9
A41: 39 | B41: mFloatingTextDisplayName_content_en | C41: 标题（英文） | G41: 10
A42: 40 | B42: mTooltipText_content_zh | C42: 说明（中文） | E42: √ | G42: 12
A43: 41 | B43: mTooltipText_content_en | C43: 说明（英文） | G43: 13
A44: 42 | B44: mDynamicTooltipText_content_zh | C44: 详细信息（中文） | E44: √ | G44: 15
A45: 43 | B45: mDynamicTooltipText_content_en | C45: 详细信息（英文） | G45: 16
A46: 44 | B46: belonging_cheatset_mName | C46: 所属指令集代码 | E46: √ | G46: 2

Sheet spell_header
A1: Index | B1: Key | C1: Value | D1: DirectlyImport? | E1: Flexible | F1: defaultValue | G1: OutputOrder
A2: 0 | B2: key | C2: 主键 | D2: √ | G2: 0
A3: 1 | B3: ObjectName | C3: 指令对象名称 | D3: √ | G3: 1
A4: 2 | B4: mScriptName | C4: 脚本名称 | D4: √ | G4: 7
A5: 3 | B5: {34cdd819} | D5: √ | E5: √ | G5: 2
A6: 4 | B6: Script | C6: 脚本主键 | D6: √ | E6: √ | G6: 6
A7: 5 | B7: mSpell flags | C7: 指令旗标 | D7: √ | E7: √ | G7: 9
A8: 6 | B8: mSpell mAffectsTypeFlags | C8: 作用目标类型旗标 | D8: √ | E8: √ | G8: 10
A9: 7 | B9: mSpell mAffectsStatusFlags | C9: 作用状态旗标 | D9: √ | E9: √ | G9: 11
A10: 8 | B10: mSpell mRequiredUnitTags mObjectTagList | C10: 所需目标单位标签列表 | D10: √ | G10: 71
A11: 9 | B11: mSpell mExcludedUnitTags mObjectTagList | C11: 无效目标单位标签列表 | D11: √ | G11: 72
A12: 10 | B12: mSpell mPlatformSpellInfo mAvatarLevelRequired | C12: 展现化身所需等级 | D12: √ | E12: √ | G12: 75
A13: 11 | B13: mSpell mPlatformSpellInfo mSpellID | C13: 指令序号 | D13: √ | E13: √ | G13: 74
A14: 12 | B14: mSpell mPlatformSpellInfo mPlatformEnabled | C14: 可用性 | D14: √ | E14: √ | F14: FALSE | G14: 76
A15: 13 | B15: mSpell mPlatformSpellInfo mGameModes | C15: 适用游戏模式 | D15: √ | E15: √ | G15: 77
A16: 14 | B16: mSpell mCastRequirementsCaster | C16: 施法条件 | D16: √ | E16: √ | G16: 67
A17: 15 | B17: mSpell mCastRequirementsTarget | C17: 施法目标条件 | D17: √ | E17: √ | G17: 68
A18: 16 | B18: mSpell mAlternateName | C18: 指令别名 | D18: √ | E18: √ | G18: 8
A19: 17 | B19: mSpell mSpellTags | C19: 指令标签 | D19: √ | E19: √ | G19: 12
A20: 18 | B20: mSpell mEffectAmount | C20: 效应因子 | D20: √ | E20: √ | G20: 33
A21: 19 | B21: mSpell DataValues | C21: 数值 | D21: √ | E21: √ | G21: 34
A22: 20 | B22: mSpell DataValuesModeOverride | C22: 模式覆盖数值 | D22: √ | E22: √ | G22: 35
A23: 21 | B23: mSpell {b08bc498} | C23: 模式覆盖基础充能时间 | D23: √ | E23: √ | G23: 30
A24: 22 | B24: mSpell {f9c2333e} | C24: 模式覆盖基础冷却时间 | D24: √ | E24: √ | G24: 23
A25: 23 | B25: mSpell mSpellCalculations | C25: 数值计算 | D25: √ | E25: √ | G25: 36
A26: 24 | B26: mSpell mCoefficient | C26: 系数1 | D26: √ | E26: √ | G26: 38
... A33: 31 | B33: mSpell mKeywordWhenAcquired | C33: 获得技能时的关键字 | D33: √ | E33: √ | G33: 78
A34: 32 | B34: mSpell PassiveSpellAffectedByCooldown | C34: 被动技能冷却时间受技能急速影响 | D34: √ | E34: √ | F34: FALSE | G34: 24
A35: 33 | B35: mSpell ImgIconPath | C35: 缩略图路径 | D35: √ | E35: √ | G35: 242
A36: 34 | B36: mSpell mMinimapIconName | C36: 小地图缩略图路径 | D36: √ | E36: √ | G36: 244
A37: 35 | B37: mSpell mCastTime | C37: 施法时间 | D37: √ | E37: √ | G37: 52
A38: 36 | B38: mSpell {11704a2b} | D38: √ | G38: 83
A39: 37 | B39: mSpell {f26881a0} | D39: √ | G39: 84
A40: 38 | B40: mSpell mChannelDuration | C40: 引导持续时间 | D40: √ | E40: √ | G40: 53
A41: 39 | B41: mSpell cooldownTime | C41: 基础冷却时间 | D41: √ | E41: √ | G41: 20
A42: 40 | B42: mSpell Cooldown values | C42: 基础冷却时间值 | D42: √ | G42: 21
A43: 41 | B43: mSpell Cooldown {0a3e0478} | C43: 基础冷却时间值简化表示 | D43: √ | E43: √ | G43: 22
A44: 42 | B44: mSpell delayCastOffsetPercent | C44: 施法偏移百分比 | D44: √ | E44: √ | G44: 60
A45: 43 | B45: mSpell delayTotalTimePercent | C45: 施法总时间百分比 | D45: √ | E45: √ | G45: 61
A46: 44 | B46: mSpell mStartCooldown | C46: 冷却计时时间点 | D46: √ | E46: √ | G46: 26
A47: 45 | B47: mSpell mIsDelayedByCastLocked | C47: 施法锁定延迟 | D47: √ | E47: √ | F47: FALSE | G47: 66
A48: 46 | B48: mSpell mPreCastLockoutDeltaTime | C48: 施法前锁定状态时间 | D48: √ | E48: √ | G48: 62
A49: 47 | B49: mSpell mPreCastLockoutDeltaTimeData mSpellLockDeltaTimeCalculation | C49: 施法前锁定状态时间计算 | D49: √ | G49: 63
A50: 48 | B50: mSpell mPostCastLockoutDeltaTime | C50: 施法后锁定状态时间 | D50: √ | E50: √ | G50: 64
A51: 49 | B51: mSpell mCasterPositionEndOfCastUpdate | C51: 施法后更新施法者位置参数 | D51: √ | E51: √ | G51: 65
A52: 50 | B52: mSpell mCharacterPassiveBuffs | C52: 被动技能增益 | D52: √ | E52: √ | G52: 79
A53: 51 | B53: mSpell mChargeUpdateInterval | C53: 充能数更新间隔（秒） | D53: √ | E53: √ | G53: 73
A54: 52 | B54: mSpell mCancelChargeOnRecastTime | C54: 取消冲锋的再次施法冻结时间（秒） | D54: √ | E54: √ | G54: 80
A55: 53 | B55: mSpell mCastRangeGrowthMax | C55: 施法范围成长最大值 | D55: √ | E55: √ | G55: 46
A56: 54 | B56: mSpell mCastRangeGrowthStartTime | C56: 施法范围成长开始时间 | D56: √ | E56: √ | G56: 47
A57: 55 | B57: mSpell mCastRangeGrowthDuration | C57: 施法范围成长持续时间 | D57: √ | E57: √ | G57: 48
A58: 56 | B58: mSpell {48201b0d} | D58: √ | E58: √ | G58: 81
A59: 57 | B59: mSpell {f4ca428f} | D59: √ | E59: √ | G59: 82
A60: 58 | B60: mSpell mMaxAmmo | C60: 最大充能数 | D60: √ | E60: √ | G60: 27
A61: 59 | B61: mSpell mAmmoUsed | C61: 可用充能数 | D61: √ | E61: √ | G61: 28
A62: 60 | B62: mSpell mAmmoRechargeTime | C62: 基础充能时间 | D62: √ | E62: √ | G62: 29
A63: 61 | B63: mSpell mAmmoNotAffectedByCDR | C63: 充能时间不受冷却缩减影响 | D63: √ | E63: √ | F63: FALSE | G63: 31
A64: 62 | B64: mSpell mCostAlwaysShownInUI | C64: 总是显示技能消耗 | D64: √ | E64: √ | F64: FALSE | G64: 18
A65: 63 | B65: mSpell mCooldownNotAffectedByCDR | C65: 冷却时间不受冷却缩减影响 | D65: √ | E65: √ | F65: FALSE | G65: 25
A66: 64 | B66: mSpell mAmmoCountHiddenInUI | C66: 充能数隐藏 | D66: √ | E66: √ | F66: FALSE | G66: 32
A67: 65 | B67: mSpell cannotBeSuppressed | C67: 不受压制影响 | D67: √ | E67: √ | F67: FALSE | G67: 99
A68: 66 | B68: mSpell mCanTriggerChargeSpellWhileDisabled | C68: 受到限制效果时仍能触发冲锋技能 | D68: √ | E68: √ | F68: FALSE | G68: 91
A69: 67 | B69: mSpell canCastWhileDisabled | C69: 受到限制效果时仍能施法 | D69: √ | E69: √ | F69: FALSE | G69: 90
A70: 68 | B70: mSpell canCastOrQueueWhileCasting | C70: 施放其它技能时允许施法或进入施法队列 | D70: √ | E70: √ | F70: FALSE | G70: 100
A71: 69 | B71: mSpell mCantCancelWhileWindingUp | C71: 施法后无法取消 | D71: √ | E71: √ | F71: FALSE | G71: 94
A72: 70 | B72: mSpell mCantCancelWhileWindingUpTargetingChampion | C72: 对目标英雄施放后无法取消 | D72: √ | E72: √ | F72: FALSE | G72: 95
A73: 71 | B73: mSpell mCantCancelWhileChanneling | C73: 引导时无法取消 | D73: √ | E73: √ | F73: FALSE | G73: 96
A74: 72 | B74: mSpell cantCastWhileRooted | C74: 定身时无法施放 | D74: √ | E74: √ | F74: FALSE | G74: 92
... A90: 88 | B90: mSpell mUseChargeChanneling | C90: 引导时冲锋 | D90: √ | E90: √ | F90: FALSE | G90: 97
A91: 89 | B91: mSpell ShowChannelBarPerSpellLevelOverride | C91: 不同等级是否展示引导条 | D91: √ | E91: √ | G91: 105
A92: 90 | B92: mSpell castRangeUseBoundingBoxes | C92: 从边界框开始计算施法距离 | D92: √ | E92: √ | F92: FALSE | G92: 49
A93: 91 | B93: mSpell mCanMoveWhileChanneling | C93: 引导时可移动 | D93: √ | E93: √ | F93: FALSE | G93: 98
A94: 92 | B94: mSpell mDisableCastBar | C94: 禁用施法条 | D94: √ | E94: √ | F94: FALSE | G94: 58
A95: 93 | B95: mSpell mShowChannelBar | C95: 显示引导条 | D95: √ | E95: √ | F95: TRUE | G95: 59
A96: 94 | B96: mSpell alwaysSnapFacing | C96: 施法时立即转向 | D96: √ | E96: √ | F96: FALSE | G96: 69
A97: 95 | B97: mSpell useAnimatorFramerate | C97: 使用动画生成器帧率 | D97: √ | E97: √ | F97: FALSE | G97: 135
A98: 96 | B98: mSpell bHaveHitEffect | C98: 具有命中特效 | D98: √ | E98: √ | F98: FALSE | G98: 152
A99: 97 | B99: mSpell mOrientRadiusTextureFromPlayer | C99: 从玩家定义纹理半径 | D99: √ | E99: √ | F99: FALSE | G99: 137
A100: 98 | B100: mSpell bIsToggleSpell | C100: 开关型技能 | D100: √ | E100: √ | F100: FALSE | G100: 13
A101: 99 | B101: mSpell mDoNotNeedToFaceTarget | C101: 施法时不需要面向目标 | D101: √ | E101: √ | F101: FALSE | G101: 70
A102: 100 | B102: mSpell mNoWinddownIfCancelled | C102: 打断后不会触发技能结束效果 | D102: √ | E102: √ | F102: FALSE | G102: 118
A103: 101 | B103: mSpell mTurnSpeedScalar | C103: 转向速度标量 | D103: √ | E103: √ | G103: 139
A104: 102 | B104: mSpell mIgnoreRangeCheck | C104: 施法时不检查距离 | D104: √ | E104: √ | F104: FALSE | G104: 112
A105: 103 | B105: mSpell mUpdateRotationWhenCasting | C105: 施法时更新服务器轮转 | D105: √ | E105: √ | F105: FALSE | G105: 142
A106: 104 | B106: mSpell mPingableWhileDisabled | C106: 禁用时可标记 | D106: √ | E106: √ | F106: FALSE | G106: 93
A107: 105 | B107: mSpell mOverrideAttackTime mTotalAttackTimeSecs | C107: 覆盖攻击时间计算 | D107: √ | E107: √ | G107: 144
A108: 106 | B108: mSpell mOverrideAttackTime SetOverrideAttackDelay | C108: 启用攻击延迟覆盖 | D108: √ | E108: √ | F108: TRUE | G108: 143
A109: 107 | B109: mSpell mOverrideAttackTime mCastTimePercent | C109: 施放时间百分比 | D109: √ | E109: √ | G109: 145
A110: 108 | B110: mSpell mUseAutoattackCastTimeData mAutoattackCastTimeCalculation | C110: 自动攻击时间计算 | D110: √ | E110: √ | G110: 147
A111: 109 | B111: mSpell mUseAutoattackCastTimeData mUseCastTimeAsTotalTime | C111: 自动攻击时间作为总攻击时间 | D111: √ | E111: √ | F111: TRUE | G111: 148
A112: 110 | B112: mSpell mConsideredAsAutoAttack | C112: 视为自动攻击 | D112: √ | E112: √ | F112: FALSE | G112: 146
A113: 111 | B113: mSpell mIgnoreAnimContinueUntilCastFrame | C113: 动画直到施放帧时持续 | D113: √ | E113: √ | F113: FALSE | G113: 138
A114: 112 | B114: mSpell mHideRangeIndicatorWhenCasting | C114: 施法时隐藏距离指示器 | D114: √ | E114: √ | F114: FALSE | G114: 113
A115: 113 | B115: mSpell mDoesNotConsumeMana | C115: 不消耗法力值 | D115: √ | E115: √ | F115: FALSE | G115: 14
A116: 114 | B116: mSpell mLockedSpellOriginationCastID | C116: 激活时锁定技能施放起源ID | D116: √ | E116: √ | F116: FALSE | G116: 120
A117: 115 | B117: mSpell mDoesNotConsumeCooldown | C117: 不立即进入冷却时间 | D117: √ | E117: √ | F117: FALSE | G117: 119
A118: 116 | B118: mSpell mRollForCriticalHit | C118: 参与暴击概率计算 | D118: √ | E118: √ | F118: FALSE | G118: 121
A119: 117 | B119: mSpell mMinimapIconDisplayFlag | C119: 小地图缩略图显示旗标 | D119: √ | E119: √ | G119: 149
A120: 118 | B120: mSpell ShouldReceiveInputEvents | C120: 需要接收输入事件以保持 | D120: √ | E120: √ | F120: FALSE | G120: 122
A121: 119 | B121: mSpell castRange | C121: 施法范围 | D121: √ | E121: √ | G121: 42
...

Sheet summoner_spell_header
A1: Index | B1: Key | C1: Value | D1: DirectlyImport? | E1: Flexible | F1: defaultValue | G1: OutputOrder
A2: 0 | B2: key | C2: =_xlfn.LET(_xlpm.x,VLOOKUP($B2,spell_header!$B$2:$G$373,2,FALSE),IF(_xlpm.x="","",_xlpm.x)) -> 主键 | D2: =IF(VLOOKUP($B2,spell_header!$B$2:$G$373,3,FALSE)="√","√","") -> √ | E2: =IF(VLOOKUP($B2,spell_header!$B$2:$G$373,4,FALSE)="√","√","") | F2: =_xlfn.LET(_xlpm.x,VLOOKUP($B2,spell_header!$B$2:$G$373,5,FALSE),IF(_xlpm.x="","",_xlpm.x)) | G2: 0
A3: 1 | B3: ObjectName | C3: =_xlfn.LET(_xlpm.x,VLOOKUP($B3,spell_header!$B$2:$G$373,2,FALSE),IF(_xlpm.x="","",_xlpm.x)) -> 指令对象名称 | D3: =IF(VLOOKUP($B3,spell_header!$B$2:$G$373,3,FALSE)="√","√","") -> √ | E3: =IF(VLOOKUP($B3,spell_header!$B$2:$G$373,4,FALSE)="√","√","") | F3: =_xlfn.LET(_xlpm.x,VLOOKUP($B3,spell_header!$B$2:$G$373,5,FALSE),IF(_xlpm.x="","",_xlpm.x)) | G3: 1
A4: 2 | B4: mScriptName | C4: =_xlfn.LET(_xlpm.x,VLOOKUP($B4,spell_header!$B$2:$G$373,2,FALSE),IF(_xlpm.x="","",_xlpm.x)) -> 脚本名称 | D4: =IF(VLOOKUP($B4,spell_header!$B$2:$G$373,3,FALSE)="√","√","") -> √ | E4: =IF(VLOOKUP($B4,spell_header!$B$2:$G$373,4,FALSE)="√","√","") | F4: =_xlfn.LET(_xlpm.x,VLOOKUP($B4,spell_header!$B$2:$G$373,5,FALSE),IF(_xlpm.x="","",_xlpm.x)) | G4: 11
A5: 3 | B5: {34cdd819} | C5: =_xlfn.LET(_xlpm.x,VLOOKUP($B5,spell_header!$B$2:$G$373,2,FALSE),IF(_xlpm.x="","",_xlpm.x)) | D5: =IF(VLOOKUP($B5,spell_header!$B$2:$G$373,3,FALSE)="√","√","") -> √ | E5: =IF(VLOOKUP($B5,spell_header!$B$2:$G$373,4,FALSE)="√","√","") -> √ | F5: =_xlfn.LET(_xlpm.x,VLOOKUP($B5,spell_header!$B$2:$G$373,5,FALSE),IF(_xlpm.x="","",_xlpm.x)) | G5: 9
A6: 4 | B6: Script | C6: =_xlfn.LET(_xlpm.x,VLOOKUP($B6,spell_header!$B$2:$G$373,2,FALSE),IF(_xlpm.x="","",_xlpm.x)) -> 脚本主键 | D6: =IF(VLOOKUP($B6,spell_header!$B$2:$G$373,3,FALSE)="√","√","") -> √ | E6: =IF(VLOOKUP($B6,spell_header!$B$2:$G$373,4,FALSE)="√","√","") -> √ | F6: =_xlfn.LET(_xlpm.x,VLOOKUP($B6,spell_header!$B$2:$G$373,5,FALSE),IF(_xlpm.x="","",_xlpm.x)) | G6: 10
A7: 5 | B7: mSpell flags | C7: =_xlfn.LET(_xlpm.x,VLOOKUP($B7,spell_header!$B$2:$G$373,2,FALSE),IF(_xlpm.x="","",_xlpm.x)) -> 指令旗标 | D7: =IF(VLOOKUP($B7,spell_header!$B$2:$G$373,3,FALSE)="√","√","") -> √ | E7: =IF(VLOOKUP($B7,spell_header!$B$2:$G$373,4,FALSE)="√","√","") -> √ | F7: =_xlfn.LET(_xlpm.x,VLOOKUP($B7,spell_header!$B$2:$G$373,5,FALSE),IF(_xlpm.x="","",_xlpm.x)) | G7: 13
A8: 6 | B8: mSpell mAffectsTypeFlags | C8: =_xlfn.LET(_xlpm.x,VLOOKUP($B8,spell_header!$B$2:$G$373,2,FALSE),IF(_xlpm.x="","",_xlpm.x)) -> 作用目标类型旗标 | D8: =IF(VLOOKUP($B8,spell_header!$B$2:$G$373,3,FALSE)="√","√","") -> √ | E8: =IF(VLOOKUP($B8,spell_header!$B$2:$G$373,4,FALSE)="√","√","") -> √ | F8: =_xlfn.LET(_xlpm.x,VLOOKUP($B8,spell_header!$B$2:$G$373,5,FALSE),IF(_xlpm.x="","",_xlpm.x)) | G8: 14
A9: 7 | B9: mSpell mAffectsStatusFlags | C9: =_xlfn.LET(_xlpm.x,VLOOKUP($B9,spell_header!$B$2:$G$373,2,FALSE),IF(_xlpm.x="","",_xlpm.x)) -> 作用状态旗标 | D9: =IF(VLOOKUP($B9,spell_header!$B$2:$G$373,3,FALSE)="√","√","") -> √ | E9: =IF(VLOOKUP($B9,spell_header!$B$2:$G$373,4,FALSE)="√","√","") -> √ | F9: =_xlfn.LET(_xlpm.x,VLOOKUP($B9,spell_header!$B$2:$G$373,5,FALSE),IF(_xlpm.x="","",_xlpm.x)) | G9: 15
A10: 8 | B10: mSpell mRequiredUnitTags mObjectTagList | C10: =_xlfn.LET(_xlpm.x,VLOOKUP($B10,spell_header!$B$2:$G$373,2,FALSE),IF(_xlpm.x="","",_xlpm.x)) -> 所需目标单位标签列表 | D10: =IF(VLOOKUP($B10,spell_header!$B$2:$G$373,3,FALSE)="√","√","") -> √ | E10: =IF(VLOOKUP($B10,spell_header!$B$2:$G$373,4,FALSE)="√","√","") | F10: =_xlfn.LET(_xlpm.x,VLOOKUP($B10,spell_header!$B$2:$G$373,5,FALSE),IF(_xlpm.x="","",_xlpm.x)) | G10: 75
A11: 9 | B11: mSpell mExcludedUnitTags mObjectTagList | C11: =_xlfn.LET(_xlpm.x,VLOOKUP($B11,spell_header!$B$2:$G$373,2,FALSE),IF(_xlpm.x="","",_xlpm.x)) -> 无效目标单位标签列表 | D11: =IF(VLOOKUP($B11,spell_header!$B$2:$G$373,3,FALSE)="√","√","") -> √ | E11: =IF(VLOOKUP($B11,spell_header!$B$2:$G$373,4,FALSE)="√","√","") | F11: =_xlfn.LET(_xlpm.x,VLOOKUP($B11,spell_header!$B$2:$G$373,5,FALSE),IF(_xlpm.x="","",_xlpm.x)) | G11: 76
A12: 10 | B12: mSpell mPlatformSpellInfo mAvatarLevelRequired | C12: =_xlfn.LET(_xlpm.x,VLOOKUP($B12,spell_header!$B$2:$G$373,2,FALSE),IF(_xlpm.x="","",_xlpm.x)) -> 展现化身所需等级 | D12: =IF(VLOOKUP($B12,spell_header!$B$2:$G$373,3,FALSE)="√","√","") -> √ | E12: =IF(VLOOKUP($B12,spell_header!$B$2:$G$373,4,FALSE)="√","√","") -> √ | F12: =_xlfn.LET(_xlpm.x,VLOOKUP($B12,spell_header!$B$2:$G$373,5,FALSE),IF(_xlpm.x="","",_xlpm.x)) | G12: 7
A13: 11 | B13: mSpell mPlatformSpellInfo mSpellID | C13: =_xlfn.LET(_xlpm.x,VLOOKUP($B13,spell_header!$B$2:$G$373,2,FALSE),IF(_xlpm.x="","",_xlpm.x)) -> 指令序号 | D13: =IF(VLOOKUP($B13,spell_header!$B$2:$G$373,3,FALSE)="√","√","") -> √ | E13: =IF(VLOOKUP($B13,spell_header!$B$2:$G$373,4,FALSE)="√","√","") -> √ | F13: =_xlfn.LET(_xlpm.x,VLOOKUP($B13,spell_header!$B$2:$G$373,5,FALSE),IF(_xlpm.x="","",_xlpm.x)) | G13: 2
... A373: 371 | B373: BotData {591f8423} | C373: =_xlfn.LET(_xlpm.x,VLOOKUP($B373,spell_header!$B$2:$G$373,2,FALSE),IF(_xlpm.x="","",_xlpm.x)) | D373: =IF(VLOOKUP($B373,spell_header!$B$2:$G$373,3,FALSE)="√","√","") -> √ | E373: =IF(VLOOKUP($B373,spell_header!$B$2:$G$373,4,FALSE)="√","√","") -> √ | F373: =_xlfn.LET(_xlpm.x,VLOOKUP($B373,spell_header!$B$2:$G$373,5,FALSE),IF(_xlpm.x="","",_xlpm.x)) | G373: 371

Sheet perkstyle_header
A1: Index | B1: Key | C1: Value | D1: DirectlyImport? | E1: Flexible | F1: defaultValue | G1: OutputOrder
A2: 0 | B2: key | C2: 主键 | D2: √ | G2: 0
A3: 1 | B3: mPerkStyleId | C3: 符文系序号 | D3: √ | G3: 1
A4: 2 | B4: mPerkStyleName | C4: 符文系代码 | D4: √ | G4: 2
A5: 3 | B5: mDisplayNameLocalizationKey | C5: 显示名键 | D5: √ | G5: 3
A6: 4 | B6: mTooltipNameLocalizationKey | C6: 简介键 | D6: √ | G6: 7
A7: 5 | B7: mDefaultPageLocalizationKey | C7: 默认符文页名称键 | D7: √ | G7: 71
A8: 6 | B8: mIconTextureName | C8: 图标纹理名称 | D8: √ | G8: 80
A9: 7 | B9: mIsAdvancedStyle | C9: 高级符文系 | D9: √ | E9: √ | F9: FALSE | G9: 6
A10: 8 | B10: mAllowedSubStyles | C10: 可用副系序号 | D10: √ | G10: 10
A11: 9 | B11: mSubStyleBonus | C11: 副系加成 | D11: √ | G11: 13
A12: 10 | B12: mDefaultSplash mStyle | C12: 默认插画符文系 | D12: √ | G12: 81
A13: 11 | B13: mDefaultSplash mPerk1 | C13: 默认插画符文1 | D13: √ | G13: 82
A14: 12 | B14: mDefaultSplash mPerk2 | C14: 默认插画符文2 | D14: √ | G14: 83
A15: 13 | B15: mDefaultPerksWhenSplashed | C15: 渲染插画时默认使用符文 | D15: √ | G15: 74
A16: 14 | B16: mDefaultStatModsPerSubStyle | C16: 搭配各副系时的默认属性符文 | D16: √ | G16: 46
A17: 15 | B17: mSlots | C17: 槽位 | D17: √ | G17: 17
A18: 16 | B18: mSlotlinks | C18: 槽位主键 | D18: √ | G18: 14
A19: 17 | B19: mScript mSpellScriptName | C19: 指令名称 | D19: √ | G19: 77
A20: 18 | B20: mScript mSpellScriptData | C20: 指令数据 | D20: √ | E20: √ | G20: 78
A21: 19 | B21: mScriptAsSubStyle | C21: 用作副系时的指令 | D21: √ | G21: 79
A22: 20 | B22: mStyleVFXResourceResolver resourceMap | C22: 视觉效果资源解析器映射字典 | D22: √ | E22: √ | G22: 84
A23: 21 | B23: mDisplayNameLocalizationKey_content_zh | C23: 显示名（中文） | G23: 4
A24: 22 | B24: mDisplayNameLocalizationKey_content_en | C24: 显示名（英文） | G24: 5
A25: 23 | B25: mTooltipNameLocalizationKey_content_zh | C25: 简介（中文） | G25: 8
A26: 24 | B26: mTooltipNameLocalizationKey_content_en | C26: 简介（英文） | G26: 9
A27: 25 | B27: mDefaultPageLocalizationKey_content_zh | C27: 默认符文页名称（中文） | G27: 72
A28: 26 | B28: mDefaultPageLocalizationKey_content_en | C28: 默认符文页名称（英文） | G28: 73
A29: 27 | B29: mAllowedSubStyles mDisplayNameLocalizationKey_contents_zh | C29: 可用副系名称（中文） | G29: 11
A30: 28 | B30: mAllowedSubStyles mDisplayNameLocalizationKey_contents_en | C30: 可用副系名称（英文） | G30: 12
A31: 29 | B31: mDefaultPerksWhenSplashed mDisplayNameLocalizationKey_contents_zh | C31: 渲染插画时默认使用符文名称（中文） | G31: 75
A32: 30 | B32: mDefaultPerksWhenSplashed mDisplayNameLocalizationKey_contents_en | C32: 渲染插画时默认使用符文名称（英文） | G32: 76
A33: 31 | B33: mDefaultStatModsPerSubStyle1 mStyleId | C33: 搭配各副系时的默认属性符文：副系1序号 | G33: 47
A34: 32 | B34: mDefaultStatModsPerSubStyle1 mPerks | C34: 搭配各副系时的默认属性符文：副系1属性符文 | G34: 50
... A86: 84 | B86: mSlotlinks mSlotLabelKey_contents_en | C86: 槽位标签（英文） | G86: 16

Sheet perk_header
A1: Index | B1: Key | C1: Value | D1: DirectlyImport? | E1: Flexible | F1: defaultValue | G1: OutputOrder
A2: 0 | B2: key | C2: 主键 | D2: √ | G2: 0
A3: 1 | B3: mPerkId | C3: 符文序号 | D3: √ | G3: 1
A4: 2 | B4: mPerkName | C4: 符文代码 | D4: √ | G4: 2
A5: 3 | B5: mDisplayNameLocalizationKey | C5: 显示名键 | D5: √ | G5: 3
A6: 4 | B6: mTooltipNameLocalizationKey | C6: 简介键 | D6: √ | E6: √ | G6: 12
A7: 5 | B7: mPingTextLocalizationKey | C7: 标记文本键 | D7: √ | E7: √ | G7: 18
A8: 6 | B8: mShortDescLocalizationKey | C8: 简述键 | D8: √ | E8: √ | G8: 21
A9: 7 | B9: mLongDescLocalizationKey | C9: 详细信息键 | D9: √ | E9: √ | G9: 26
A10: 8 | B10: mEndOfGameStatDescriptions | C10: 赛后结算描述键 | D10: √ | E10: √ | G10: 31
A11: 9 | B11: mDisplayStatLocalizationKey | C11: 显示属性定位键 | D11: √ | E11: √ | G11: 17
A12: 10 | B12: mIconTextureName | C12: 图标纹理名称 | D12: √ | G12: 40
A13: 11 | B13: mStackable | C13: 可叠加 | D13: √ | E13: √ | F13: FALSE | G13: 10
A14: 12 | B14: mEnabled | C14: 可用性 | D14: √ | E14: √ | F14: TRUE | G14: 9
A15: 13 | B15: mScript mSpellScriptName | C15: 指令名称 | D15: √ | G15: 36
A16: 14 | B16: mScript mSpellScriptData | C16: 指令数据 | G16: 37
A17: 15 | B17: mBuffs | C17: 增益信息 | D17: √ | E17: √ | G17: 38
A18: 16 | B18: mVFXResourceResolver resourceMap | C18: 视觉效果资源解析器映射字典 | D18: √ | E18: √ | G18: 41
A19: 17 | B19: mSummonerPerkReplacements mReplacements | C19: 召唤师符文替换 | D19: √ | E19: √ | G19: 34
A20: 18 | B20: mDefault | C20: 默认符文 | D20: √ | E20: √ | F20: FALSE | G20: 11
A21: 19 | B21: mCharacters | C21: 相关角色 | D21: √ | E21: √ | G21: 35
A22: 20 | B22: mMajorChangePatchVersion | C22: 主要变更版本号 | D22: √ | E22: √ | G22: 39
A23: 21 | B23: mDisplayNameLocalizationKey_content_zh | C23: 显示名（中文） | G23: 4
A24: 22 | B24: mDisplayNameLocalizationKey_content_en | C24: 显示名（英文） | G24: 5
A25: 23 | B25: mTooltipNameLocalizationKey_content_zh | C25: 简介（中文） | G25: 13
A26: 24 | B26: mTooltipNameLocalizationKey_content_en | C26: 简介（英文） | G26: 15
A27: 25 | B27: mTooltipNameLocalizationKey_content_zh_burn | C27: 简介（中文/数值转换） | G27: 14
A28: 26 | B28: mTooltipNameLocalizationKey_content_en_burn | C28: 简介（英文/数值转换） | G28: 16
A29: 27 | B29: mPingTextLocalizationKey_content_zh | C29: 标记文本（中文） | G29: 19
A30: 28 | B30: mPingTextLocalizationKey_content_en | C30: 标记文本（英文） | G30: 20
A31: 29 | B31: mShortDescLocalizationKey_content_zh | C31: 简述（中文） | G31: 22
A32: 30 | B32: mShortDescLocalizationKey_content_en | C32: 简述（英文） | G32: 24
A33: 31 | B33: mShortDescLocalizationKey_content_zh_burn | C33: 简述（中文/数值转换） | G33: 23
A34: 32 | B34: mShortDescLocalizationKey_content_en_burn | C34: 简述（英文/数值转换） | G34: 25
... A40: 38 | B40: mEndOfGameStatDescriptions_contents_en | C40: 赛后结算描述（英文） | G40: 33
A41: 39 | B41: belonging_perkstyle_key | C41: 所属符文系主键
A42: 40 | B42: belonging_perkstyle mDisplayNameLocalizationKey_content_zh | C42: 所属符文系显示名（中文） | G42: 6
A43: 41 | B43: belonging_perkstyle mDisplayNameLocalizationKey_content_en | C43: 所属符文系显示名（英文） | G43: 7
A44: 42 | B44: belonging_perkstyle_slotIndex | C44: 所属符文系槽位序号 | G44: 8

Sheet champion_header
A1: Index | B1: Key | C1: Value | D1: DirectlyImport? | E1: Flexible1 | F1: Flexible2 | G1: defaultValue | H1: OutputOrder1 (champion; before v16.5) | I1: OutputOrder2 (character; before v16.5) | J1: OutputOrder3 (champion; after v16.5) | K1: OutputOrder4 (character; after v16.5)
A2: 0 | B2: key | C2: 主键 | D2: √ | H2: 0 | I2: 0 | J2: 0 | K2: 0
A3: 1 | B3: modeFolder | C3: 游戏模式文件夹 | E3: √ | F3: √ | H3: 1 | I3: 1 | J3: 1 | K3: 1
A4: 2 | B4: mCharacterName | C4: 角色名称 | D4: √ | H4: 2 | I4: 2 | J4: 2 | K4: 2
A5: 3 | B5: mFallbackCharacterName | C5: 备用名称 | D5: √ | E5: √ | F5: √ | H5: 6 | I5: 6 | J5: 6 | K5: 6
A6: 4 | B6: PackmanagerData | C6: 跟随者数据 | D6: √ | E6: √ | F6: √ | H6: 143 | I6: 143 | J6: 143 | K6: 143
A7: 5 | B7: {dd661aab} | C7: 冲刺配置 | D7: √ | E7: √ | F7: √ | H7: 192 | I7: 192 | J7: 192 | K7: 192
A8: 6 | B8: evolutionData | C8: 技能进化数据 | D8: √ | E8: √ | F8: √ | H8: 193 | I8: 193 | J8: 193 | K8: 193
A9: 7 | B9: useableData | C9: 可用数据 | D9: √ | F9: √ | H9: 157 | I9: 157 | J9: 157 | K9: 157
A10: 8 | B10: baseHP | C10: 基础生命值 | D10: √ | F10: √ | H10: 51 | I10: 51
A11: 9 | B11: hpPerLevel | C11: 成长生命值 | D11: √ | F11: √ | H11: 52 | I11: 52
A12: 10 | B12: baseStaticHPRegen | C12: 基础生命回复 | D12: √ | E12: √ | F12: √ | H12: 63 | I12: 63
A13: 11 | B13: hpRegenPerLevel | C13: 生命回复成长 | D13: √ | E13: √ | F13: √ | H13: 64 | I13: 64
A14: 12 | B14: highlightHealthbarIcons | C14: 高亮生命槽 | D14: √ | E14: √ | F14: √ | G14: FALSE | H14: 110 | I14: 110 | J14: 110 | K14: 110
A15: 13 | B15: healthBarHeight | C15: 血条高度 | D15: √ | E15: √ | F15: √ | H15: 115 | I15: 115 | J15: 115 | K15: 115
A16: 14 | B16: selfChampSpecificHealthSuffix | C16: 己方视角下的英雄生命槽颜色 | D16: √ | E16: √ | F16: √ | H16: 111 | I16: 111 | J16: 111 | K16: 111
A17: 15 | B17: selfCBChampSpecificHealthSuffix | C17: 己方色盲视角下的英雄生命槽颜色 | D17: √ | E17: √ | F17: √ | H17: 112 | I17: 112 | J17: 112 | K17: 112
A18: 16 | B18: allyChampSpecificHealthSuffix | C18: 友方视角下的英雄生命槽颜色 | D18: √ | E18: √ | F18: √ | H18: 113 | I18: 113 | J18: 113 | K18: 113
A19: 17 | B19: enemyChampSpecificHealthSuffix | C19: 敌方视角下的英雄生命槽颜色 | D19: √ | E19: √ | F19: √ | H19: 114 | I19: 114 | J19: 114 | K19: 114
A20: 18 | B20: healthBarFullParallax | C20: 生命槽使用完整视差效果 | D20: √ | F20: √ | G20: FALSE | H20: 116 | I20: 116 | J20: 116 | K20: 116
A21: 19 | B21: primaryAbilityResource | C21: 主要施法资源 | D21: √ | F21: √ | H21: 15 | I21: 15 | J21: 15 | K21: 15
A22: 20 | B22: secondaryAbilityResource | C22: 次要施法资源 | D22: √ | E22: √ | F22: √ | H22: 28 | I22: 28 | J22: 28 | K22: 28
A23: 21 | B23: baseDamage | C23: 基础攻击力 | D23: √ | F23: √ | H23: 53 | I23: 53
A24: 22 | B24: damagePerLevel | C24: 成长攻击力 | D24: √ | E24: √ | F24: √ | H24: 54 | I24: 54
A25: 23 | B25: baseArmor | C25: 基础护甲 | D25: √ | F25: √ | H25: 55 | I25: 55
A26: 24 | B26: armorPerLevel | C26: 成长护甲 | D26: √ | E26: √ | F26: √ | H26: 56 | I26: 56
A27: 25 | B27: critPerLevel | C27: 成长暴击几率 | D27: √ | F27: √ | H27: 67 | I27: 67 | J27: 67 | K27: 67
A28: 26 | B28: baseSpellBlock | C28: 基础魔法抗性 | D28: √ | F28: √ | H28: 57 | I28: 57
A29: 27 | B29: baseCritChance | C29: 基础暴击几率 | D29: √ | F29: √ | H29: 66 | I29: 66 | J29: 66 | K29: 66
A30: 28 | B30: spellBlockPerLevel | C30: 成长魔法抗性 | D30: √ | E30: √ | F30: √ | H30: 58 | I30: 58
A31: 29 | B31: critDamageMultiplier | C31: 暴击伤害修正率 | D31: √ | E31: √ | F31: √ | H31: 68 | I31: 68 | J31: 68 | K31: 68
A32: 30 | B32: baseMoveSpeed | C32: 基础移动速度 | D32: √ | F32: √ | H32: 62 | I32: 62
A33: 31 | B33: RotationSmoothing | C33: 模型旋转平滑度 | D33: √ | F33: √ | H33: 141 | I33: 141 | J33: 141 | K33: 141
A34: 32 | B34: attackRange | C34: 攻击距离 | D34: √ | F34: √ | H34: 65 | I34: 65
A35: 33 | B35: attackSpeed | C35: 基础攻击速度 | D35: √ | F35: √ | H35: 59 | I35: 59
A36: 34 | B36: attackSpeedRatio | C36: 攻击速度收益率 | D36: √ | F36: √ | H36: 61 | I36: 61
A37: 35 | B37: attackSpeedPerLevel | C37: 成长攻击速度 | D37: √ | E37: √ | F37: √ | H37: 60 | I37: 60
A38: 36 | B38: TreatAutoAttacksAsNormalSpells | C38: 自动攻击视为技能配置 | D38: √ | E38: √ | F38: √ | H38: 137 | I38: 137 | J38: 137 | K38: 137
A39: 37 | B39: mAdaptiveForceToAbilityPowerWeight | C39: 适应之力转法强比例 | D39: √ | E39: √ | F39: √ | H39: 69 | I39: 69 | J39: 69 | K39: 69
A40: 38 | B40: acquisitionRange | C40: 索敌范围半径 | D40: √ | E40: √ | F40: √ | H40: 121 | I40: 121 | J40: 121 | K40: 121
A41: 39 | B41: basicAttack | C41: 普通攻击动作参数 | D41: √ | F41: √ | H41: 126 | I41: 126 | J41: 126 | K41: 126
A42: 40 | B42: extraAttacks | C42: 其它攻击动作参数 | D42: √ | E42: √ | F42: √ | H42: 134 | I42: 134 | J42: 134 | K42: 134
A43: 41 | B43: critAttacks | C43: 暴击动作参数 | D43: √ | E43: √ | F43: √ | H43: 135 | I43: 135 | J43: 135 | K43: 135
A44: 42 | B44: expGivenOnDeath | C44: 阵亡时获取经验值 | D44: √ | E44: √ | F44: √ | H44: 107 | I44: 107 | J44: 107 | K44: 107
A45: 43 | B45: goldGivenOnDeath | C45: 阵亡时获取金币 | D45: √ | E45: √ | F45: √ | H45: 108 | I45: 108 | J45: 108 | K45: 108
A46: 44 | B46: deathEventListeningRadius | C46: 死亡事件监听范围半径 | D46: √ | E46: √ | F46: √ | H46: 122 | I46: 122 | J46: 122 | K46: 122
A47: 45 | B47: spellNames | C47: 技能指令名称列表 | D47: √ | F47: √ | H47: 181 | I47: 181 | J47: 181 | K47: 181
A48: 46 | B48: spells | C48: 技能指令代码列表 | D48: √ | F48: √ | H48: 182 | I48: 182 | J48: 182 | K48: 182
A49: 47 | B49: extraSpells | C49: 其它指令代码列表 | D49: √ | E49: √ | F49: √ | H49: 189 | I49: 189 | J49: 189 | K49: 189
A50: 48 | B50: {c1984296} | C50: 更多指令代码列表 | D50: √ | E50: √ | F50: √ | H50: 190 | I50: 190 | J50: 190 | K50: 190
A51: 49 | B51: mAbilities | C51: 技能键列表 | D51: √ | F51: √ | H51: 177 | I51: 177 | J51: 177 | K51: 177
A52: 50 | B52: criticalAttack | C52: 暴击指令键 | D52: √ | E52: √ | F52: √ | H52: 136 | I52: 136 | J52: 136 | K52: 136
A53: 51 | B53: passiveName | C53: 被动技能名称键 | D53: √ | E53: √ | F53: √ | H53: 162 | I53: 162 | J53: 162 | K53: 162
A54: 52 | B54: passiveLuaName | C54: 被动技能脚本名 | D54: √ | E54: √ | F54: √ | H54: 165 | I54: 165 | J54: 165 | K54: 165
A55: 53 | B55: passiveToolTip | C55: 被动技能描述文本键 | D55: √ | E55: √ | F55: √ | H55: 170 | I55: 170 | J55: 170 | K55: 170
A56: 54 | B56: passiveRange | C56: 被动技能范围 | D56: √ | E56: √ | F56: √ | H56: 166 | I56: 166 | J56: 166 | K56: 166
A57: 55 | B57: passiveSpell | C57: 被动技能指令代码 | D57: √ | E57: √ | F57: √ | H57: 168 | I57: 168 | J57: 168 | K57: 168
A58: 56 | B58: passive1IconName | C58: 被动技能图标1路径 | D58: √ | F58: √ | H58: 176 | I58: 176 | J58: 176 | K58: 176
A59: 57 | B59: perceptionBubbleRadius | C59: 感知气泡半径 | D59: √ | F59: √ | H59: 124 | I59: 124 | J59: 124 | K59: 124
A60: 58 | B60: significance | C60: 选取优先级系数 | D60: √ | F60: √ | H60: 125 | I60: 125 | J60: 125 | K60: 125
A61: 59 | B61: friendlyTooltip | C61: 友军说明文本键 | D61: √ | E61: √ | F61: √ | H61: 207 | I61: 207 | J61: 207 | K61: 207
A62: 60 | B62: enemyTooltip | C62: 敌军说明文本键 | D62: √ | E62: √ | F62: √ | H62: 210 | I62: 210 | J62: 210 | K62: 210
A63: 61 | B63: minimapIconOverride | C63: 小地图图标重载名称 | D63: √ | F63: √ | H63: 7 | I63: 7 | J63: 7 | K63: 7
A64: 62 | B64: name | C64: 显示名键 | D64: √ | F64: √ | H64: 3 | I64: 3 | J64: 3 | K64: 3
A65: 63 | B65: silhouetteAttachmentAnim | C65: 附身轮廓动画名称 | D65: √ | E65: √ | F65: √ | H65: 139 | I65: 139 | J65: 139 | K65: 139
A66: 64 | B66: parName | C66: 次要施法资源名称键 | D66: √ | E66: √ | F66: √ | H66: 48 | I66: 48 | J66: 48 | K66: 48
A67: 65 | B67: weaponMaterials | C67: 武器材料 | D67: √ | E67: √ | F67: √ | H67: 138 | I67: 138 | J67: 138 | K67: 138
A68: 66 | B68: outlineBBoxExpansion | C68: 轮廓扩展半径 | D68: √ | E68: √ | F68: √ | H68: 123 | I68: 123 | J68: 123 | K68: 123
A69: 67 | B69: charAudioNameOverride | C69: 英雄语音覆盖代码 | D69: √ | E69: √ | F69: √ | H69: 191 | I69: 191 | J69: 191 | K69: 191
A70: 68 | B70: mUseCCAnimations | C70: 移动受损动画已激活 | D70: √ | E70: √ | F70: √ | G70: FALSE | H70: 140 | I70: 140 | J70: 140 | K70: 140
A71: 69 | B71: selectionHeight | C71: 鼠标指针选择高度 | D71: √ | F71: √ | H71: 117 | I71: 117 | J71: 117 | K71: 117
A72: 70 | B72: selectionRadius | C72: 鼠标指针选择半径 | D72: √ | F72: √ | H72: 118 | I72: 118 | J72: 118 | K72: 118
A73: 71 | B73: pathfindingCollisionRadius | C73: 寻路碰撞体积半径 | D73: √ | F73: √ | H73: 119 | I73: 119 | J73: 119 | K73: 119
A74: 72 | B74: overrideGameplayCollisionRadius | C74: 特定条件覆盖碰撞体积半径 | D74: √ | E74: √ | F74: √ | H74: 120 | I74: 120 | J74: 120 | K74: 120
A75: 73 | B75: unitTagsString | C75: 单位类型标签字符串 | D75: √ | F75: √ | H75: 13 | I75: 13 | J75: 13 | K75: 13
A76: 74 | B76: friendlyUxOverrideTeam | C76: 友方界面队伍取值 | D76: √ | E76: √ | F76: √ | H76: 213 | I76: 213 | J76: 213 | K76: 213
A77: 75 | B77: friendlyUxOverrideIncludeTagsString | C77: 友方界面队伍包含字符串 | D77: √ | E77: √ | F77: √ | H77: 214 | I77: 214 | J77: 214 | K77: 214
A78: 76 | B78: friendlyUxOverrideExcludeTagsString | C78: 友方界面队伍不包含字符串 | D78: √ | E78: √ | F78: √ | H78: 215 | I78: 215 | J78: 215 | K78: 215
A79: 77 | B79: mEducationToolData | C79: 教程配置 | D79: √ | E79: √ | F79: √ | H79: 204 | I79: 204 | J79: 204 | K79: 204
A80: 78 | B80: mAbilitySlotCC | C80: 技能槽位控制效果分类变量 | D80: √ | E80: √ | F80: √ | H80: 178 | I80: 178 | J80: 178 | K80: 178
A81: 79 | B81: characterToolData | C81: 英雄说明 | D81: √ | F81: √ | H81: 71 | I81: 71 | J81: 71 | K81: 71
A82: 80 | B82: platformEnabled | C82: 大区可用性 | D82: √ | F82: √ | G82: FALSE | H82: 9 | I82: 9 | J82: 9 | K82: 9
A83: 81 | B83: spellLevelUpInfo | C83: 技能升级信息 | D83: √ | E83: √ | F83: √ | H83: 179 | I83: 179 | J83: 179 | K83: 179
A84: 82 | B84: RecSpellRankUpInfolist | C84: 推荐技能加点顺序列表 | D84: √ | E84: √ | F84: √ | H84: 180 | I84: 180 | J84: 180 | K84: 180
A85: 83 | B85: useRiotRelationships | C85: 采用新版设计理念 | D85: √ | E85: √ | F85: √ | G85: FALSE | H85: 142 | I85: 142 | J85: 142 | K85: 142
A86: 84 | B86: flags | C86: 旗标 | D86: √ | E86: √ | F86: √ | H86: 14 | I86: 14 | J86: 14 | K86: 14
A87: 85 | B87: purchaseIdentities | C87: 购买装备具备特质 | D87: √ | F87: √ | H87: 109 | I87: 109 | J87: 109 | K87: 109
A88: 86 | B88: mPreferredPerkStyle | C88: 推荐符文主系 | D88: √ | F88: √ | H88: 105 | I88: 105 | J88: 105 | K88: 105
A89: 87 | B89: mCharacterCalculations | C89: 英雄数据计算 | D89: √ | E89: √ | F89: √ | H89: 216 | I89: 216 | J89: 216 | K89: 216
A90: 88 | B90: mPerkReplacements | C90: 符文替换信息 | D90: √ | E90: √ | F90: √ | H90: 106 | I90: 106 | J90: 106 | K90: 106
A91: 89 | B91: mCharacterPassiveSpell | C91: 被动技能指令键 | D91: √ | F91: √ | H91: 167 | I91: 167 | J91: 167 | K91: 167
A92: 90 | B92: mCharacterPassiveBuffs | C92: 被动技能增益信息 | D92: √ | F92: √ | H92: 175 | I92: 175 | J92: 175 | K92: 175
A93: 91 | B93: {6854087e} | C93: 游戏模式数据覆盖 | D93: √ | E93: √ | F93: √ | H93: 70 | I93: 70 | J93: 70 | K93: 70
A94: 92 | B94: {c5c48b41} | D94: √ | E94: √ | F94: √ | H94: 217 | I94: 217 | J94: 217 | K94: 217
A95: 93 | B95: tier | C95: 卡费（仅云顶之弈） | D95: √ | F95: √ | I95: 221 | K95: 221
A96: 94 | B96: NumToCombine | C96: 升星所需单位数量（仅云顶之弈） | D96: √ | F96: √ | I96: 222 | K96: 222
A97: 95 | B97: BoardCountContribution | C97: 占用出战单位数（仅云顶之弈） | D97: √ | F97: √ | I97: 223 | K97: 223
A98: 96 | B98: mLinkedTraits | C98: 相关羁绊信息（仅云顶之弈） | D98: √ | F98: √ | I98: 224 | K98: 224
A99: 97 | B99: CharacterRole | C99: 角色定位（仅云顶之弈） | D99: √ | F99: √ | I99: 225 | K99: 225
A100: 98 | B100: mMoveInterval | C100: 移动间隔（秒）（仅云顶之弈） | D100: √ | F100: √ | I100: 226 | K100: 226
...

Sheet champion_spell_header
A1: Index | B1: Key | C1: Value | D1: DirectlyImport? | E1: Flexible | F1: defaultValue | G1: OutputOrder
A2: 0 | B2: mCharacterName | C2: 角色名称 | G2: 2
A3: 1 | B3: isRootSpell | C3: 根技能 | G3: 8
A4: 2 | B4: rootAbility_key | C4: 所属技能键 | D4: √ | G4: 7
A5: 3 | B5: rootAbility_mLifetimeManuallyManaged | C5: 所属技能的持续时间可控制 | E5: √ | F5: FALSE | G5: 12
A6: 4 | B6: rootAbility_mName | C6: 所属技能名称 | G6: 9
A7: 5 | B7: rootAbility_mType | C7: 所属技能类型 | E7: √ | G7: 10
A8: 6 | B8: rootAbility_AbilityTraits | C8: 所属技能特征旗标 | E8: √ | G8: 11
A9: 7 | B9: spellHotKey | C9: 技能热键 | G9: 3
A10: 8 | B10: key | C10: =_xlfn.LET(_xlpm.x,VLOOKUP($B10,spell_header!$B$2:$G$373,2,FALSE),IF(_xlpm.x="","",_xlpm.x)) -> 主键 | D10: =IF(VLOOKUP($B10,spell_header!$B$2:$G$373,3,FALSE)="√","√","") -> √ | E10: =IF(VLOOKUP($B10,spell_header!$B$2:$G$373,4,FALSE)="√","√","") | F10: =_xlfn.LET(_xlpm.x,VLOOKUP($B10,spell_header!$B$2:$G$373,5,FALSE),IF(_xlpm.x="","",_xlpm.x)) | G10: 0
A11: 9 | B11: ObjectName | C11: =_xlfn.LET(_xlpm.x,VLOOKUP($B11,spell_header!$B$2:$G$373,2,FALSE),IF(_xlpm.x="","",_xlpm.x)) -> 指令对象名称 | D11: =IF(VLOOKUP($B11,spell_header!$B$2:$G$373,3,FALSE)="√","√","") -> √ | E11: =IF(VLOOKUP($B11,spell_header!$B$2:$G$373,4,FALSE)="√","√","") | F11: =_xlfn.LET(_xlpm.x,VLOOKUP($B11,spell_header!$B$2:$G$373,5,FALSE),IF(_xlpm.x="","",_xlpm.x)) | G11: 1
A12: 10 | B12: mScriptName | C12: =_xlfn.LET(_xlpm.x,VLOOKUP($B12,spell_header!$B$2:$G$373,2,FALSE),IF(_xlpm.x="","",_xlpm.x)) -> 脚本名称 | D12: =IF(VLOOKUP($B12,spell_header!$B$2:$G$373,3,FALSE)="√","√","") -> √ | E12: =IF(VLOOKUP($B12,spell_header!$B$2:$G$373,4,FALSE)="√","√","") | F12: =_xlfn.LET(_xlpm.x,VLOOKUP($B12,spell_header!$B$2:$G$373,5,FALSE),IF(_xlpm.x="","",_xlpm.x)) | G12: 15
A13: 11 | B13: {34cdd819} | C13: =_xlfn.LET(_xlpm.x,VLOOKUP($B13,spell_header!$B$2:$G$373,2,FALSE),IF(_xlpm.x="","",_xlpm.x)) | D13: =IF(VLOOKUP($B13,spell_header!$B$2:$G$373,3,FALSE)="√","√","") -> √ | E13: =IF(VLOOKUP($B13,spell_header!$B$2:$G$373,4,FALSE)="√","√","") -> √ | F13: =_xlfn.LET(_xlpm.x,VLOOKUP($B13,spell_header!$B$2:$G$373,5,FALSE),IF(_xlpm.x="","",_xlpm.x)) | G13: 13
A14: 12 | B14: Script | C14: =_xlfn.LET(_xlpm.x,VLOOKUP($B14,spell_header!$B$2:$G$373,2,FALSE),IF(_xlpm.x="","",_xlpm.x)) -> 脚本主键 | D14: =IF(VLOOKUP($B14,spell_header!$B$2:$G$373,3,FALSE)="√","√","") -> √ | E14: =IF(VLOOKUP($B14,spell_header!$B$2:$G$373,4,FALSE)="√","√","") -> √ | F14: =_xlfn.LET(_xlpm.x,VLOOKUP($B14,spell_header!$B$2:$G$373,5,FALSE),IF(_xlpm.x="","",_xlpm.x)) | G14: 14
A15: 13 | B15: mSpell flags | C15: =_xlfn.LET(_xlpm.x,VLOOKUP($B15,spell_header!$B$2:$G$373,2,FALSE),IF(_xlpm.x="","",_xlpm.x)) -> 指令旗标 | D15: =IF(VLOOKUP($B15,spell_header!$B$2:$G$373,3,FALSE)="√","√","") -> √ | E15: =IF(VLOOKUP($B15,spell_header!$B$2:$G$373,4,FALSE)="√","√","") -> √ | F15: =_xlfn.LET(_xlpm.x,VLOOKUP($B15,spell_header!$B$2:$G$373,5,FALSE),IF(_xlpm.x="","",_xlpm.x)) | G15: 17
A16: 14 | B16: mSpell mAffectsTypeFlags | C16: =_xlfn.LET(_xlpm.x,VLOOKUP($B16,spell_header!$B$2:$G$373,2,FALSE),IF(_xlpm.x="","",_xlpm.x)) -> 作用目标类型旗标 | D16: =IF(VLOOKUP($B16,spell_header!$B$2:$G$373,3,FALSE)="√","√","") -> √ | E16: =IF(VLOOKUP($B16,spell_header!$B$2:$G$373,4,FALSE)="√","√","") -> √ | F16: =_xlfn.LET(_xlpm.x,VLOOKUP($B16,spell_header!$B$2:$G$373,5,FALSE),IF(_xlpm.x="","",_xlpm.x)) | G16: 18
A17: 15 | B17: mSpell mAffectsStatusFlags | C17: =_xlfn.LET(_xlpm.x,VLOOKUP($B17,spell_header!$B$2:$G$373,2,FALSE),IF(_xlpm.x="","",_xlpm.x)) -> 作用状态旗标 | D17: =IF(VLOOKUP($B17,spell_header!$B$2:$G$373,3,FALSE)="√","√","") -> √ | E17: =IF(VLOOKUP($B17,spell_header!$B$2:$G$373,4,FALSE)="√","√","") -> √ | F17: =_xlfn.LET(_xlpm.x,VLOOKUP($B17,spell_header!$B$2:$G$373,5,FALSE),IF(_xlpm.x="","",_xlpm.x)) | G17: 19
A18: 16 | B18: mSpell mRequiredUnitTags mObjectTagList | C18: =_xlfn.LET(_xlpm.x,VLOOKUP($B18,spell_header!$B$2:$G$373,2,FALSE),IF(_xlpm.x="","",_xlpm.x)) -> 所需目标单位标签列表 | D18: =IF(VLOOKUP($B18,spell_header!$B$2:$G$373,3,FALSE)="√","√","") -> √ | E18: =IF(VLOOKUP($B18,spell_header!$B$2:$G$373,4,FALSE)="√","√","") | F18: =_xlfn.LET(_xlpm.x,VLOOKUP($B18,spell_header!$B$2:$G$373,5,FALSE),IF(_xlpm.x="","",_xlpm.x)) | G18: 79
A19: 17 | B19: mSpell mExcludedUnitTags mObjectTagList | C19: =_xlfn.LET(_xlpm.x,VLOOKUP($B19,spell_header!$B$2:$G$373,2,FALSE),IF(_xlpm.x="","",_xlpm.x)) -> 无效目标单位标签列表 | D19: =IF(VLOOKUP($B19,spell_header!$B$2:$G$373,3,FALSE)="√","√","") -> √ | E19: =IF(VLOOKUP($B19,spell_header!$B$2:$G$373,4,FALSE)="√","√","") | F19: =_xlfn.LET(_xlpm.x,VLOOKUP($B19,spell_header!$B$2:$G$373,5,FALSE),IF(_xlpm.x="","",_xlpm.x)) | G19: 80
A20: 18 | B20: mSpell mPlatformSpellInfo mAvatarLevelRequired | C20: =_xlfn.LET(_xlpm.x,VLOOKUP($B20,spell_header!$B$2:$G$373,2,FALSE),IF(_xlpm.x="","",_xlpm.x)) -> 展现化身所需等级 | D20: =IF(VLOOKUP($B20,spell_header!$B$2:$G$373,3,FALSE)="√","√","") -> √ | E20: =IF(VLOOKUP($B20,spell_header!$B$2:$G$373,4,FALSE)="√","√","") -> √ | F20: =_xlfn.LET(_xlpm.x,VLOOKUP($B20,spell_header!$B$2:$G$373,5,FALSE),IF(_xlpm.x="","",_xlpm.x)) | G20: 83
A21: 19 | B21: mSpell mPlatformSpellInfo mSpellID | C21: =_xlfn.LET(_xlpm.x,VLOOKUP($B21,spell_header!$B$2:$G$373,2,FALSE),IF(_xlpm.x="","",_xlpm.x)) -> 指令序号 | D21: =IF(VLOOKUP($B21,spell_header!$B$2:$G$373,3,FALSE)="√","√","") -> √ | E21: =IF(VLOOKUP($B21,spell_header!$B$2:$G$373,4,FALSE)="√","√","") -> √ | F21: =_xlfn.LET(_xlpm.x,VLOOKUP($B21,spell_header!$B$2:$G$373,5,FALSE),IF(_xlpm.x="","",_xlpm.x)) | G21: 82
... A381: 379 | B381: BotData {591f8423} | C381: =_xlfn.LET(_xlpm.x,VLOOKUP($B381,spell_header!$B$2:$G$373,2,FALSE),IF(_xlpm.x="","",_xlpm.x)) | D381: =IF(VLOOKUP($B381,spell_header!$B$2:$G$373,3,FALSE)="√","√","") -> √ | E381: =IF(VLOOKUP($B381,spell_header!$B$2:$G$373,4,FALSE)="√","√","") -> √ | F381: =_xlfn.LET(_xlpm.x,VLOOKUP($B381,spell_header!$B$2:$G$373,5,FALSE),IF(_xlpm.x="","",_xlpm.x)) | G381: 379

Sheet item_header
A1: Index | B1: Key | C1: Value | D1: DirectlyImport? | E1: Flexible | F1: defaultValue | G1: OutputOrder
A2: 0 | B2: key | C2: 主键 | D2: √ | G2: 0
A3: 1 | B3: spellName | C3: 施法事件名称 | D3: √ | E3: √ | G3: 8
A4: 2 | B4: mDisplayName | C4: 显示名键 | D4: √ | E4: √ | G4: 2
A5: 3 | B5: mRequiredPurchaseIdentities | C5: 购买所需条件 | D5: √ | E5: √ | G5: 49
A6: 4 | B6: mRequiredChampion | C6: 适用英雄 | D6: √ | E6: √ | G6: 50
A7: 5 | B7: mRequiredSpellName | C7: 所需指令名 | D7: √ | E7: √ | G7: 52
A8: 6 | B8: mDisabledDescriptionOverride | C8: 禁用信息重载 | D8: √ | E8: √ | G8: 56
A9: 7 | B9: mDeathRecapName | C9: 死亡回放代码 | D9: √ | E9: √ | G9: 5
A10: 8 | B10: mRequiredLevel | C10: 所需英雄等级 | D10: √ | E10: √ | G10: 51
A11: 9 | B11: itemID | C11: 装备序号 | D11: √ | G11: 1
A12: 10 | B12: maxStack | C12: 最大持有数量 | D12: √ | E12: √ | G12: 26
A13: 11 | B13: mItemGroups | C13: 装备分组 | D13: √ | G13: 45
A14: 12 | B14: mItemAdviceAttributes | C14: 装备推荐属性 | D14: √ | E14: √ | G14: 46
A15: 13 | B15: itemVOGroup | C15: 装备音效分组 | D15: √ | E15: √ | G15: 48
A16: 14 | B16: price | C16: 合成费用 | D16: √ | E16: √ | G16: 27
A17: 15 | B17: mRequiredBuffCurrencyCost | C17: 其它费用 | D17: √ | E17: √ | G17: 30
A18: 16 | B18: mItemCalloutPlayer | C18: 购买时弹出提示 | D18: √ | E18: √ | F18: FALSE | G18: 57
A19: 17 | B19: mRequiredBuffCurrencyName | C19: 其它货币类型 | D19: √ | E19: √ | G19: 29
A20: 18 | B20: RestrictedBuffName | C20: 限定增益名称 | D20: √ | E20: √ | G20: 58
A21: 19 | B21: consumed | C21: 消耗品 | D21: √ | E21: √ | F21: FALSE | G21: 7
A22: 20 | B22: usableInStore | C22: 商店中可用 | D22: √ | E22: √ | F22: FALSE | G22: 12
A23: 21 | B23: consumeOnAcquire | C23: 购买时消耗 | D23: √ | E23: √ | F23: FALSE | G23: 13
A24: 22 | B24: clickable | C24: 可单击使用 | D24: √ | E24: √ | F24: FALSE | G24: 6
A25: 23 | B25: mHiddenFromOpponents | C25: 对手不可见 | D25: √ | E25: √ | F25: FALSE | G25: 14
A26: 24 | B26: mItemCalloutSpectator | C26: 观战购买时弹出提示 | D26: √ | E26: √ | F26: FALSE | G26: 15
A27: 25 | B27: ShowCooldownVfxToAllies | C27: 友军可见冷却时间 | D27: √ | E27: √ | F27: TRUE | G27: 16
A28: 26 | B28: ShowCooldownInPings | C28: 可标记冷却时间 | D28: √ | E28: √ | F28: TRUE | G28: 17
A29: 27 | B29: mCanBeSold | C29: 可以售出 | D29: √ | E29: √ | F29: FALSE | G29: 10
A30: 28 | B30: specialRecipe | C30: 特殊合成材料序号 | D30: √ | E30: √ | G30: 31
A31: 29 | B31: epicness | C31: 稀有度指数 | D31: √ | E31: √ | G31: 41
A32: 30 | B32: SecondaryEpicness | C32: 次要稀有度指数 | D32: √ | E32: √ | G32: 43
A33: 31 | B33: sidegradeItemLinks | C33: 同级替换路径 | D33: √ | E33: √ | G33: 34
A34: 32 | B34: mEffectAmount | C34: 因子取值 | D34: √ | E34: √ | G34: 88
A35: 33 | B35: recipeItemLinks | C35: 合成路径 | D35: √ | E35: √ | G35: 23
A36: 34 | B36: requiredItemLinks | C36: 所需装备路径 | D36: √ | E36: √ | G36: 53
A37: 35 | B37: mScripts | C37: 指令 | D37: √ | E37: √ | G37: 9
A38: 36 | B38: mItemModifiers | C38: 装备调整策略 | D38: √ | E38: √ | G38: 90
A39: 37 | B39: mDataValues | C39: 数值 | D39: √ | E39: √ | G39: 91
A40: 38 | B40: mFlatAttackRangeMod | C40: 固定攻击距离 | D40: √ | E40: √ | G40: 85
A41: 39 | B41: mPercentArmorPenetrationMod | C41: 护甲穿透 | D41: √ | E41: √ | G41: 80
... A83: 81 | B83: LastMajorChangeMinorPatchVersion | C83: 装备效果重做小版本 | D83: √ | E83: √ | G83: 97
A84: 82 | B84: mItemDataClient | C84: 客户端数据 | D84: √ | G84: 103
A85: 83 | B85: mVFXResourceResolver | C85: 视觉效果资源解析 | D85: √ | E85: √ | G85: 102
A86: 84 | B86: mDisplayName_content_zh | C86: 显示名（中文） | E86: √ | G86: 3
A87: 85 | B87: mDisplayName_content_en | C87: 显示名（英文） | E87: √ | G87: 4
A88: 86 | B88: mItemAdviceAttributes_content | C88: 装备推荐属性内容 | E88: √ | G88: 47
A89: 87 | B89: totalPrice | C89: 总费用 | G89: 28
A90: 88 | B90: specialRecipe_displayName_content_zh | C90: 特殊合成材料（中文） | E90: √ | G90: 32
A91: 89 | B91: specialRecipe_displayName_content_en | C91: 特殊合成材料（英文） | E91: √ | G91: 33
A92: 90 | B92: rarity | C92: 位阶 | E92: √ | G92: 42
A93: 91 | B93: secondaryRarity | C93: 次要位阶 | E93: √ | G93: 44
A94: 92 | B94: sidegradeItemNames_content_zh | C94: 同级替换装备（中文） | E94: √ | G94: 35
A95: 93 | B95: sidegradeItemNames_content_en | C95: 同级替换装备（英文） | E95: √ | G95: 36
A96: 94 | B96: recipeItemNames_content_zh | C96: 合成材料（中文） | E96: √ | G96: 24
A97: 95 | B97: recipeItemNames_content_en | C97: 合成材料（英文） | E97: √ | G97: 25
A98: 96 | B98: requiredItemNames_content_zh | C98: 所需材料（中文） | E98: √ | G98: 54
A99: 97 | B99: requiredItemNames_content_en | C99: 所需材料（英文） | E99: √ | G99: 55
A100: 98 | B100: mItemDataBuildNames_content_zh | C100: 同品类合成装备（中文） | E100: √ | G100: 38
A101: 99 | B101: mItemDataBuildNames_content_en | C101: 同品类合成装备（英文） | E101: √ | G101: 39
A102: 100 | B102: LastMajorChangeVersion | C102: 装备效果重做版本 | E102: √ | G102: 98
A103: 101 | B103: mItemDataAvailability mInStore | C103: 商店可见性 | D103: √ | E103: √ | F103: FALSE | G103: 19
A104: 102 | B104: mItemDataAvailability mForceLoad | C104: 强制加载 | D104: √ | E104: √ | F104: FALSE | G104: 20
A105: 103 | B105: mItemDataAvailability mHidefromAll | C105: 对所有人隐藏 | D105: √ | E105: √ | F105: FALSE | G105: 21
A106: 104 | B106: mItemDataClient mTooltipData mObjectName | C106: 详细信息对象名称 | D106: √ | E106: √ | G106: 104
A107: 105 | B107: mItemDataClient mTooltipData mFormat | C107: 详细信息格式 | D107: √ | E107: √ | G107: 105
A108: 106 | B108: mItemDataClient mTooltipData EnableExtendedTooltip | C108: 详细信息可展开 | D108: √ | E108: √ | F108: TRUE | G108: 106
A109: 107 | B109: mItemDataClient mTooltipData mLocKeys keyName | C109: 名称键 | D109: √ | E109: √ | G109: 124
A110: 108 | B110: mItemDataClient mTooltipData mLocKeys keyActive | C110: 主动效果键 | D110: √ | E110: √ | G110: 127
A111: 109 | B111: mItemDataClient mTooltipData mLocKeys keyTooltip | C111: 详细信息键 | D111: √ | E111: √ | G111: 132
A112: 110 | B112: mItemDataClient mTooltipData mLocKeys keyShopOnlyText | C112: 仅商店呈现文本键 | D112: √ | E112: √ | G112: 137
A113: 111 | B113: mItemDataClient mTooltipData mLocKeys keyFlavorText | C113: 旁白键 | D113: √ | E113: √ | G113: 142
A114: 112 | B114: mItemDataClient mTooltipData mLocKeys keyBrief | C114: 简介键 | D114: √ | E114: √ | G114: 145
A115: 113 | B115: mItemDataClient mTooltipData mLocKeys keySummary | C115: 总结键 | D115: √ | E115: √ | G115: 150
A116: 114 | B116: mItemDataClient mTooltipData mLocKeys keyInventoryOnlyText | C116: 仅装备栏呈现文本键 | D116: √ | E116: √ | G116: 155
A117: 115 | B117: mItemDataClient mTooltipData mLocKeys keyActiveInventory | C117: 主动效果动态描述键 | D117: √ | E117: √ | G117: 160
A118: 116 | B118: mItemDataClient mTooltipData mLocKeys keyColloquialism | C118: 检索键 | D118: √ | E118: √ | G118: 165
A119: 117 | B119: mItemDataClient mTooltipData mLocKeys keyTooltipInventory | C119: 装备栏详细信息键 | D119: √ | E119: √ | G119: 168
A120: 118 | B120: mItemDataClient mTooltipData mLocKeys keyTooltipInventoryExtended | C120: 装备栏展开详细信息键 | D120: √ | E120: √ | G120: 173
... A128: 126 | B128: mItemDataClient mTooltipData mLocKeys keyPrice | C128: 价格键 | D128: √ | E128: √ | G128: 211
A129: 127 | B129: mItemDataClient mTooltipData mLists Stats Elements | C129: 属性元素 | D129: √ | G129: 107
A130: 128 | B130: mItemDataClient mDescription | C130: 描述键 | D130: √ | E130: √ | G130: 109
A131: 129 | B131: mItemDataClient mDynamicTooltip | C131: 动态详细信息键 | D131: √ | E131: √ | G131: 114
A132: 130 | B132: mItemDataClient mShopTooltip | C132: 商店详细信息键 | D132: √ | E132: √ | G132: 119
A133: 131 | B133: mItemDataClient inventoryIcon | C133: 装备栏图标 | D133: √ | E133: √ | G133: 212
A134: 132 | B134: mItemDataClient InventoryIconSmall | C134: 装备栏小图标 | D134: √ | E134: √ | G134: 213
A135: 133 | B135: mItemDataClient InventoryIconLarge | C135: 装备栏大图标 | D135: √ | E135: √ | G135: 214
A136: 134 | B136: mItemDataClient epicness | C136: 客户端内稀有度指数 | D136: √ | E136: √ | G136: 215
A137: 135 | B137: mItemDataClient effectRadius | C137: 影响范围半径 | D137: √ | E137: √ | G137: 217
A138: 136 | B138: mItemDataClient InventoryIconMaterial | C138: 装备栏图标修饰材料 | D138: √ | E138: √ | G138: 218
A139: 137 | B139: mItemDataClient mFloatVarsDecimals | C139: 小数位数控制 | D139: √ | E139: √ | G139: 219
A140: 138 | B140: mItemDataClient mTooltipData mStatList | C140: 属性效果 | E140: √ | G140: 108
A141: 139 | B141: mItemDataClient mTooltipData mLocKeys keyName_content_zh | C141: 名称（中文） | E141: √ | G141: 125
A142: 140 | B142: mItemDataClient mTooltipData mLocKeys keyName_content_en | C142: 名称（英文） | E142: √ | G142: 126
A143: 141 | B143: mItemDataClient mTooltipData mLocKeys keyActive_content_zh | C143: 主动效果（中文） | E143: √ | G143: 128
A144: 142 | B144: mItemDataClient mTooltipData mLocKeys keyActive_content_zh_burn | C144: 主动效果（中文/数值转换） | E144: √ | G144: 129
A145: 143 | B145: mItemDataClient mTooltipData mLocKeys keyActive_content_en | C145: 主动效果（英文） | E145: √ | G145: 130
A146: 144 | B146: mItemDataClient mTooltipData mLocKeys keyActive_content_en_burn | C146: 主动效果（英文/数值转换） | E146: √ | G146: 131
A147: 145 | B147: mItemDataClient mTooltipData mLocKeys keyTooltip_content_zh | C147: 详细信息（中文） | E147: √ | G147: 133
A148: 146 | B148: mItemDataClient mTooltipData mLocKeys keyTooltip_content_zh_burn | C148: 详细信息（中文/数值转换） | E148: √ | G148: 134
...

Sheet itemGroup_header
A1: Index | B1: Key | C1: Value | D1: DirectlyImport? | E1: Flexible | F1: defaultValue | G1: OutputOrder
A2: 0 | B2: key | C2: 主键 | D2: √ | G2: 0
A3: 1 | B3: mItemGroupID | C3: 装备分组名称 | D3: √ | G3: 1
A4: 2 | B4: mItemModifiers | C4: 装备修饰方案 | D4: √ | E4: √ | G4: 3
A5: 3 | B5: mInventorySlotMin | C5: 装备栏最小槽位号 | D5: √ | E5: √ | G5: 4
A6: 4 | B6: mInventorySlotMax | C6: 装备栏最大槽位号 | D6: √ | E6: √ | G6: 5
A7: 5 | B7: mMaxGroupOwnable | C7: 组内最多持有装备数量 | D7: √ | E7: √ | G7: 2
A8: 6 | B8: {dbc029fa} | D8: √ | E8: √ | F8: FALSE | G8: 7
A9: 7 | B9: mPurchaseCooldown | C9: 连点预防间隔（秒） | D9: √ | E9: √ | G9: 6

Sheet itemModifier_header
A1: Index | B1: Key | C1: Value | D1: DirectlyImport? | E1: Flexible | F1: defaultValue | G1: OutputOrder
A2: 0 | B2: key | C2: 主键 | D2: √ | G2: 0
A3: 1 | B3: mItemModifierID | C3: 装备修饰名称 | D3: √ | G3: 1
A4: 2 | B4: mModifiedIfBuildsFromItem | C4: 合成构件包含以下装备时修饰 | D4: √ | E4: √ | G4: 18
A5: 3 | B5: mModifiedItem | C5: 修饰装备 | D5: √ | E5: √ | G5: 2
A6: 4 | B6: mDeltaMaxStacks | C6: 最大持有数量变化值 | D6: √ | E6: √ | G6: 10
A7: 5 | B7: mModifiedGroup | C7: 修饰装备分组 | D7: √ | E7: √ | G7: 5
A8: 6 | B8: mMaximumModifierInstancesToBeActive | C8: 最大生效实例数量 | D8: √ | E8: √ | G8: 11
A9: 7 | B9: {06d9d838} | C9: 修饰前的基础构件 | D9: √ | E9: √ | G9: 21
A10: 8 | B10: {917537a9} | C10: 修饰后的基础构件 | D10: √ | E10: √ | G10: 24
A11: 9 | B11: mModifierIsInheritedByOwnedParentItems | C11: 大件继承构件修饰 | D11: √ | E11: √ | F11: FALSE | G11: 7
A12: 10 | B12: mIgnoreSpecificMaxGroupOwnable | C12: 不受其它最大持有数量限制影响 | D12: √ | E12: √ | F12: FALSE | G12: 8
A13: 11 | B13: mMaximumDeltasToStack | C13: 效果叠加次数最大变化量 | D13: √ | E13: √ | G13: 17
A14: 12 | B14: mShowAsModifiedInUI | C14: 显示为已修饰 | D14: √ | E14: √ | F14: FALSE | G14: 6
A15: 13 | B15: mDeltaGoldCostPercent | C15: 折扣 | D15: √ | E15: √ | G15: 16
A16: 14 | B16: mDeltaRequiredLevel | C16: 所需等级变化值 | D16: √ | E16: √ | G16: 12
A17: 15 | B17: mDeltaGoldCost | C17: 固定价格变化 | D17: √ | E17: √ | G17: 15
A18: 16 | B18: mDescriptionToReplace | C18: 替代简述键 | D18: √ | E18: √ | G18: 36
A19: 17 | B19: mDynamicTooltipToReplace | C19: 替代动态详细信息键 | D19: √ | E19: √ | G19: 39
A20: 18 | B20: mVisualPriority | C20: 计分板排列优先级 | D20: √ | E20: √ | G20: 14
A21: 19 | B21: inventoryIconToOverlay | C21: 装备栏覆盖图标路径 | D21: √ | E21: √ | G21: 48
A22: 20 | B22: mDescriptionToAppend | C22: 追加简述键 | D22: √ | E22: √ | G22: 42
A23: 21 | B23: mDynamicTooltipToAppend | C23: 追加动态详细信息键 | D23: √ | E23: √ | G23: 45
A24: 22 | B24: mDisplayNameToAppend | C24: 追加显示名键 | D24: √ | E24: √ | G24: 27
A25: 23 | B25: mDisplayNameToReplace | C25: 替代显示名键 | D25: √ | E25: √ | G25: 30
A26: 24 | B26: mDisplayNameToPrepend | C26: 前附显示名键 | D26: √ | E26: √ | G26: 33
A27: 25 | B27: mClickableToEnable | C27: 单击使用技能 | D27: √ | E27: √ | F27: FALSE | G27: 9
A28: 26 | B28: mSpellNameToReplace | C28: 取代技能名称 | D28: √ | E28: √ | G28: 13
A29: 27 | B29: {20b65c83} | C29: 升级边框方案名称 | D29: √ | E29: √ | G29: 49
A30: 28 | B30: mModifiedIfBuildsFromItem_mDisplayName_content_zh | C30: 修饰构件装备名称（中文） | E30: √ | G30: 19
A31: 29 | B31: mModifiedIfBuildsFromItem_mDisplayName_content_en | C31: 修饰构件装备名称（英文） | E31: √ | G31: 20
A32: 30 | B32: mModifiedItem_mDisplayName_content_zh | C32: 修饰装备名称（中文） | E32: √ | G32: 3
A33: 31 | B33: mModifiedItem_mDisplayName_content_en | C33: 修饰装备名称（英文） | E33: √ | G33: 4
A34: 32 | B34: {06d9d838}_mDisplayName_content_zh | C34: 修饰前的基础构件名称（中文） | E34: √ | G34: 22
A35: 33 | B35: {06d9d838}_mDisplayName_content_en | C35: 修饰前的基础构件名称（英文） | E35: √ | G35: 23
A36: 34 | B36: {917537a9}_mDisplayName_content_zh | C36: 修饰后的基础构件名称（中文） | E36: √ | G36: 25
A37: 35 | B37: {917537a9}_mDisplayName_content_en | C37: 修饰后的基础构件名称（英文） | E37: √ | G37: 26
A38: 36 | B38: mDescriptionToReplace_content_zh | C38: 替代简述（中文） | E38: √ | G38: 37
A39: 37 | B39: mDescriptionToReplace_content_en | C39: 替代简述（英文） | E39: √ | G39: 38
A40: 38 | B40: mDynamicTooltipToReplace_content_zh | C40: 替代动态详细信息（中文） | E40: √ | G40: 40
A41: 39 | B41: mDynamicTooltipToReplace_content_en | C41: 替代动态详细信息（英文） | E41: √ | G41: 41
... A51: 49 | B51: mDisplayNameToPrepend_content_en | C51: 前附显示名（英文） | E51: √ | G51: 35

Sheet augment_header
A1: Index | B1: Key | C1: Value | D1: DirectlyImport? | E1: Flexible | F1: defaultValue | G1: OutputOrder
A2: 0 | B2: key | C2: 主键 | D2: √ | G2: 0
A3: 1 | B3: AugmentNameId | C3: 强化符文代码 | D3: √ | G3: 1
A4: 2 | B4: Enabled | C4: 可用性 | D4: √ | E4: √ | F4: TRUE | G4: 3
A5: 3 | B5: NameTra | C5: 名称键 | D5: √ | G5: 4
A6: 4 | B6: DescriptionTra | C6: 简介键 | D6: √ | G6: 21
A7: 5 | B7: AugmentTooltipTra | C7: 强化符文详细信息键 | D7: √ | G7: 26
A8: 6 | B8: RootSpell | C8: 根指令主键 | D8: √ | G8: 56
A9: 7 | B9: AdditionalSpells | C9: 其它指令主键列表 | D9: √ | G9: 58
A10: 8 | B10: mAugmentTags | C10: 强化符文标签 | D10: √ | E10: √ | G10: 15
A11: 9 | B11: mBuildTags | C11: 构建标签 | D11: √ | E11: √ | G11: 16
A12: 10 | B12: {3696d198} {c4182067} | C12: 强化符文详细信息描述部分键 | D12: √ | G12: 31
A13: 11 | B13: {3696d198} {231af825} | C13: 强化符文详细信息追踪部分键 | D13: √ | E13: √ | G13: 36
A14: 12 | B14: {791eb92e} {5753a320} {c98a82ca} | C14: 满级效果简介键 | D14: √ | G14: 41
A15: 13 | B15: {791eb92e} {5753a320} {05835d27} | C15: 满级效果详细信息键 | D15: √ | G15: 46
A16: 14 | B16: AugmentLargeIconPath | C16: 强化符文大图标路径 | D16: √ | G16: 64
A17: 15 | B17: AugmentSmallIconPath | C17: 强化符文小图标路径 | D17: √ | G17: 65
A18: 16 | B18: {815dad28} | C18: 次级稀有度 | D18: √ | E18: √ | G18: 9
A19: 17 | B19: AugmentDisplayTags | C19: 强化符文显示标签 | D19: √ | G19: 11
A20: 18 | B20: rarity | C20: 稀有度 | D20: √ | E20: √ | G20: 7
A21: 19 | B21: {ed593c9c} | C21: 不占用栏位 | D21: √ | E21: √ | F21: FALSE | G21: 17
A22: 20 | B22: AugmentPlatformId | C22: 强化符文序号 | D22: √ | F22: -1 | G22: 2
A23: 21 | B23: QuestData Quest | C23: 任务线主键 | D23: √ | E23: √ | G23: 60
A24: 22 | B24: {e3a02eac} | C24: 技能重载 | D24: √ | E24: √ | F24: FALSE | G24: 18
A25: 23 | B25: ResourceResolver | C25: 资源解析器主键 | D25: √ | E25: √ | G25: 62
A26: 24 | B26: NameTra_content_zh | C26: 名称（中文） | G26: 5
A27: 25 | B27: NameTra_content_en | C27: 名称（英文） | G27: 6
A28: 26 | B28: DescriptionTra_content_zh | C28: 简介（中文） | G28: 22
A29: 27 | B29: DescriptionTra_content_zh_burn | C29: 简介（中文/数值转换） | G29: 23
A30: 28 | B30: DescriptionTra_content_en | C30: 简介（英文） | G30: 24
A31: 29 | B31: DescriptionTra_content_en_burn | C31: 简介（英文/数值转换） | G31: 25
A32: 30 | B32: AugmentTooltipTra_content_zh | C32: 强化符文详细信息（中文） | G32: 27
A33: 31 | B33: AugmentTooltipTra_content_zh_burn | C33: 强化符文详细信息（中文/数值转换） | G33: 28
A34: 32 | B34: AugmentTooltipTra_content_en | C34: 强化符文详细信息（英文） | G34: 29
A35: 33 | B35: AugmentTooltipTra_content_en_burn | C35: 强化符文详细信息（英文/数值转换） | G35: 30
A36: 34 | B36: {3696d198} {c4182067}_content_zh | C36: 强化符文详细信息描述部分（中文） | G36: 32
A37: 35 | B37: {3696d198} {c4182067}_content_zh_burn | C37: 强化符文详细信息描述部分（中文/数值转换） | G37: 33
... A52: 50 | B52: AugmentDisplayTags_content | C52: 强化符文显示标签内容 | G52: 12
A53: 51 | B53: rarityValue | C53: 位阶 | E53: √ | G53: 8
A54: 52 | B54: RootSpellObject | C54: 根指令对象 | D54: √ | G54: 57
A55: 53 | B55: AdditionalSpells_Object | C55: 其它指令对象 | D55: √ | G55: 59
A56: 54 | B56: RootSpell mSpell DataValues MaxLevel | C56: 最大等级 | D56: √ | G56: 10
A57: 55 | B57: ResourceResolver resourceMap | C57: 资源解析器映射字典 | D57: √ | G57: 63
A58: 56 | B58: questline {bc1b3d88} | D58: √ | G58: 13
A59: 57 | B59: questline QuestName | C59: 任务线代码 | D59: √ | G59: 14
A60: 58 | B60: questline {4796bf5f} | C60: 任务线名称键
A61: 59 | B61: questline {c88f1a9b} | C61: 任务完成描述键 | D61: √ | G61: 51
A62: 60 | B62: questline {06b06978} texturePath | C62: 任务栏位图标纹理路径 | D62: √
A63: 61 | B63: questline {ee2e0dbc} | D63: √ | E63: √ | F63: FALSE | G63: 19
A64: 62 | B64: questline Milestones | C64: 任务线里程信息
A65: 63 | B65: questline {09d67381} | C65: 任务线相关强化符文 | D65: √ | G65: 61
A66: 64 | B66: questline {c504ece0} | D66: √ | F66: FALSE | G66: 20
A67: 65 | B67: questline {4796bf5f}_content_zh | C67: 任务线对应强化符文名称（中文）
A68: 66 | B68: questline {4796bf5f}_content_en | C68: 任务线对应强化符文名称（英文）
A69: 67 | B69: questline {c88f1a9b}_content_zh | C69: 任务完成描述（中文） | G69: 52
A70: 68 | B70: questline {c88f1a9b}_content_zh_burn | C70: 任务完成描述（中文/数值转换） | G70: 53
A71: 69 | B71: questline {c88f1a9b}_content_en | C71: 任务完成描述（英文） | G71: 54
A72: 70 | B72: questline {c88f1a9b}_content_en_burn | C72: 任务完成描述（英文/数值转换） | G72: 55

Sheet CherryAugment_header
A1: Index | B1: Key | C1: Value | D1: DirectlyImport? | E1: Flexible | F1: defaultValue | G1: OutputOrder
A2: 0 | B2: key | C2: =_xlfn.LET(_xlpm.x,VLOOKUP($B2,augment_header!$B$2:$G$72,2,FALSE),IF(_xlpm.x="","",_xlpm.x)) -> 主键 | D2: =IF(VLOOKUP($B2,augment_header!$B$2:$G$72,3,FALSE)="√","√","") -> √ | E2: =IF(VLOOKUP($B2,augment_header!$B$2:$G$72,4,FALSE)="√","√","") | F2: =_xlfn.LET(_xlpm.x,VLOOKUP($B2,augment_header!$B$2:$G$72,5,FALSE),IF(_xlpm.x="","",_xlpm.x)) | G2: 0
A3: 1 | B3: AugmentNameId | C3: =_xlfn.LET(_xlpm.x,VLOOKUP($B3,augment_header!$B$2:$G$72,2,FALSE),IF(_xlpm.x="","",_xlpm.x)) -> 强化符文代码 | D3: =IF(VLOOKUP($B3,augment_header!$B$2:$G$72,3,FALSE)="√","√","") -> √ | E3: =IF(VLOOKUP($B3,augment_header!$B$2:$G$72,4,FALSE)="√","√","") | F3: =_xlfn.LET(_xlpm.x,VLOOKUP($B3,augment_header!$B$2:$G$72,5,FALSE),IF(_xlpm.x="","",_xlpm.x)) | G3: 1
A4: 2 | B4: Enabled | C4: =_xlfn.LET(_xlpm.x,VLOOKUP($B4,augment_header!$B$2:$G$72,2,FALSE),IF(_xlpm.x="","",_xlpm.x)) -> 可用性 | D4: =IF(VLOOKUP($B4,augment_header!$B$2:$G$72,3,FALSE)="√","√","") -> √ | E4: =IF(VLOOKUP($B4,augment_header!$B$2:$G$72,4,FALSE)="√","√","") -> √ | F4: =_xlfn.LET(_xlpm.x,VLOOKUP($B4,augment_header!$B$2:$G$72,5,FALSE),IF(_xlpm.x="","",_xlpm.x)) -> TRUE | G4: 3
A5: 3 | B5: NameTra | C5: =_xlfn.LET(_xlpm.x,VLOOKUP($B5,augment_header!$B$2:$G$72,2,FALSE),IF(_xlpm.x="","",_xlpm.x)) -> 名称键 | D5: =IF(VLOOKUP($B5,augment_header!$B$2:$G$72,3,FALSE)="√","√","") -> √ | E5: =IF(VLOOKUP($B5,augment_header!$B$2:$G$72,4,FALSE)="√","√","") | F5: =_xlfn.LET(_xlpm.x,VLOOKUP($B5,augment_header!$B$2:$G$72,5,FALSE),IF(_xlpm.x="","",_xlpm.x)) | G5: 4
A6: 4 | B6: DescriptionTra | C6: =_xlfn.LET(_xlpm.x,VLOOKUP($B6,augment_header!$B$2:$G$72,2,FALSE),IF(_xlpm.x="","",_xlpm.x)) -> 简介键 | D6: =IF(VLOOKUP($B6,augment_header!$B$2:$G$72,3,FALSE)="√","√","") -> √ | E6: =IF(VLOOKUP($B6,augment_header!$B$2:$G$72,4,FALSE)="√","√","") | F6: =_xlfn.LET(_xlpm.x,VLOOKUP($B6,augment_header!$B$2:$G$72,5,FALSE),IF(_xlpm.x="","",_xlpm.x)) | G6: 16
A7: 5 | B7: AugmentTooltipTra | C7: =_xlfn.LET(_xlpm.x,VLOOKUP($B7,augment_header!$B$2:$G$72,2,FALSE),IF(_xlpm.x="","",_xlpm.x)) -> 强化符文详细信息键 | D7: =IF(VLOOKUP($B7,augment_header!$B$2:$G$72,3,FALSE)="√","√","") -> √ | E7: =IF(VLOOKUP($B7,augment_header!$B$2:$G$72,4,FALSE)="√","√","") | F7: =_xlfn.LET(_xlpm.x,VLOOKUP($B7,augment_header!$B$2:$G$72,5,FALSE),IF(_xlpm.x="","",_xlpm.x)) | G7: 21
A8: 6 | B8: RootSpell | C8: =_xlfn.LET(_xlpm.x,VLOOKUP($B8,augment_header!$B$2:$G$72,2,FALSE),IF(_xlpm.x="","",_xlpm.x)) -> 根指令主键 | D8: =IF(VLOOKUP($B8,augment_header!$B$2:$G$72,3,FALSE)="√","√","") -> √ | E8: =IF(VLOOKUP($B8,augment_header!$B$2:$G$72,4,FALSE)="√","√","") | F8: =_xlfn.LET(_xlpm.x,VLOOKUP($B8,augment_header!$B$2:$G$72,5,FALSE),IF(_xlpm.x="","",_xlpm.x)) | G8: 46
A9: 7 | B9: AdditionalSpells | C9: =_xlfn.LET(_xlpm.x,VLOOKUP($B9,augment_header!$B$2:$G$72,2,FALSE),IF(_xlpm.x="","",_xlpm.x)) -> 其它指令主键列表 | D9: =IF(VLOOKUP($B9,augment_header!$B$2:$G$72,3,FALSE)="√","√","") -> √ | E9: =IF(VLOOKUP($B9,augment_header!$B$2:$G$72,4,FALSE)="√","√","") | F9: =_xlfn.LET(_xlpm.x,VLOOKUP($B9,augment_header!$B$2:$G$72,5,FALSE),IF(_xlpm.x="","",_xlpm.x))
A10: 8 | B10: mAugmentTags | C10: =_xlfn.LET(_xlpm.x,VLOOKUP($B10,augment_header!$B$2:$G$72,2,FALSE),IF(_xlpm.x="","",_xlpm.x)) -> 强化符文标签 | D10: =IF(VLOOKUP($B10,augment_header!$B$2:$G$72,3,FALSE)="√","√","") -> √ | E10: =IF(VLOOKUP($B10,augment_header!$B$2:$G$72,4,FALSE)="√","√","") -> √ | F10: =_xlfn.LET(_xlpm.x,VLOOKUP($B10,augment_header!$B$2:$G$72,5,FALSE),IF(_xlpm.x="","",_xlpm.x)) | G10: 13
A11: 9 | B11: mBuildTags | C11: =_xlfn.LET(_xlpm.x,VLOOKUP($B11,augment_header!$B$2:$G$72,2,FALSE),IF(_xlpm.x="","",_xlpm.x)) -> 构建标签 | D11: =IF(VLOOKUP($B11,augment_header!$B$2:$G$72,3,FALSE)="√","√","") -> √ | E11: =IF(VLOOKUP($B11,augment_header!$B$2:$G$72,4,FALSE)="√","√","") -> √ | F11: =_xlfn.LET(_xlpm.x,VLOOKUP($B11,augment_header!$B$2:$G$72,5,FALSE),IF(_xlpm.x="","",_xlpm.x)) | G11: 14
A12: 10 | B12: {3696d198} {c4182067} | C12: =_xlfn.LET(_xlpm.x,VLOOKUP($B12,augment_header!$B$2:$G$72,2,FALSE),IF(_xlpm.x="","",_xlpm.x)) -> 强化符文详细信息描述部分键 | D12: =IF(VLOOKUP($B12,augment_header!$B$2:$G$72,3,FALSE)="√","√","") -> √ | E12: =IF(VLOOKUP($B12,augment_header!$B$2:$G$72,4,FALSE)="√","√","") | F12: =_xlfn.LET(_xlpm.x,VLOOKUP($B12,augment_header!$B$2:$G$72,5,FALSE),IF(_xlpm.x="","",_xlpm.x)) | G12: 26
A13: 11 | B13: {3696d198} {231af825} | C13: =_xlfn.LET(_xlpm.x,VLOOKUP($B13,augment_header!$B$2:$G$72,2,FALSE),IF(_xlpm.x="","",_xlpm.x)) -> 强化符文详细信息追踪部分键 | D13: =IF(VLOOKUP($B13,augment_header!$B$2:$G$72,3,FALSE)="√","√","") -> √ | E13: =IF(VLOOKUP($B13,augment_header!$B$2:$G$72,4,FALSE)="√","√","") -> √ | F13: =_xlfn.LET(_xlpm.x,VLOOKUP($B13,augment_header!$B$2:$G$72,5,FALSE),IF(_xlpm.x="","",_xlpm.x)) | G13: 31
A14: 12 | B14: {791eb92e} {5753a320} {c98a82ca} | C14: =_xlfn.LET(_xlpm.x,VLOOKUP($B14,augment_header!$B$2:$G$72,2,FALSE),IF(_xlpm.x="","",_xlpm.x)) -> 满级效果简介键 | D14: =IF(VLOOKUP($B14,augment_header!$B$2:$G$72,3,FALSE)="√","√","") -> √ | E14: =IF(VLOOKUP($B14,augment_header!$B$2:$G$72,4,FALSE)="√","√","") | F14: =_xlfn.LET(_xlpm.x,VLOOKUP($B14,augment_header!$B$2:$G$72,5,FALSE),IF(_xlpm.x="","",_xlpm.x)) | G14: 36
A15: 13 | B15: {791eb92e} {5753a320} {05835d27} | C15: =_xlfn.LET(_xlpm.x,VLOOKUP($B15,augment_header!$B$2:$G$72,2,FALSE),IF(_xlpm.x="","",_xlpm.x)) -> 满级效果详细信息键 | D15: =IF(VLOOKUP($B15,augment_header!$B$2:$G$72,3,FALSE)="√","√","") -> √ | E15: =IF(VLOOKUP($B15,augment_header!$B$2:$G$72,4,FALSE)="√","√","") | F15: =_xlfn.LET(_xlpm.x,VLOOKUP($B15,augment_header!$B$2:$G$72,5,FALSE),IF(_xlpm.x="","",_xlpm.x)) | G15: 41
A16: 14 | B16: AugmentLargeIconPath | C16: =_xlfn.LET(_xlpm.x,VLOOKUP($B16,augment_header!$B$2:$G$72,2,FALSE),IF(_xlpm.x="","",_xlpm.x)) -> 强化符文大图标路径 | D16: =IF(VLOOKUP($B16,augment_header!$B$2:$G$72,3,FALSE)="√","√","") -> √ | E16: =IF(VLOOKUP($B16,augment_header!$B$2:$G$72,4,FALSE)="√","√","") | F16: =_xlfn.LET(_xlpm.x,VLOOKUP($B16,augment_header!$B$2:$G$72,5,FALSE),IF(_xlpm.x="","",_xlpm.x)) | G16: 48
A17: 15 | B17: AugmentSmallIconPath | C17: =_xlfn.LET(_xlpm.x,VLOOKUP($B17,augment_header!$B$2:$G$72,2,FALSE),IF(_xlpm.x="","",_xlpm.x)) -> 强化符文小图标路径 | D17: =IF(VLOOKUP($B17,augment_header!$B$2:$G$72,3,FALSE)="√","√","") -> √ | E17: =IF(VLOOKUP($B17,augment_header!$B$2:$G$72,4,FALSE)="√","√","") | F17: =_xlfn.LET(_xlpm.x,VLOOKUP($B17,augment_header!$B$2:$G$72,5,FALSE),IF(_xlpm.x="","",_xlpm.x)) | G17: 49
A18: 16 | B18: {815dad28} | C18: =_xlfn.LET(_xlpm.x,VLOOKUP($B18,augment_header!$B$2:$G$72,2,FALSE),IF(_xlpm.x="","",_xlpm.x)) -> 次级稀有度 | D18: =IF(VLOOKUP($B18,augment_header!$B$2:$G$72,3,FALSE)="√","√","") -> √ | E18: =IF(VLOOKUP($B18,augment_header!$B$2:$G$72,4,FALSE)="√","√","") -> √ | F18: =_xlfn.LET(_xlpm.x,VLOOKUP($B18,augment_header!$B$2:$G$72,5,FALSE),IF(_xlpm.x="","",_xlpm.x)) | G18: 9
A19: 17 | B19: AugmentDisplayTags | C19: =_xlfn.LET(_xlpm.x,VLOOKUP($B19,augment_header!$B$2:$G$72,2,FALSE),IF(_xlpm.x="","",_xlpm.x)) -> 强化符文显示标签 | D19: =IF(VLOOKUP($B19,augment_header!$B$2:$G$72,3,FALSE)="√","√","") -> √ | E19: =IF(VLOOKUP($B19,augment_header!$B$2:$G$72,4,FALSE)="√","√","") | F19: =_xlfn.LET(_xlpm.x,VLOOKUP($B19,augment_header!$B$2:$G$72,5,FALSE),IF(_xlpm.x="","",_xlpm.x)) | G19: 11
A20: 18 | B20: rarity | C20: =_xlfn.LET(_xlpm.x,VLOOKUP($B20,augment_header!$B$2:$G$72,2,FALSE),IF(_xlpm.x="","",_xlpm.x)) -> 稀有度 | D20: =IF(VLOOKUP($B20,augment_header!$B$2:$G$72,3,FALSE)="√","√","") -> √ | E20: =IF(VLOOKUP($B20,augment_header!$B$2:$G$72,4,FALSE)="√","√","") -> √ | F20: =_xlfn.LET(_xlpm.x,VLOOKUP($B20,augment_header!$B$2:$G$72,5,FALSE),IF(_xlpm.x="","",_xlpm.x)) | G20: 7
A21: 19 | B21: {ed593c9c} | C21: =_xlfn.LET(_xlpm.x,VLOOKUP($B21,augment_header!$B$2:$G$72,2,FALSE),IF(_xlpm.x="","",_xlpm.x)) -> 不占用栏位 | D21: =IF(VLOOKUP($B21,augment_header!$B$2:$G$72,3,FALSE)="√","√","") -> √ | E21: =IF(VLOOKUP($B21,augment_header!$B$2:$G$72,4,FALSE)="√","√","") -> √ | F21: =_xlfn.LET(_xlpm.x,VLOOKUP($B21,augment_header!$B$2:$G$72,5,FALSE),IF(_xlpm.x="","",_xlpm.x)) -> FALSE | G21: 15
A22: 20 | B22: AugmentPlatformId | C22: =_xlfn.LET(_xlpm.x,VLOOKUP($B22,augment_header!$B$2:$G$72,2,FALSE),IF(_xlpm.x="","",_xlpm.x)) -> 强化符文序号 | D22: =IF(VLOOKUP($B22,augment_header!$B$2:$G$72,3,FALSE)="√","√","") -> √ | E22: =IF(VLOOKUP($B22,augment_header!$B$2:$G$72,4,FALSE)="√","√","") | F22: =_xlfn.LET(_xlpm.x,VLOOKUP($B22,augment_header!$B$2:$G$72,5,FALSE),IF(_xlpm.x="","",_xlpm.x)) -> -1 | G22: 2
A23: 21 | B23: QuestData Quest | C23: =_xlfn.LET(_xlpm.x,VLOOKUP($B23,augment_header!$B$2:$G$72,2,FALSE),IF(_xlpm.x="","",_xlpm.x)) -> 任务线主键 | D23: =IF(VLOOKUP($B23,augment_header!$B$2:$G$72,3,FALSE)="√","√","") -> √ | E23: =IF(VLOOKUP($B23,augment_header!$B$2:$G$72,4,FALSE)="√","√","") -> √ | F23: =_xlfn.LET(_xlpm.x,VLOOKUP($B23,augment_header!$B$2:$G$72,5,FALSE),IF(_xlpm.x="","",_xlpm.x))
A24: 22 | B24: {e3a02eac} | C24: =_xlfn.LET(_xlpm.x,VLOOKUP($B24,augment_header!$B$2:$G$72,2,FALSE),IF(_xlpm.x="","",_xlpm.x)) -> 技能重载 | D24: =IF(VLOOKUP($B24,augment_header!$B$2:$G$72,3,FALSE)="√","√","") -> √ | E24: =IF(VLOOKUP($B24,augment_header!$B$2:$G$72,4,FALSE)="√","√","") -> √ | F24: =_xlfn.LET(_xlpm.x,VLOOKUP($B24,augment_header!$B$2:$G$72,5,FALSE),IF(_xlpm.x="","",_xlpm.x)) -> FALSE
A25: 23 | B25: ResourceResolver | C25: =_xlfn.LET(_xlpm.x,VLOOKUP($B25,augment_header!$B$2:$G$72,2,FALSE),IF(_xlpm.x="","",_xlpm.x)) -> 资源解析器主键 | D25: =IF(VLOOKUP($B25,augment_header!$B$2:$G$72,3,FALSE)="√","√","") -> √ | E25: =IF(VLOOKUP($B25,augment_header!$B$2:$G$72,4,FALSE)="√","√","") -> √ | F25: =_xlfn.LET(_xlpm.x,VLOOKUP($B25,augment_header!$B$2:$G$72,5,FALSE),IF(_xlpm.x="","",_xlpm.x))
A26: 24 | B26: NameTra_content_zh | C26: =_xlfn.LET(_xlpm.x,VLOOKUP($B26,augment_header!$B$2:$G$72,2,FALSE),IF(_xlpm.x="","",_xlpm.x)) -> 名称（中文） | D26: =IF(VLOOKUP($B26,augment_header!$B$2:$G$72,3,FALSE)="√","√","") | E26: =IF(VLOOKUP($B26,augment_header!$B$2:$G$72,4,FALSE)="√","√","") | F26: =_xlfn.LET(_xlpm.x,VLOOKUP($B26,augment_header!$B$2:$G$72,5,FALSE),IF(_xlpm.x="","",_xlpm.x)) | G26: 5
A27: 25 | B27: NameTra_content_en | C27: =_xlfn.LET(_xlpm.x,VLOOKUP($B27,augment_header!$B$2:$G$72,2,FALSE),IF(_xlpm.x="","",_xlpm.x)) -> 名称（英文） | D27: =IF(VLOOKUP($B27,augment_header!$B$2:$G$72,3,FALSE)="√","√","") | E27: =IF(VLOOKUP($B27,augment_header!$B$2:$G$72,4,FALSE)="√","√","") | F27: =_xlfn.LET(_xlpm.x,VLOOKUP($B27,augment_header!$B$2:$G$72,5,FALSE),IF(_xlpm.x="","",_xlpm.x)) | G27: 6
A28: 26 | B28: DescriptionTra_content_zh | C28: =_xlfn.LET(_xlpm.x,VLOOKUP($B28,augment_header!$B$2:$G$72,2,FALSE),IF(_xlpm.x="","",_xlpm.x)) -> 简介（中文） | D28: =IF(VLOOKUP($B28,augment_header!$B$2:$G$72,3,FALSE)="√","√","") | E28: =IF(VLOOKUP($B28,augment_header!$B$2:$G$72,4,FALSE)="√","√","") | F28: =_xlfn.LET(_xlpm.x,VLOOKUP($B28,augment_header!$B$2:$G$72,5,FALSE),IF(_xlpm.x="","",_xlpm.x)) | G28: 17
A29: 27 | B29: DescriptionTra_content_zh_burn | C29: =_xlfn.LET(_xlpm.x,VLOOKUP($B29,augment_header!$B$2:$G$72,2,FALSE),IF(_xlpm.x="","",_xlpm.x)) -> 简介（中文/数值转换） | D29: =IF(VLOOKUP($B29,augment_header!$B$2:$G$72,3,FALSE)="√","√","") | E29: =IF(VLOOKUP($B29,augment_header!$B$2:$G$72,4,FALSE)="√","√","") | F29: =_xlfn.LET(_xlpm.x,VLOOKUP($B29,augment_header!$B$2:$G$72,5,FALSE),IF(_xlpm.x="","",_xlpm.x)) | G29: 18
A30: 28 | B30: DescriptionTra_content_en | C30: =_xlfn.LET(_xlpm.x,VLOOKUP($B30,augment_header!$B$2:$G$72,2,FALSE),IF(_xlpm.x="","",_xlpm.x)) -> 简介（英文） | D30: =IF(VLOOKUP($B30,augment_header!$B$2:$G$72,3,FALSE)="√","√","") | E30: =IF(VLOOKUP($B30,augment_header!$B$2:$G$72,4,FALSE)="√","√","") | F30: =_xlfn.LET(_xlpm.x,VLOOKUP($B30,augment_header!$B$2:$G$72,5,FALSE),IF(_xlpm.x="","",_xlpm.x)) | G30: 19
A31: 29 | B31: DescriptionTra_content_en_burn | C31: =_xlfn.LET(_xlpm.x,VLOOKUP($B31,augment_header!$B$2:$G$72,2,FALSE),IF(_xlpm.x="","",_xlpm.x)) -> 简介（英文/数值转换） | D31: =IF(VLOOKUP($B31,augment_header!$B$2:$G$72,3,FALSE)="√","√","") | E31: =IF(VLOOKUP($B31,augment_header!$B$2:$G$72,4,FALSE)="√","√","") | F31: =_xlfn.LET(_xlpm.x,VLOOKUP($B31,augment_header!$B$2:$G$72,5,FALSE),IF(_xlpm.x="","",_xlpm.x)) | G31: 20
A32: 30 | B32: AugmentTooltipTra_content_zh | C32: =_xlfn.LET(_xlpm.x,VLOOKUP($B32,augment_header!$B$2:$G$72,2,FALSE),IF(_xlpm.x="","",_xlpm.x)) -> 强化符文详细信息（中文） | D32: =IF(VLOOKUP($B32,augment_header!$B$2:$G$72,3,FALSE)="√","√","") | E32: =IF(VLOOKUP($B32,augment_header!$B$2:$G$72,4,FALSE)="√","√","") | F32: =_xlfn.LET(_xlpm.x,VLOOKUP($B32,augment_header!$B$2:$G$72,5,FALSE),IF(_xlpm.x="","",_xlpm.x)) | G32: 22
A33: 31 | B33: AugmentTooltipTra_content_zh_burn | C33: =_xlfn.LET(_xlpm.x,VLOOKUP($B33,augment_header!$B$2:$G$72,2,FALSE),IF(_xlpm.x="","",_xlpm.x)) -> 强化符文详细信息（中文/数值转换） | D33: =IF(VLOOKUP($B33,augment_header!$B$2:$G$72,3,FALSE)="√","√","") | E33: =IF(VLOOKUP($B33,augment_header!$B$2:$G$72,4,FALSE)="√","√","") | F33: =_xlfn.LET(_xlpm.x,VLOOKUP($B33,augment_header!$B$2:$G$72,5,FALSE),IF(_xlpm.x="","",_xlpm.x)) | G33: 23
A34: 32 | B34: AugmentTooltipTra_content_en | C34: =_xlfn.LET(_xlpm.x,VLOOKUP($B34,augment_header!$B$2:$G$72,2,FALSE),IF(_xlpm.x="","",_xlpm.x)) -> 强化符文详细信息（英文） | D34: =IF(VLOOKUP($B34,augment_header!$B$2:$G$72,3,FALSE)="√","√","") | E34: =IF(VLOOKUP($B34,augment_header!$B$2:$G$72,4,FALSE)="√","√","") | F34: =_xlfn.LET(_xlpm.x,VLOOKUP($B34,augment_header!$B$2:$G$72,5,FALSE),IF(_xlpm.x="","",_xlpm.x)) | G34: 24
A35: 33 | B35: AugmentTooltipTra_content_en_burn | C35: =_xlfn.LET(_xlpm.x,VLOOKUP($B35,augment_header!$B$2:$G$72,2,FALSE),IF(_xlpm.x="","",_xlpm.x)) -> 强化符文详细信息（英文/数值转换） | D35: =IF(VLOOKUP($B35,augment_header!$B$2:$G$72,3,FALSE)="√","√","") | E35: =IF(VLOOKUP($B35,augment_header!$B$2:$G$72,4,FALSE)="√","√","") | F35: =_xlfn.LET(_xlpm.x,VLOOKUP($B35,augment_header!$B$2:$G$72,5,FALSE),IF(_xlpm.x="","",_xlpm.x)) | G35: 25
A36: 34 | B36: {3696d198} {c4182067}_content_zh | C36: =_xlfn.LET(_xlpm.x,VLOOKUP($B36,augment_header!$B$2:$G$72,2,FALSE),IF(_xlpm.x="","",_xlpm.x)) -> 强化符文详细信息描述部分（中文） | D36: =IF(VLOOKUP($B36,augment_header!$B$2:$G$72,3,FALSE)="√","√","") | E36: =IF(VLOOKUP($B36,augment_header!$B$2:$G$72,4,FALSE)="√","√","") | F36: =_xlfn.LET(_xlpm.x,VLOOKUP($B36,augment_header!$B$2:$G$72,5,FALSE),IF(_xlpm.x="","",_xlpm.x)) | G36: 27
A37: 35 | B37: {3696d198} {c4182067}_content_zh_burn | C37: =_xlfn.LET(_xlpm.x,VLOOKUP($B37,augment_header!$B$2:$G$72,2,FALSE),IF(_xlpm.x="","",_xlpm.x)) -> 强化符文详细信息描述部分（中文/数值转换） | D37: =IF(VLOOKUP($B37,augment_header!$B$2:$G$72,3,FALSE)="√","√","") | E37: =IF(VLOOKUP($B37,augment_header!$B$2:$G$72,4,FALSE)="√","√","") | F37: =_xlfn.LET(_xlpm.x,VLOOKUP($B37,augment_header!$B$2:$G$72,5,FALSE),IF(_xlpm.x="","",_xlpm.x)) | G37: 28
... A54: 52 | B54: RootSpellObject | C54: =_xlfn.LET(_xlpm.x,VLOOKUP($B54,augment_header!$B$2:$G$72,2,FALSE),IF(_xlpm.x="","",_xlpm.x)) -> 根指令对象 | D54: =IF(VLOOKUP($B54,augment_header!$B$2:$G$72,3,FALSE)="√","√","") -> √ | E54: =IF(VLOOKUP($B54,augment_header!$B$2:$G$72,4,FALSE)="√","√","") | F54: =_xlfn.LET(_xlpm.x,VLOOKUP($B54,augment_header!$B$2:$G$72,5,FALSE),IF(_xlpm.x="","",_xlpm.x)) | G54: 47
A55: 53 | B55: AdditionalSpells_Object | C55: =_xlfn.LET(_xlpm.x,VLOOKUP($B55,augment_header!$B$2:$G$72,2,FALSE),IF(_xlpm.x="","",_xlpm.x)) -> 其它指令对象 | D55: =IF(VLOOKUP($B55,augment_header!$B$2:$G$72,3,FALSE)="√","√","") -> √ | E55: =IF(VLOOKUP($B55,augment_header!$B$2:$G$72,4,FALSE)="√","√","") | F55: =_xlfn.LET(_xlpm.x,VLOOKUP($B55,augment_header!$B$2:$G$72,5,FALSE),IF(_xlpm.x="","",_xlpm.x))
A56: 54 | B56: RootSpell mSpell DataValues MaxLevel | C56: =_xlfn.LET(_xlpm.x,VLOOKUP($B56,augment_header!$B$2:$G$72,2,FALSE),IF(_xlpm.x="","",_xlpm.x)) -> 最大等级 | D56: =IF(VLOOKUP($B56,augment_header!$B$2:$G$72,3,FALSE)="√","√","") -> √ | E56: =IF(VLOOKUP($B56,augment_header!$B$2:$G$72,4,FALSE)="√","√","") | F56: =_xlfn.LET(_xlpm.x,VLOOKUP($B56,augment_header!$B$2:$G$72,5,FALSE),IF(_xlpm.x="","",_xlpm.x)) | G56: 10
A57: 55 | B57: ResourceResolver resourceMap | C57: =_xlfn.LET(_xlpm.x,VLOOKUP($B57,augment_header!$B$2:$G$72,2,FALSE),IF(_xlpm.x="","",_xlpm.x)) -> 资源解析器映射字典 | D57: =IF(VLOOKUP($B57,augment_header!$B$2:$G$72,3,FALSE)="√","√","") -> √ | E57: =IF(VLOOKUP($B57,augment_header!$B$2:$G$72,4,FALSE)="√","√","") | F57: =_xlfn.LET(_xlpm.x,VLOOKUP($B57,augment_header!$B$2:$G$72,5,FALSE),IF(_xlpm.x="","",_xlpm.x))
A58: 56 | B58: questline {bc1b3d88} | C58: =_xlfn.LET(_xlpm.x,VLOOKUP($B58,augment_header!$B$2:$G$72,2,FALSE),IF(_xlpm.x="","",_xlpm.x)) | D58: =IF(VLOOKUP($B58,augment_header!$B$2:$G$72,3,FALSE)="√","√","") -> √ | E58: =IF(VLOOKUP($B58,augment_header!$B$2:$G$72,4,FALSE)="√","√","") | F58: =_xlfn.LET(_xlpm.x,VLOOKUP($B58,augment_header!$B$2:$G$72,5,FALSE),IF(_xlpm.x="","",_xlpm.x))
A59: 57 | B59: questline QuestName | C59: =_xlfn.LET(_xlpm.x,VLOOKUP($B59,augment_header!$B$2:$G$72,2,FALSE),IF(_xlpm.x="","",_xlpm.x)) -> 任务线代码 | D59: =IF(VLOOKUP($B59,augment_header!$B$2:$G$72,3,FALSE)="√","√","") -> √ | E59: =IF(VLOOKUP($B59,augment_header!$B$2:$G$72,4,FALSE)="√","√","") | F59: =_xlfn.LET(_xlpm.x,VLOOKUP($B59,augment_header!$B$2:$G$72,5,FALSE),IF(_xlpm.x="","",_xlpm.x))
A60: 58 | B60: questline {4796bf5f} | C60: =_xlfn.LET(_xlpm.x,VLOOKUP($B60,augment_header!$B$2:$G$72,2,FALSE),IF(_xlpm.x="","",_xlpm.x)) -> 任务线名称键 | D60: =IF(VLOOKUP($B60,augment_header!$B$2:$G$72,3,FALSE)="√","√","") | E60: =IF(VLOOKUP($B60,augment_header!$B$2:$G$72,4,FALSE)="√","√","") | F60: =_xlfn.LET(_xlpm.x,VLOOKUP($B60,augment_header!$B$2:$G$72,5,FALSE),IF(_xlpm.x="","",_xlpm.x))
A61: 59 | B61: questline {c88f1a9b} | C61: =_xlfn.LET(_xlpm.x,VLOOKUP($B61,augment_header!$B$2:$G$72,2,FALSE),IF(_xlpm.x="","",_xlpm.x)) -> 任务完成描述键 | D61: =IF(VLOOKUP($B61,augment_header!$B$2:$G$72,3,FALSE)="√","√","") -> √ | E61: =IF(VLOOKUP($B61,augment_header!$B$2:$G$72,4,FALSE)="√","√","") | F61: =_xlfn.LET(_xlpm.x,VLOOKUP($B61,augment_header!$B$2:$G$72,5,FALSE),IF(_xlpm.x="","",_xlpm.x))
A62: 60 | B62: questline {06b06978} texturePath | C62: =_xlfn.LET(_xlpm.x,VLOOKUP($B62,augment_header!$B$2:$G$72,2,FALSE),IF(_xlpm.x="","",_xlpm.x)) -> 任务栏位图标纹理路径 | D62: =IF(VLOOKUP($B62,augment_header!$B$2:$G$72,3,FALSE)="√","√","") -> √ | E62: =IF(VLOOKUP($B62,augment_header!$B$2:$G$72,4,FALSE)="√","√","") | F62: =_xlfn.LET(_xlpm.x,VLOOKUP($B62,augment_header!$B$2:$G$72,5,FALSE),IF(_xlpm.x="","",_xlpm.x))
A63: 61 | B63: questline {ee2e0dbc} | C63: =_xlfn.LET(_xlpm.x,VLOOKUP($B63,augment_header!$B$2:$G$72,2,FALSE),IF(_xlpm.x="","",_xlpm.x)) | D63: =IF(VLOOKUP($B63,augment_header!$B$2:$G$72,3,FALSE)="√","√","") -> √ | E63: =IF(VLOOKUP($B63,augment_header!$B$2:$G$72,4,FALSE)="√","√","") -> √ | F63: =_xlfn.LET(_xlpm.x,VLOOKUP($B63,augment_header!$B$2:$G$72,5,FALSE),IF(_xlpm.x="","",_xlpm.x)) -> FALSE
A64: 62 | B64: questline Milestones | C64: =_xlfn.LET(_xlpm.x,VLOOKUP($B64,augment_header!$B$2:$G$72,2,FALSE),IF(_xlpm.x="","",_xlpm.x)) -> 任务线里程信息 | D64: =IF(VLOOKUP($B64,augment_header!$B$2:$G$72,3,FALSE)="√","√","") | E64: =IF(VLOOKUP($B64,augment_header!$B$2:$G$72,4,FALSE)="√","√","") | F64: =_xlfn.LET(_xlpm.x,VLOOKUP($B64,augment_header!$B$2:$G$72,5,FALSE),IF(_xlpm.x="","",_xlpm.x))
A65: 63 | B65: questline {09d67381} | C65: =_xlfn.LET(_xlpm.x,VLOOKUP($B65,augment_header!$B$2:$G$72,2,FALSE),IF(_xlpm.x="","",_xlpm.x)) -> 任务线相关强化符文 | D65: =IF(VLOOKUP($B65,augment_header!$B$2:$G$72,3,FALSE)="√","√","") -> √ | E65: =IF(VLOOKUP($B65,augment_header!$B$2:$G$72,4,FALSE)="√","√","") | F65: =_xlfn.LET(_xlpm.x,VLOOKUP($B65,augment_header!$B$2:$G$72,5,FALSE),IF(_xlpm.x="","",_xlpm.x))
A66: 64 | B66: questline {c504ece0} | C66: =_xlfn.LET(_xlpm.x,VLOOKUP($B66,augment_header!$B$2:$G$72,2,FALSE),IF(_xlpm.x="","",_xlpm.x)) | D66: =IF(VLOOKUP($B66,augment_header!$B$2:$G$72,3,FALSE)="√","√","") -> √ | E66: =IF(VLOOKUP($B66,augment_header!$B$2:$G$72,4,FALSE)="√","√","") | F66: =_xlfn.LET(_xlpm.x,VLOOKUP($B66,augment_header!$B$2:$G$72,5,FALSE),IF(_xlpm.x="","",_xlpm.x)) -> FALSE
A67: 65 | B67: questline {4796bf5f}_content_zh | C67: =_xlfn.LET(_xlpm.x,VLOOKUP($B67,augment_header!$B$2:$G$72,2,FALSE),IF(_xlpm.x="","",_xlpm.x)) -> 任务线对应强化符文名称（中文） | D67: =IF(VLOOKUP($B67,augment_header!$B$2:$G$72,3,FALSE)="√","√","") | E67: =IF(VLOOKUP($B67,augment_header!$B$2:$G$72,4,FALSE)="√","√","") | F67: =_xlfn.LET(_xlpm.x,VLOOKUP($B67,augment_header!$B$2:$G$72,5,FALSE),IF(_xlpm.x="","",_xlpm.x))
A68: 66 | B68: questline {4796bf5f}_content_en | C68: =_xlfn.LET(_xlpm.x,VLOOKUP($B68,augment_header!$B$2:$G$72,2,FALSE),IF(_xlpm.x="","",_xlpm.x)) -> 任务线对应强化符文名称（英文） | D68: =IF(VLOOKUP($B68,augment_header!$B$2:$G$72,3,FALSE)="√","√","") | E68: =IF(VLOOKUP($B68,augment_header!$B$2:$G$72,4,FALSE)="√","√","") | F68: =_xlfn.LET(_xlpm.x,VLOOKUP($B68,augment_header!$B$2:$G$72,5,FALSE),IF(_xlpm.x="","",_xlpm.x))
... A72: 70 | B72: questline {c88f1a9b}_content_en_burn | C72: =_xlfn.LET(_xlpm.x,VLOOKUP($B72,augment_header!$B$2:$G$72,2,FALSE),IF(_xlpm.x="","",_xlpm.x)) -> 任务完成描述（英文/数值转换） | D72: =IF(VLOOKUP($B72,augment_header!$B$2:$G$72,3,FALSE)="√","√","") | E72: =IF(VLOOKUP($B72,augment_header!$B$2:$G$72,4,FALSE)="√","√","") | F72: =_xlfn.LET(_xlpm.x,VLOOKUP($B72,augment_header!$B$2:$G$72,5,FALSE),IF(_xlpm.x="","",_xlpm.x))

Sheet SwarmAugment_header
A1: Index | B1: Key | C1: Value | D1: DirectlyImport? | E1: Flexible | F1: defaultValue | G1: OutputOrder
A2: 0 | B2: key | C2: =_xlfn.LET(_xlpm.x,VLOOKUP($B2,augment_header!$B$2:$G$72,2,FALSE),IF(_xlpm.x="","",_xlpm.x)) -> 主键 | D2: =IF(VLOOKUP($B2,augment_header!$B$2:$G$72,3,FALSE)="√","√","") -> √ | E2: =IF(VLOOKUP($B2,augment_header!$B$2:$G$72,4,FALSE)="√","√","") | F2: =_xlfn.LET(_xlpm.x,VLOOKUP($B2,augment_header!$B$2:$G$72,5,FALSE),IF(_xlpm.x="","",_xlpm.x)) | G2: 0
A3: 1 | B3: AugmentNameId | C3: =_xlfn.LET(_xlpm.x,VLOOKUP($B3,augment_header!$B$2:$G$72,2,FALSE),IF(_xlpm.x="","",_xlpm.x)) -> 强化符文代码 | D3: =IF(VLOOKUP($B3,augment_header!$B$2:$G$72,3,FALSE)="√","√","") -> √ | E3: =IF(VLOOKUP($B3,augment_header!$B$2:$G$72,4,FALSE)="√","√","") | F3: =_xlfn.LET(_xlpm.x,VLOOKUP($B3,augment_header!$B$2:$G$72,5,FALSE),IF(_xlpm.x="","",_xlpm.x)) | G3: 1
A4: 2 | B4: Enabled | C4: =_xlfn.LET(_xlpm.x,VLOOKUP($B4,augment_header!$B$2:$G$72,2,FALSE),IF(_xlpm.x="","",_xlpm.x)) -> 可用性 | D4: =IF(VLOOKUP($B4,augment_header!$B$2:$G$72,3,FALSE)="√","√","") -> √ | E4: =IF(VLOOKUP($B4,augment_header!$B$2:$G$72,4,FALSE)="√","√","") -> √ | F4: =_xlfn.LET(_xlpm.x,VLOOKUP($B4,augment_header!$B$2:$G$72,5,FALSE),IF(_xlpm.x="","",_xlpm.x)) -> TRUE
A5: 3 | B5: NameTra | C5: =_xlfn.LET(_xlpm.x,VLOOKUP($B5,augment_header!$B$2:$G$72,2,FALSE),IF(_xlpm.x="","",_xlpm.x)) -> 名称键 | D5: =IF(VLOOKUP($B5,augment_header!$B$2:$G$72,3,FALSE)="√","√","") -> √ | E5: =IF(VLOOKUP($B5,augment_header!$B$2:$G$72,4,FALSE)="√","√","") | F5: =_xlfn.LET(_xlpm.x,VLOOKUP($B5,augment_header!$B$2:$G$72,5,FALSE),IF(_xlpm.x="","",_xlpm.x)) | G5: 3
A6: 4 | B6: DescriptionTra | C6: =_xlfn.LET(_xlpm.x,VLOOKUP($B6,augment_header!$B$2:$G$72,2,FALSE),IF(_xlpm.x="","",_xlpm.x)) -> 简介键 | D6: =IF(VLOOKUP($B6,augment_header!$B$2:$G$72,3,FALSE)="√","√","") -> √ | E6: =IF(VLOOKUP($B6,augment_header!$B$2:$G$72,4,FALSE)="√","√","") | F6: =_xlfn.LET(_xlpm.x,VLOOKUP($B6,augment_header!$B$2:$G$72,5,FALSE),IF(_xlpm.x="","",_xlpm.x)) | G6: 9
A7: 5 | B7: AugmentTooltipTra | C7: =_xlfn.LET(_xlpm.x,VLOOKUP($B7,augment_header!$B$2:$G$72,2,FALSE),IF(_xlpm.x="","",_xlpm.x)) -> 强化符文详细信息键 | D7: =IF(VLOOKUP($B7,augment_header!$B$2:$G$72,3,FALSE)="√","√","") -> √ | E7: =IF(VLOOKUP($B7,augment_header!$B$2:$G$72,4,FALSE)="√","√","") | F7: =_xlfn.LET(_xlpm.x,VLOOKUP($B7,augment_header!$B$2:$G$72,5,FALSE),IF(_xlpm.x="","",_xlpm.x)) | G7: 14
A8: 6 | B8: RootSpell | C8: =_xlfn.LET(_xlpm.x,VLOOKUP($B8,augment_header!$B$2:$G$72,2,FALSE),IF(_xlpm.x="","",_xlpm.x)) -> 根指令主键 | D8: =IF(VLOOKUP($B8,augment_header!$B$2:$G$72,3,FALSE)="√","√","") -> √ | E8: =IF(VLOOKUP($B8,augment_header!$B$2:$G$72,4,FALSE)="√","√","") | F8: =_xlfn.LET(_xlpm.x,VLOOKUP($B8,augment_header!$B$2:$G$72,5,FALSE),IF(_xlpm.x="","",_xlpm.x)) | G8: 19
A9: 7 | B9: AdditionalSpells | C9: =_xlfn.LET(_xlpm.x,VLOOKUP($B9,augment_header!$B$2:$G$72,2,FALSE),IF(_xlpm.x="","",_xlpm.x)) -> 其它指令主键列表 | D9: =IF(VLOOKUP($B9,augment_header!$B$2:$G$72,3,FALSE)="√","√","") -> √ | E9: =IF(VLOOKUP($B9,augment_header!$B$2:$G$72,4,FALSE)="√","√","") | F9: =_xlfn.LET(_xlpm.x,VLOOKUP($B9,augment_header!$B$2:$G$72,5,FALSE),IF(_xlpm.x="","",_xlpm.x))
A10: 8 | B10: mAugmentTags | C10: =_xlfn.LET(_xlpm.x,VLOOKUP($B10,augment_header!$B$2:$G$72,2,FALSE),IF(_xlpm.x="","",_xlpm.x)) -> 强化符文标签 | D10: =IF(VLOOKUP($B10,augment_header!$B$2:$G$72,3,FALSE)="√","√","") -> √ | E10: =IF(VLOOKUP($B10,augment_header!$B$2:$G$72,4,FALSE)="√","√","") -> √ | F10: =_xlfn.LET(_xlpm.x,VLOOKUP($B10,augment_header!$B$2:$G$72,5,FALSE),IF(_xlpm.x="","",_xlpm.x))
A11: 9 | B11: mBuildTags | C11: =_xlfn.LET(_xlpm.x,VLOOKUP($B11,augment_header!$B$2:$G$72,2,FALSE),IF(_xlpm.x="","",_xlpm.x)) -> 构建标签 | D11: =IF(VLOOKUP($B11,augment_header!$B$2:$G$72,3,FALSE)="√","√","") -> √ | E11: =IF(VLOOKUP($B11,augment_header!$B$2:$G$72,4,FALSE)="√","√","") -> √ | F11: =_xlfn.LET(_xlpm.x,VLOOKUP($B11,augment_header!$B$2:$G$72,5,FALSE),IF(_xlpm.x="","",_xlpm.x)) | G11: 8
A12: 10 | B12: {3696d198} {c4182067} | C12: =_xlfn.LET(_xlpm.x,VLOOKUP($B12,augment_header!$B$2:$G$72,2,FALSE),IF(_xlpm.x="","",_xlpm.x)) -> 强化符文详细信息描述部分键 | D12: =IF(VLOOKUP($B12,augment_header!$B$2:$G$72,3,FALSE)="√","√","") -> √ | E12: =IF(VLOOKUP($B12,augment_header!$B$2:$G$72,4,FALSE)="√","√","") | F12: =_xlfn.LET(_xlpm.x,VLOOKUP($B12,augment_header!$B$2:$G$72,5,FALSE),IF(_xlpm.x="","",_xlpm.x))
A13: 11 | B13: {3696d198} {231af825} | C13: =_xlfn.LET(_xlpm.x,VLOOKUP($B13,augment_header!$B$2:$G$72,2,FALSE),IF(_xlpm.x="","",_xlpm.x)) -> 强化符文详细信息追踪部分键 | D13: =IF(VLOOKUP($B13,augment_header!$B$2:$G$72,3,FALSE)="√","√","") -> √ | E13: =IF(VLOOKUP($B13,augment_header!$B$2:$G$72,4,FALSE)="√","√","") -> √ | F13: =_xlfn.LET(_xlpm.x,VLOOKUP($B13,augment_header!$B$2:$G$72,5,FALSE),IF(_xlpm.x="","",_xlpm.x))
A14: 12 | B14: {791eb92e} {5753a320} {c98a82ca} | C14: =_xlfn.LET(_xlpm.x,VLOOKUP($B14,augment_header!$B$2:$G$72,2,FALSE),IF(_xlpm.x="","",_xlpm.x)) -> 满级效果简介键 | D14: =IF(VLOOKUP($B14,augment_header!$B$2:$G$72,3,FALSE)="√","√","") -> √ | E14: =IF(VLOOKUP($B14,augment_header!$B$2:$G$72,4,FALSE)="√","√","") | F14: =_xlfn.LET(_xlpm.x,VLOOKUP($B14,augment_header!$B$2:$G$72,5,FALSE),IF(_xlpm.x="","",_xlpm.x))
A15: 13 | B15: {791eb92e} {5753a320} {05835d27} | C15: =_xlfn.LET(_xlpm.x,VLOOKUP($B15,augment_header!$B$2:$G$72,2,FALSE),IF(_xlpm.x="","",_xlpm.x)) -> 满级效果详细信息键 | D15: =IF(VLOOKUP($B15,augment_header!$B$2:$G$72,3,FALSE)="√","√","") -> √ | E15: =IF(VLOOKUP($B15,augment_header!$B$2:$G$72,4,FALSE)="√","√","") | F15: =_xlfn.LET(_xlpm.x,VLOOKUP($B15,augment_header!$B$2:$G$72,5,FALSE),IF(_xlpm.x="","",_xlpm.x))
A16: 14 | B16: AugmentLargeIconPath | C16: =_xlfn.LET(_xlpm.x,VLOOKUP($B16,augment_header!$B$2:$G$72,2,FALSE),IF(_xlpm.x="","",_xlpm.x)) -> 强化符文大图标路径 | D16: =IF(VLOOKUP($B16,augment_header!$B$2:$G$72,3,FALSE)="√","√","") -> √ | E16: =IF(VLOOKUP($B16,augment_header!$B$2:$G$72,4,FALSE)="√","√","") | F16: =_xlfn.LET(_xlpm.x,VLOOKUP($B16,augment_header!$B$2:$G$72,5,FALSE),IF(_xlpm.x="","",_xlpm.x)) | G16: 21
A17: 15 | B17: AugmentSmallIconPath | C17: =_xlfn.LET(_xlpm.x,VLOOKUP($B17,augment_header!$B$2:$G$72,2,FALSE),IF(_xlpm.x="","",_xlpm.x)) -> 强化符文小图标路径 | D17: =IF(VLOOKUP($B17,augment_header!$B$2:$G$72,3,FALSE)="√","√","") -> √ | E17: =IF(VLOOKUP($B17,augment_header!$B$2:$G$72,4,FALSE)="√","√","") | F17: =_xlfn.LET(_xlpm.x,VLOOKUP($B17,augment_header!$B$2:$G$72,5,FALSE),IF(_xlpm.x="","",_xlpm.x)) | G17: 22
A18: 16 | B18: {815dad28} | C18: =_xlfn.LET(_xlpm.x,VLOOKUP($B18,augment_header!$B$2:$G$72,2,FALSE),IF(_xlpm.x="","",_xlpm.x)) -> 次级稀有度 | D18: =IF(VLOOKUP($B18,augment_header!$B$2:$G$72,3,FALSE)="√","√","") -> √ | E18: =IF(VLOOKUP($B18,augment_header!$B$2:$G$72,4,FALSE)="√","√","") -> √ | F18: =_xlfn.LET(_xlpm.x,VLOOKUP($B18,augment_header!$B$2:$G$72,5,FALSE),IF(_xlpm.x="","",_xlpm.x))
A19: 17 | B19: AugmentDisplayTags | C19: =_xlfn.LET(_xlpm.x,VLOOKUP($B19,augment_header!$B$2:$G$72,2,FALSE),IF(_xlpm.x="","",_xlpm.x)) -> 强化符文显示标签 | D19: =IF(VLOOKUP($B19,augment_header!$B$2:$G$72,3,FALSE)="√","√","") -> √ | E19: =IF(VLOOKUP($B19,augment_header!$B$2:$G$72,4,FALSE)="√","√","") | F19: =_xlfn.LET(_xlpm.x,VLOOKUP($B19,augment_header!$B$2:$G$72,5,FALSE),IF(_xlpm.x="","",_xlpm.x))
A20: 18 | B20: rarity | C20: =_xlfn.LET(_xlpm.x,VLOOKUP($B20,augment_header!$B$2:$G$72,2,FALSE),IF(_xlpm.x="","",_xlpm.x)) -> 稀有度 | D20: =IF(VLOOKUP($B20,augment_header!$B$2:$G$72,3,FALSE)="√","√","") -> √ | E20: =IF(VLOOKUP($B20,augment_header!$B$2:$G$72,4,FALSE)="√","√","") -> √ | F20: =_xlfn.LET(_xlpm.x,VLOOKUP($B20,augment_header!$B$2:$G$72,5,FALSE),IF(_xlpm.x="","",_xlpm.x)) | G20: 6
A21: 19 | B21: {ed593c9c} | C21: =_xlfn.LET(_xlpm.x,VLOOKUP($B21,augment_header!$B$2:$G$72,2,FALSE),IF(_xlpm.x="","",_xlpm.x)) -> 不占用栏位 | D21: =IF(VLOOKUP($B21,augment_header!$B$2:$G$72,3,FALSE)="√","√","") -> √ | E21: =IF(VLOOKUP($B21,augment_header!$B$2:$G$72,4,FALSE)="√","√","") -> √ | F21: =_xlfn.LET(_xlpm.x,VLOOKUP($B21,augment_header!$B$2:$G$72,5,FALSE),IF(_xlpm.x="","",_xlpm.x)) -> FALSE
A22: 20 | B22: AugmentPlatformId | C22: =_xlfn.LET(_xlpm.x,VLOOKUP($B22,augment_header!$B$2:$G$72,2,FALSE),IF(_xlpm.x="","",_xlpm.x)) -> 强化符文序号 | D22: =IF(VLOOKUP($B22,augment_header!$B$2:$G$72,3,FALSE)="√","√","") -> √ | E22: =IF(VLOOKUP($B22,augment_header!$B$2:$G$72,4,FALSE)="√","√","") | F22: =_xlfn.LET(_xlpm.x,VLOOKUP($B22,augment_header!$B$2:$G$72,5,FALSE),IF(_xlpm.x="","",_xlpm.x)) -> -1 | G22: 2
A23: 21 | B23: QuestData Quest | C23: =_xlfn.LET(_xlpm.x,VLOOKUP($B23,augment_header!$B$2:$G$72,2,FALSE),IF(_xlpm.x="","",_xlpm.x)) -> 任务线主键 | D23: =IF(VLOOKUP($B23,augment_header!$B$2:$G$72,3,FALSE)="√","√","") -> √ | E23: =IF(VLOOKUP($B23,augment_header!$B$2:$G$72,4,FALSE)="√","√","") -> √ | F23: =_xlfn.LET(_xlpm.x,VLOOKUP($B23,augment_header!$B$2:$G$72,5,FALSE),IF(_xlpm.x="","",_xlpm.x))
A24: 22 | B24: {e3a02eac} | C24: =_xlfn.LET(_xlpm.x,VLOOKUP($B24,augment_header!$B$2:$G$72,2,FALSE),IF(_xlpm.x="","",_xlpm.x)) -> 技能重载 | D24: =IF(VLOOKUP($B24,augment_header!$B$2:$G$72,3,FALSE)="√","√","") -> √ | E24: =IF(VLOOKUP($B24,augment_header!$B$2:$G$72,4,FALSE)="√","√","") -> √ | F24: =_xlfn.LET(_xlpm.x,VLOOKUP($B24,augment_header!$B$2:$G$72,5,FALSE),IF(_xlpm.x="","",_xlpm.x)) -> FALSE
A25: 23 | B25: ResourceResolver | C25: =_xlfn.LET(_xlpm.x,VLOOKUP($B25,augment_header!$B$2:$G$72,2,FALSE),IF(_xlpm.x="","",_xlpm.x)) -> 资源解析器主键 | D25: =IF(VLOOKUP($B25,augment_header!$B$2:$G$72,3,FALSE)="√","√","") -> √ | E25: =IF(VLOOKUP($B25,augment_header!$B$2:$G$72,4,FALSE)="√","√","") -> √ | F25: =_xlfn.LET(_xlpm.x,VLOOKUP($B25,augment_header!$B$2:$G$72,5,FALSE),IF(_xlpm.x="","",_xlpm.x))
A26: 24 | B26: NameTra_content_zh | C26: =_xlfn.LET(_xlpm.x,VLOOKUP($B26,augment_header!$B$2:$G$72,2,FALSE),IF(_xlpm.x="","",_xlpm.x)) -> 名称（中文） | D26: =IF(VLOOKUP($B26,augment_header!$B$2:$G$72,3,FALSE)="√","√","") | E26: =IF(VLOOKUP($B26,augment_header!$B$2:$G$72,4,FALSE)="√","√","") | F26: =_xlfn.LET(_xlpm.x,VLOOKUP($B26,augment_header!$B$2:$G$72,5,FALSE),IF(_xlpm.x="","",_xlpm.x)) | G26: 4
A27: 25 | B27: NameTra_content_en | C27: =_xlfn.LET(_xlpm.x,VLOOKUP($B27,augment_header!$B$2:$G$72,2,FALSE),IF(_xlpm.x="","",_xlpm.x)) -> 名称（英文） | D27: =IF(VLOOKUP($B27,augment_header!$B$2:$G$72,3,FALSE)="√","√","") | E27: =IF(VLOOKUP($B27,augment_header!$B$2:$G$72,4,FALSE)="√","√","") | F27: =_xlfn.LET(_xlpm.x,VLOOKUP($B27,augment_header!$B$2:$G$72,5,FALSE),IF(_xlpm.x="","",_xlpm.x)) | G27: 5
A28: 26 | B28: DescriptionTra_content_zh | C28: =_xlfn.LET(_xlpm.x,VLOOKUP($B28,augment_header!$B$2:$G$72,2,FALSE),IF(_xlpm.x="","",_xlpm.x)) -> 简介（中文） | D28: =IF(VLOOKUP($B28,augment_header!$B$2:$G$72,3,FALSE)="√","√","") | E28: =IF(VLOOKUP($B28,augment_header!$B$2:$G$72,4,FALSE)="√","√","") | F28: =_xlfn.LET(_xlpm.x,VLOOKUP($B28,augment_header!$B$2:$G$72,5,FALSE),IF(_xlpm.x="","",_xlpm.x)) | G28: 10
A29: 27 | B29: DescriptionTra_content_zh_burn | C29: =_xlfn.LET(_xlpm.x,VLOOKUP($B29,augment_header!$B$2:$G$72,2,FALSE),IF(_xlpm.x="","",_xlpm.x)) -> 简介（中文/数值转换） | D29: =IF(VLOOKUP($B29,augment_header!$B$2:$G$72,3,FALSE)="√","√","") | E29: =IF(VLOOKUP($B29,augment_header!$B$2:$G$72,4,FALSE)="√","√","") | F29: =_xlfn.LET(_xlpm.x,VLOOKUP($B29,augment_header!$B$2:$G$72,5,FALSE),IF(_xlpm.x="","",_xlpm.x)) | G29: 11
A30: 28 | B30: DescriptionTra_content_en | C30: =_xlfn.LET(_xlpm.x,VLOOKUP($B30,augment_header!$B$2:$G$72,2,FALSE),IF(_xlpm.x="","",_xlpm.x)) -> 简介（英文） | D30: =IF(VLOOKUP($B30,augment_header!$B$2:$G$72,3,FALSE)="√","√","") | E30: =IF(VLOOKUP($B30,augment_header!$B$2:$G$72,4,FALSE)="√","√","") | F30: =_xlfn.LET(_xlpm.x,VLOOKUP($B30,augment_header!$B$2:$G$72,5,FALSE),IF(_xlpm.x="","",_xlpm.x)) | G30: 12
A31: 29 | B31: DescriptionTra_content_en_burn | C31: =_xlfn.LET(_xlpm.x,VLOOKUP($B31,augment_header!$B$2:$G$72,2,FALSE),IF(_xlpm.x="","",_xlpm.x)) -> 简介（英文/数值转换） | D31: =IF(VLOOKUP($B31,augment_header!$B$2:$G$72,3,FALSE)="√","√","") | E31: =IF(VLOOKUP($B31,augment_header!$B$2:$G$72,4,FALSE)="√","√","") | F31: =_xlfn.LET(_xlpm.x,VLOOKUP($B31,augment_header!$B$2:$G$72,5,FALSE),IF(_xlpm.x="","",_xlpm.x)) | G31: 13
A32: 30 | B32: AugmentTooltipTra_content_zh | C32: =_xlfn.LET(_xlpm.x,VLOOKUP($B32,augment_header!$B$2:$G$72,2,FALSE),IF(_xlpm.x="","",_xlpm.x)) -> 强化符文详细信息（中文） | D32: =IF(VLOOKUP($B32,augment_header!$B$2:$G$72,3,FALSE)="√","√","") | E32: =IF(VLOOKUP($B32,augment_header!$B$2:$G$72,4,FALSE)="√","√","") | F32: =_xlfn.LET(_xlpm.x,VLOOKUP($B32,augment_header!$B$2:$G$72,5,FALSE),IF(_xlpm.x="","",_xlpm.x)) | G32: 15
A33: 31 | B33: AugmentTooltipTra_content_zh_burn | C33: =_xlfn.LET(_xlpm.x,VLOOKUP($B33,augment_header!$B$2:$G$72,2,FALSE),IF(_xlpm.x="","",_xlpm.x)) -> 强化符文详细信息（中文/数值转换） | D33: =IF(VLOOKUP($B33,augment_header!$B$2:$G$72,3,FALSE)="√","√","") | E33: =IF(VLOOKUP($B33,augment_header!$B$2:$G$72,4,FALSE)="√","√","") | F33: =_xlfn.LET(_xlpm.x,VLOOKUP($B33,augment_header!$B$2:$G$72,5,FALSE),IF(_xlpm.x="","",_xlpm.x)) | G33: 16
A34: 32 | B34: AugmentTooltipTra_content_en | C34: =_xlfn.LET(_xlpm.x,VLOOKUP($B34,augment_header!$B$2:$G$72,2,FALSE),IF(_xlpm.x="","",_xlpm.x)) -> 强化符文详细信息（英文） | D34: =IF(VLOOKUP($B34,augment_header!$B$2:$G$72,3,FALSE)="√","√","") | E34: =IF(VLOOKUP($B34,augment_header!$B$2:$G$72,4,FALSE)="√","√","") | F34: =_xlfn.LET(_xlpm.x,VLOOKUP($B34,augment_header!$B$2:$G$72,5,FALSE),IF(_xlpm.x="","",_xlpm.x)) | G34: 17
A35: 33 | B35: AugmentTooltipTra_content_en_burn | C35: =_xlfn.LET(_xlpm.x,VLOOKUP($B35,augment_header!$B$2:$G$72,2,FALSE),IF(_xlpm.x="","",_xlpm.x)) -> 强化符文详细信息（英文/数值转换） | D35: =IF(VLOOKUP($B35,augment_header!$B$2:$G$72,3,FALSE)="√","√","") | E35: =IF(VLOOKUP($B35,augment_header!$B$2:$G$72,4,FALSE)="√","√","") | F35: =_xlfn.LET(_xlpm.x,VLOOKUP($B35,augment_header!$B$2:$G$72,5,FALSE),IF(_xlpm.x="","",_xlpm.x)) | G35: 18
A36: 34 | B36: {3696d198} {c4182067}_content_zh | C36: =_xlfn.LET(_xlpm.x,VLOOKUP($B36,augment_header!$B$2:$G$72,2,FALSE),IF(_xlpm.x="","",_xlpm.x)) -> 强化符文详细信息描述部分（中文） | D36: =IF(VLOOKUP($B36,augment_header!$B$2:$G$72,3,FALSE)="√","√","") | E36: =IF(VLOOKUP($B36,augment_header!$B$2:$G$72,4,FALSE)="√","√","") | F36: =_xlfn.LET(_xlpm.x,VLOOKUP($B36,augment_header!$B$2:$G$72,5,FALSE),IF(_xlpm.x="","",_xlpm.x))
A37: 35 | B37: {3696d198} {c4182067}_content_zh_burn | C37: =_xlfn.LET(_xlpm.x,VLOOKUP($B37,augment_header!$B$2:$G$72,2,FALSE),IF(_xlpm.x="","",_xlpm.x)) -> 强化符文详细信息描述部分（中文/数值转换） | D37: =IF(VLOOKUP($B37,augment_header!$B$2:$G$72,3,FALSE)="√","√","") | E37: =IF(VLOOKUP($B37,augment_header!$B$2:$G$72,4,FALSE)="√","√","") | F37: =_xlfn.LET(_xlpm.x,VLOOKUP($B37,augment_header!$B$2:$G$72,5,FALSE),IF(_xlpm.x="","",_xlpm.x))
A38: 36 | B38: {3696d198} {c4182067}_content_en | C38: =_xlfn.LET(_xlpm.x,VLOOKUP($B38,augment_header!$B$2:$G$72,2,FALSE),IF(_xlpm.x="","",_xlpm.x)) -> 强化符文详细信息描述部分（英文） | D38: =IF(VLOOKUP($B38,augment_header!$B$2:$G$72,3,FALSE)="√","√","") | E38: =IF(VLOOKUP($B38,augment_header!$B$2:$G$72,4,FALSE)="√","√","") | F38: =_xlfn.LET(_xlpm.x,VLOOKUP($B38,augment_header!$B$2:$G$72,5,FALSE),IF(_xlpm.x="","",_xlpm.x))
A39: 37 | B39: {3696d198} {c4182067}_content_en_burn | C39: =_xlfn.LET(_xlpm.x,VLOOKUP($B39,augment_header!$B$2:$G$72,2,FALSE),IF(_xlpm.x="","",_xlpm.x)) -> 强化符文详细信息描述部分（英文/数值转换） | D39: =IF(VLOOKUP($B39,augment_header!$B$2:$G$72,3,FALSE)="√","√","") | E39: =IF(VLOOKUP($B39,augment_header!$B$2:$G$72,4,FALSE)="√","√","") | F39: =_xlfn.LET(_xlpm.x,VLOOKUP($B39,augment_header!$B$2:$G$72,5,FALSE),IF(_xlpm.x="","",_xlpm.x))
A40: 38 | B40: {3696d198} {231af825}_content_zh | C40: =_xlfn.LET(_xlpm.x,VLOOKUP($B40,augment_header!$B$2:$G$72,2,FALSE),IF(_xlpm.x="","",_xlpm.x)) -> 强化符文详细信息追踪部分（中文） | D40: =IF(VLOOKUP($B40,augment_header!$B$2:$G$72,3,FALSE)="√","√","") | E40: =IF(VLOOKUP($B40,augment_header!$B$2:$G$72,4,FALSE)="√","√","") | F40: =_xlfn.LET(_xlpm.x,VLOOKUP($B40,augment_header!$B$2:$G$72,5,FALSE),IF(_xlpm.x="","",_xlpm.x))
A41: 39 | B41: {3696d198} {231af825}_content_zh_burn | C41: =_xlfn.LET(_xlpm.x,VLOOKUP($B41,augment_header!$B$2:$G$72,2,FALSE),IF(_xlpm.x="","",_xlpm.x)) -> 强化符文详细信息追踪部分（中文/数值转换） | D41: =IF(VLOOKUP($B41,augment_header!$B$2:$G$72,3,FALSE)="√","√","") | E41: =IF(VLOOKUP($B41,augment_header!$B$2:$G$72,4,FALSE)="√","√","") | F41: =_xlfn.LET(_xlpm.x,VLOOKUP($B41,augment_header!$B$2:$G$72,5,FALSE),IF(_xlpm.x="","",_xlpm.x))
A42: 40 | B42: {3696d198} {231af825}_content_en | C42: =_xlfn.LET(_xlpm.x,VLOOKUP($B42,augment_header!$B$2:$G$72,2,FALSE),IF(_xlpm.x="","",_xlpm.x)) -> 强化符文详细信息追踪部分（英文） | D42: =IF(VLOOKUP($B42,augment_header!$B$2:$G$72,3,FALSE)="√","√","") | E42: =IF(VLOOKUP($B42,augment_header!$B$2:$G$72,4,FALSE)="√","√","") | F42: =_xlfn.LET(_xlpm.x,VLOOKUP($B42,augment_header!$B$2:$G$72,5,FALSE),IF(_xlpm.x="","",_xlpm.x))
A43: 41 | B43: {3696d198} {231af825}_content_en_burn | C43: =_xlfn.LET(_xlpm.x,VLOOKUP($B43,augment_header!$B$2:$G$72,2,FALSE),IF(_xlpm.x="","",_xlpm.x)) -> 强化符文详细信息追踪部分（英文/数值转换） | D43: =IF(VLOOKUP($B43,augment_header!$B$2:$G$72,3,FALSE)="√","√","") | E43: =IF(VLOOKUP($B43,augment_header!$B$2:$G$72,4,FALSE)="√","√","") | F43: =_xlfn.LET(_xlpm.x,VLOOKUP($B43,augment_header!$B$2:$G$72,5,FALSE),IF(_xlpm.x="","",_xlpm.x))
A44: 42 | B44: {791eb92e} {5753a320} {c98a82ca}_content_zh | C44: =_xlfn.LET(_xlpm.x,VLOOKUP($B44,augment_header!$B$2:$G$72,2,FALSE),IF(_xlpm.x="","",_xlpm.x)) -> 满级效果简介（中文） | D44: =IF(VLOOKUP($B44,augment_header!$B$2:$G$72,3,FALSE)="√","√","") | E44: =IF(VLOOKUP($B44,augment_header!$B$2:$G$72,4,FALSE)="√","√","") | F44: =_xlfn.LET(_xlpm.x,VLOOKUP($B44,augment_header!$B$2:$G$72,5,FALSE),IF(_xlpm.x="","",_xlpm.x))
A45: 43 | B45: {791eb92e} {5753a320} {c98a82ca}_content_zh_burn | C45: =_xlfn.LET(_xlpm.x,VLOOKUP($B45,augment_header!$B$2:$G$72,2,FALSE),IF(_xlpm.x="","",_xlpm.x)) -> 满级效果简介（中文/数值转换） | D45: =IF(VLOOKUP($B45,augment_header!$B$2:$G$72,3,FALSE)="√","√","") | E45: =IF(VLOOKUP($B45,augment_header!$B$2:$G$72,4,FALSE)="√","√","") | F45: =_xlfn.LET(_xlpm.x,VLOOKUP($B45,augment_header!$B$2:$G$72,5,FALSE),IF(_xlpm.x="","",_xlpm.x))
A46: 44 | B46: {791eb92e} {5753a320} {c98a82ca}_content_en | C46: =_xlfn.LET(_xlpm.x,VLOOKUP($B46,augment_header!$B$2:$G$72,2,FALSE),IF(_xlpm.x="","",_xlpm.x)) -> 满级效果简介（英文） | D46: =IF(VLOOKUP($B46,augment_header!$B$2:$G$72,3,FALSE)="√","√","") | E46: =IF(VLOOKUP($B46,augment_header!$B$2:$G$72,4,FALSE)="√","√","") | F46: =_xlfn.LET(_xlpm.x,VLOOKUP($B46,augment_header!$B$2:$G$72,5,FALSE),IF(_xlpm.x="","",_xlpm.x))
A47: 45 | B47: {791eb92e} {5753a320} {c98a82ca}_content_en_burn | C47: =_xlfn.LET(_xlpm.x,VLOOKUP($B47,augment_header!$B$2:$G$72,2,FALSE),IF(_xlpm.x="","",_xlpm.x)) -> 满级效果简介（英文/数值转换） | D47: =IF(VLOOKUP($B47,augment_header!$B$2:$G$72,3,FALSE)="√","√","") | E47: =IF(VLOOKUP($B47,augment_header!$B$2:$G$72,4,FALSE)="√","√","") | F47: =_xlfn.LET(_xlpm.x,VLOOKUP($B47,augment_header!$B$2:$G$72,5,FALSE),IF(_xlpm.x="","",_xlpm.x))
... A52: 50 | B52: AugmentDisplayTags_content | C52: =_xlfn.LET(_xlpm.x,VLOOKUP($B52,augment_header!$B$2:$G$72,2,FALSE),IF(_xlpm.x="","",_xlpm.x)) -> 强化符文显示标签内容 | D52: =IF(VLOOKUP($B52,augment_header!$B$2:$G$72,3,FALSE)="√","√","") | E52: =IF(VLOOKUP($B52,augment_header!$B$2:$G$72,4,FALSE)="√","√","") | F52: =_xlfn.LET(_xlpm.x,VLOOKUP($B52,augment_header!$B$2:$G$72,5,FALSE),IF(_xlpm.x="","",_xlpm.x))
A53: 51 | B53: rarityValue | C53: =_xlfn.LET(_xlpm.x,VLOOKUP($B53,augment_header!$B$2:$G$72,2,FALSE),IF(_xlpm.x="","",_xlpm.x)) -> 位阶 | D53: =IF(VLOOKUP($B53,augment_header!$B$2:$G$72,3,FALSE)="√","√","") | E53: =IF(VLOOKUP($B53,augment_header!$B$2:$G$72,4,FALSE)="√","√","") -> √ | F53: =_xlfn.LET(_xlpm.x,VLOOKUP($B53,augment_header!$B$2:$G$72,5,FALSE),IF(_xlpm.x="","",_xlpm.x)) | G53: 7
A54: 52 | B54: RootSpellObject | C54: =_xlfn.LET(_xlpm.x,VLOOKUP($B54,augment_header!$B$2:$G$72,2,FALSE),IF(_xlpm.x="","",_xlpm.x)) -> 根指令对象 | D54: =IF(VLOOKUP($B54,augment_header!$B$2:$G$72,3,FALSE)="√","√","") -> √ | E54: =IF(VLOOKUP($B54,augment_header!$B$2:$G$72,4,FALSE)="√","√","") | F54: =_xlfn.LET(_xlpm.x,VLOOKUP($B54,augment_header!$B$2:$G$72,5,FALSE),IF(_xlpm.x="","",_xlpm.x)) | G54: 20
A55: 53 | B55: AdditionalSpells_Object | C55: =_xlfn.LET(_xlpm.x,VLOOKUP($B55,augment_header!$B$2:$G$72,2,FALSE),IF(_xlpm.x="","",_xlpm.x)) -> 其它指令对象 | D55: =IF(VLOOKUP($B55,augment_header!$B$2:$G$72,3,FALSE)="√","√","") -> √ | E55: =IF(VLOOKUP($B55,augment_header!$B$2:$G$72,4,FALSE)="√","√","") | F55: =_xlfn.LET(_xlpm.x,VLOOKUP($B55,augment_header!$B$2:$G$72,5,FALSE),IF(_xlpm.x="","",_xlpm.x))
A56: 54 | B56: RootSpell mSpell DataValues MaxLevel | C56: =_xlfn.LET(_xlpm.x,VLOOKUP($B56,augment_header!$B$2:$G$72,2,FALSE),IF(_xlpm.x="","",_xlpm.x)) -> 最大等级 | D56: =IF(VLOOKUP($B56,augment_header!$B$2:$G$72,3,FALSE)="√","√","") -> √ | E56: =IF(VLOOKUP($B56,augment_header!$B$2:$G$72,4,FALSE)="√","√","") | F56: =_xlfn.LET(_xlpm.x,VLOOKUP($B56,augment_header!$B$2:$G$72,5,FALSE),IF(_xlpm.x="","",_xlpm.x))
A57: 55 | B57: ResourceResolver resourceMap | C57: =_xlfn.LET(_xlpm.x,VLOOKUP($B57,augment_header!$B$2:$G$72,2,FALSE),IF(_xlpm.x="","",_xlpm.x)) -> 资源解析器映射字典 | D57: =IF(VLOOKUP($B57,augment_header!$B$2:$G$72,3,FALSE)="√","√","") -> √ | E57: =IF(VLOOKUP($B57,augment_header!$B$2:$G$72,4,FALSE)="√","√","") | F57: =_xlfn.LET(_xlpm.x,VLOOKUP($B57,augment_header!$B$2:$G$72,5,FALSE),IF(_xlpm.x="","",_xlpm.x))
A58: 56 | B58: questline {bc1b3d88} | C58: =_xlfn.LET(_xlpm.x,VLOOKUP($B58,augment_header!$B$2:$G$72,2,FALSE),IF(_xlpm.x="","",_xlpm.x)) | D58: =IF(VLOOKUP($B58,augment_header!$B$2:$G$72,3,FALSE)="√","√","") -> √ | E58: =IF(VLOOKUP($B58,augment_header!$B$2:$G$72,4,FALSE)="√","√","") | F58: =_xlfn.LET(_xlpm.x,VLOOKUP($B58,augment_header!$B$2:$G$72,5,FALSE),IF(_xlpm.x="","",_xlpm.x))
A59: 57 | B59: questline QuestName | C59: =_xlfn.LET(_xlpm.x,VLOOKUP($B59,augment_header!$B$2:$G$72,2,FALSE),IF(_xlpm.x="","",_xlpm.x)) -> 任务线代码 | D59: =IF(VLOOKUP($B59,augment_header!$B$2:$G$72,3,FALSE)="√","√","") -> √ | E59: =IF(VLOOKUP($B59,augment_header!$B$2:$G$72,4,FALSE)="√","√","") | F59: =_xlfn.LET(_xlpm.x,VLOOKUP($B59,augment_header!$B$2:$G$72,5,FALSE),IF(_xlpm.x="","",_xlpm.x))
A60: 58 | B60: questline {4796bf5f} | C60: =_xlfn.LET(_xlpm.x,VLOOKUP($B60,augment_header!$B$2:$G$72,2,FALSE),IF(_xlpm.x="","",_xlpm.x)) -> 任务线名称键 | D60: =IF(VLOOKUP($B60,augment_header!$B$2:$G$72,3,FALSE)="√","√","") | E60: =IF(VLOOKUP($B60,augment_header!$B$2:$G$72,4,FALSE)="√","√","") | F60: =_xlfn.LET(_xlpm.x,VLOOKUP($B60,augment_header!$B$2:$G$72,5,FALSE),IF(_xlpm.x="","",_xlpm.x))
A61: 59 | B61: questline {c88f1a9b} | C61: =_xlfn.LET(_xlpm.x,VLOOKUP($B61,augment_header!$B$2:$G$72,2,FALSE),IF(_xlpm.x="","",_xlpm.x)) -> 任务完成描述键 | D61: =IF(VLOOKUP($B61,augment_header!$B$2:$G$72,3,FALSE)="√","√","") -> √ | E61: =IF(VLOOKUP($B61,augment_header!$B$2:$G$72,4,FALSE)="√","√","") | F61: =_xlfn.LET(_xlpm.x,VLOOKUP($B61,augment_header!$B$2:$G$72,5,FALSE),IF(_xlpm.x="","",_xlpm.x))
A62: 60 | B62: questline {06b06978} texturePath | C62: =_xlfn.LET(_xlpm.x,VLOOKUP($B62,augment_header!$B$2:$G$72,2,FALSE),IF(_xlpm.x="","",_xlpm.x)) -> 任务栏位图标纹理路径 | D62: =IF(VLOOKUP($B62,augment_header!$B$2:$G$72,3,FALSE)="√","√","") -> √ | E62: =IF(VLOOKUP($B62,augment_header!$B$2:$G$72,4,FALSE)="√","√","") | F62: =_xlfn.LET(_xlpm.x,VLOOKUP($B62,augment_header!$B$2:$G$72,5,FALSE),IF(_xlpm.x="","",_xlpm.x))
A63: 61 | B63: questline {ee2e0dbc} | C63: =_xlfn.LET(_xlpm.x,VLOOKUP($B63,augment_header!$B$2:$G$72,2,FALSE),IF(_xlpm.x="","",_xlpm.x)) | D63: =IF(VLOOKUP($B63,augment_header!$B$2:$G$72,3,FALSE)="√","√","") -> √ | E63: =IF(VLOOKUP($B63,augment_header!$B$2:$G$72,4,FALSE)="√","√","") -> √ | F63: =_xlfn.LET(_xlpm.x,VLOOKUP($B63,augment_header!$B$2:$G$72,5,FALSE),IF(_xlpm.x="","",_xlpm.x)) -> FALSE
A64: 62 | B64: questline Milestones | C64: =_xlfn.LET(_xlpm.x,VLOOKUP($B64,augment_header!$B$2:$G$72,2,FALSE),IF(_xlpm.x="","",_xlpm.x)) -> 任务线里程信息 | D64: =IF(VLOOKUP($B64,augment_header!$B$2:$G$72,3,FALSE)="√","√","") | E64: =IF(VLOOKUP($B64,augment_header!$B$2:$G$72,4,FALSE)="√","√","") | F64: =_xlfn.LET(_xlpm.x,VLOOKUP($B64,augment_header!$B$2:$G$72,5,FALSE),IF(_xlpm.x="","",_xlpm.x))
A65: 63 | B65: questline {09d67381} | C65: =_xlfn.LET(_xlpm.x,VLOOKUP($B65,augment_header!$B$2:$G$72,2,FALSE),IF(_xlpm.x="","",_xlpm.x)) -> 任务线相关强化符文 | D65: =IF(VLOOKUP($B65,augment_header!$B$2:$G$72,3,FALSE)="√","√","") -> √ | E65: =IF(VLOOKUP($B65,augment_header!$B$2:$G$72,4,FALSE)="√","√","") | F65: =_xlfn.LET(_xlpm.x,VLOOKUP($B65,augment_header!$B$2:$G$72,5,FALSE),IF(_xlpm.x="","",_xlpm.x))
A66: 64 | B66: questline {c504ece0} | C66: =_xlfn.LET(_xlpm.x,VLOOKUP($B66,augment_header!$B$2:$G$72,2,FALSE),IF(_xlpm.x="","",_xlpm.x)) | D66: =IF(VLOOKUP($B66,augment_header!$B$2:$G$72,3,FALSE)="√","√","") -> √ | E66: =IF(VLOOKUP($B66,augment_header!$B$2:$G$72,4,FALSE)="√","√","") | F66: =_xlfn.LET(_xlpm.x,VLOOKUP($B66,augment_header!$B$2:$G$72,5,FALSE),IF(_xlpm.x="","",_xlpm.x)) -> FALSE
... A72: 70 | B72: questline {c88f1a9b}_content_en_burn | C72: =_xlfn.LET(_xlpm.x,VLOOKUP($B72,augment_header!$B$2:$G$72,2,FALSE),IF(_xlpm.x="","",_xlpm.x)) -> 任务完成描述（英文/数值转换） | D72: =IF(VLOOKUP($B72,augment_header!$B$2:$G$72,3,FALSE)="√","√","") | E72: =IF(VLOOKUP($B72,augment_header!$B$2:$G$72,4,FALSE)="√","√","") | F72: =_xlfn.LET(_xlpm.x,VLOOKUP($B72,augment_header!$B$2:$G$72,5,FALSE),IF(_xlpm.x="","",_xlpm.x))

Sheet KiwiAugment_header
A1: Index | B1: Key | C1: Value | D1: DirectlyImport? | E1: Flexible | F1: defaultValue | G1: OutputOrder
A2: 0 | B2: isClassic | C2: 存在于经典模式版 | G2: 7
A3: 1 | B3: augmentSet | C3: 强化符文套装列表 | G3: 12
A4: 2 | B4: augmentSet_contents_zh | C4: 强化符文套装（中文） | G4: 13
A5: 3 | B5: augmentSet_contents_en | C5: 强化符文套装（英文） | G5: 14
A6: 4 | B6: key | C6: =_xlfn.LET(_xlpm.x,VLOOKUP($B6,augment_header!$B$2:$G$72,2,FALSE),IF(_xlpm.x="","",_xlpm.x)) -> 主键 | D6: =IF(VLOOKUP($B6,augment_header!$B$2:$G$72,3,FALSE)="√","√","") -> √ | E6: =IF(VLOOKUP($B6,augment_header!$B$2:$G$72,4,FALSE)="√","√","") | F6: =_xlfn.LET(_xlpm.x,VLOOKUP($B6,augment_header!$B$2:$G$72,5,FALSE),IF(_xlpm.x="","",_xlpm.x)) | G6: 0
A7: 5 | B7: AugmentNameId | C7: =_xlfn.LET(_xlpm.x,VLOOKUP($B7,augment_header!$B$2:$G$72,2,FALSE),IF(_xlpm.x="","",_xlpm.x)) -> 强化符文代码 | D7: =IF(VLOOKUP($B7,augment_header!$B$2:$G$72,3,FALSE)="√","√","") -> √ | E7: =IF(VLOOKUP($B7,augment_header!$B$2:$G$72,4,FALSE)="√","√","") | F7: =_xlfn.LET(_xlpm.x,VLOOKUP($B7,augment_header!$B$2:$G$72,5,FALSE),IF(_xlpm.x="","",_xlpm.x)) | G7: 1
A8: 6 | B8: Enabled | C8: =_xlfn.LET(_xlpm.x,VLOOKUP($B8,augment_header!$B$2:$G$72,2,FALSE),IF(_xlpm.x="","",_xlpm.x)) -> 可用性 | D8: =IF(VLOOKUP($B8,augment_header!$B$2:$G$72,3,FALSE)="√","√","") -> √ | E8: =IF(VLOOKUP($B8,augment_header!$B$2:$G$72,4,FALSE)="√","√","") -> √ | F8: =_xlfn.LET(_xlpm.x,VLOOKUP($B8,augment_header!$B$2:$G$72,5,FALSE),IF(_xlpm.x="","",_xlpm.x)) -> TRUE | G8: 3
A9: 7 | B9: NameTra | C9: =_xlfn.LET(_xlpm.x,VLOOKUP($B9,augment_header!$B$2:$G$72,2,FALSE),IF(_xlpm.x="","",_xlpm.x)) -> 名称键 | D9: =IF(VLOOKUP($B9,augment_header!$B$2:$G$72,3,FALSE)="√","√","") -> √ | E9: =IF(VLOOKUP($B9,augment_header!$B$2:$G$72,4,FALSE)="√","√","") | F9: =_xlfn.LET(_xlpm.x,VLOOKUP($B9,augment_header!$B$2:$G$72,5,FALSE),IF(_xlpm.x="","",_xlpm.x)) | G9: 4
A10: 8 | B10: DescriptionTra | C10: =_xlfn.LET(_xlpm.x,VLOOKUP($B10,augment_header!$B$2:$G$72,2,FALSE),IF(_xlpm.x="","",_xlpm.x)) -> 简介键 | D10: =IF(VLOOKUP($B10,augment_header!$B$2:$G$72,3,FALSE)="√","√","") -> √ | E10: =IF(VLOOKUP($B10,augment_header!$B$2:$G$72,4,FALSE)="√","√","") | F10: =_xlfn.LET(_xlpm.x,VLOOKUP($B10,augment_header!$B$2:$G$72,5,FALSE),IF(_xlpm.x="","",_xlpm.x)) | G10: 23
A11: 9 | B11: AugmentTooltipTra | C11: =_xlfn.LET(_xlpm.x,VLOOKUP($B11,augment_header!$B$2:$G$72,2,FALSE),IF(_xlpm.x="","",_xlpm.x)) -> 强化符文详细信息键 | D11: =IF(VLOOKUP($B11,augment_header!$B$2:$G$72,3,FALSE)="√","√","") -> √ | E11: =IF(VLOOKUP($B11,augment_header!$B$2:$G$72,4,FALSE)="√","√","") | F11: =_xlfn.LET(_xlpm.x,VLOOKUP($B11,augment_header!$B$2:$G$72,5,FALSE),IF(_xlpm.x="","",_xlpm.x)) | G11: 28
A12: 10 | B12: RootSpell | C12: =_xlfn.LET(_xlpm.x,VLOOKUP($B12,augment_header!$B$2:$G$72,2,FALSE),IF(_xlpm.x="","",_xlpm.x)) -> 根指令主键 | D12: =IF(VLOOKUP($B12,augment_header!$B$2:$G$72,3,FALSE)="√","√","") -> √ | E12: =IF(VLOOKUP($B12,augment_header!$B$2:$G$72,4,FALSE)="√","√","") | F12: =_xlfn.LET(_xlpm.x,VLOOKUP($B12,augment_header!$B$2:$G$72,5,FALSE),IF(_xlpm.x="","",_xlpm.x)) | G12: 48
A13: 11 | B13: AdditionalSpells | C13: =_xlfn.LET(_xlpm.x,VLOOKUP($B13,augment_header!$B$2:$G$72,2,FALSE),IF(_xlpm.x="","",_xlpm.x)) -> 其它指令主键列表 | D13: =IF(VLOOKUP($B13,augment_header!$B$2:$G$72,3,FALSE)="√","√","") -> √ | E13: =IF(VLOOKUP($B13,augment_header!$B$2:$G$72,4,FALSE)="√","√","") | F13: =_xlfn.LET(_xlpm.x,VLOOKUP($B13,augment_header!$B$2:$G$72,5,FALSE),IF(_xlpm.x="","",_xlpm.x)) | G13: 50
A14: 12 | B14: mAugmentTags | C14: =_xlfn.LET(_xlpm.x,VLOOKUP($B14,augment_header!$B$2:$G$72,2,FALSE),IF(_xlpm.x="","",_xlpm.x)) -> 强化符文标签 | D14: =IF(VLOOKUP($B14,augment_header!$B$2:$G$72,3,FALSE)="√","√","") -> √ | E14: =IF(VLOOKUP($B14,augment_header!$B$2:$G$72,4,FALSE)="√","√","") -> √ | F14: =_xlfn.LET(_xlpm.x,VLOOKUP($B14,augment_header!$B$2:$G$72,5,FALSE),IF(_xlpm.x="","",_xlpm.x)) | G14: 17
A15: 13 | B15: mBuildTags | C15: =_xlfn.LET(_xlpm.x,VLOOKUP($B15,augment_header!$B$2:$G$72,2,FALSE),IF(_xlpm.x="","",_xlpm.x)) -> 构建标签 | D15: =IF(VLOOKUP($B15,augment_header!$B$2:$G$72,3,FALSE)="√","√","") -> √ | E15: =IF(VLOOKUP($B15,augment_header!$B$2:$G$72,4,FALSE)="√","√","") -> √ | F15: =_xlfn.LET(_xlpm.x,VLOOKUP($B15,augment_header!$B$2:$G$72,5,FALSE),IF(_xlpm.x="","",_xlpm.x)) | G15: 18
A16: 14 | B16: {3696d198} {c4182067} | C16: =_xlfn.LET(_xlpm.x,VLOOKUP($B16,augment_header!$B$2:$G$72,2,FALSE),IF(_xlpm.x="","",_xlpm.x)) -> 强化符文详细信息描述部分键 | D16: =IF(VLOOKUP($B16,augment_header!$B$2:$G$72,3,FALSE)="√","√","") -> √ | E16: =IF(VLOOKUP($B16,augment_header!$B$2:$G$72,4,FALSE)="√","√","") | F16: =_xlfn.LET(_xlpm.x,VLOOKUP($B16,augment_header!$B$2:$G$72,5,FALSE),IF(_xlpm.x="","",_xlpm.x)) | G16: 33
A17: 15 | B17: {3696d198} {231af825} | C17: =_xlfn.LET(_xlpm.x,VLOOKUP($B17,augment_header!$B$2:$G$72,2,FALSE),IF(_xlpm.x="","",_xlpm.x)) -> 强化符文详细信息追踪部分键 | D17: =IF(VLOOKUP($B17,augment_header!$B$2:$G$72,3,FALSE)="√","√","") -> √ | E17: =IF(VLOOKUP($B17,augment_header!$B$2:$G$72,4,FALSE)="√","√","") -> √ | F17: =_xlfn.LET(_xlpm.x,VLOOKUP($B17,augment_header!$B$2:$G$72,5,FALSE),IF(_xlpm.x="","",_xlpm.x)) | G17: 38
A18: 16 | B18: {791eb92e} {5753a320} {c98a82ca} | C18: =_xlfn.LET(_xlpm.x,VLOOKUP($B18,augment_header!$B$2:$G$72,2,FALSE),IF(_xlpm.x="","",_xlpm.x)) -> 满级效果简介键 | D18: =IF(VLOOKUP($B18,augment_header!$B$2:$G$72,3,FALSE)="√","√","") -> √ | E18: =IF(VLOOKUP($B18,augment_header!$B$2:$G$72,4,FALSE)="√","√","") | F18: =_xlfn.LET(_xlpm.x,VLOOKUP($B18,augment_header!$B$2:$G$72,5,FALSE),IF(_xlpm.x="","",_xlpm.x))
A19: 17 | B19: {791eb92e} {5753a320} {05835d27} | C19: =_xlfn.LET(_xlpm.x,VLOOKUP($B19,augment_header!$B$2:$G$72,2,FALSE),IF(_xlpm.x="","",_xlpm.x)) -> 满级效果详细信息键 | D19: =IF(VLOOKUP($B19,augment_header!$B$2:$G$72,3,FALSE)="√","√","") -> √ | E19: =IF(VLOOKUP($B19,augment_header!$B$2:$G$72,4,FALSE)="√","√","") | F19: =_xlfn.LET(_xlpm.x,VLOOKUP($B19,augment_header!$B$2:$G$72,5,FALSE),IF(_xlpm.x="","",_xlpm.x))
A20: 18 | B20: AugmentLargeIconPath | C20: =_xlfn.LET(_xlpm.x,VLOOKUP($B20,augment_header!$B$2:$G$72,2,FALSE),IF(_xlpm.x="","",_xlpm.x)) -> 强化符文大图标路径 | D20: =IF(VLOOKUP($B20,augment_header!$B$2:$G$72,3,FALSE)="√","√","") -> √ | E20: =IF(VLOOKUP($B20,augment_header!$B$2:$G$72,4,FALSE)="√","√","") | F20: =_xlfn.LET(_xlpm.x,VLOOKUP($B20,augment_header!$B$2:$G$72,5,FALSE),IF(_xlpm.x="","",_xlpm.x)) | G20: 56
A21: 19 | B21: AugmentSmallIconPath | C21: =_xlfn.LET(_xlpm.x,VLOOKUP($B21,augment_header!$B$2:$G$72,2,FALSE),IF(_xlpm.x="","",_xlpm.x)) -> 强化符文小图标路径 | D21: =IF(VLOOKUP($B21,augment_header!$B$2:$G$72,3,FALSE)="√","√","") -> √ | E21: =IF(VLOOKUP($B21,augment_header!$B$2:$G$72,4,FALSE)="√","√","") | F21: =_xlfn.LET(_xlpm.x,VLOOKUP($B21,augment_header!$B$2:$G$72,5,FALSE),IF(_xlpm.x="","",_xlpm.x)) | G21: 57
A22: 20 | B22: {815dad28} | C22: =_xlfn.LET(_xlpm.x,VLOOKUP($B22,augment_header!$B$2:$G$72,2,FALSE),IF(_xlpm.x="","",_xlpm.x)) -> 次级稀有度 | D22: =IF(VLOOKUP($B22,augment_header!$B$2:$G$72,3,FALSE)="√","√","") -> √ | E22: =IF(VLOOKUP($B22,augment_header!$B$2:$G$72,4,FALSE)="√","√","") -> √ | F22: =_xlfn.LET(_xlpm.x,VLOOKUP($B22,augment_header!$B$2:$G$72,5,FALSE),IF(_xlpm.x="","",_xlpm.x))
A23: 21 | B23: AugmentDisplayTags | C23: =_xlfn.LET(_xlpm.x,VLOOKUP($B23,augment_header!$B$2:$G$72,2,FALSE),IF(_xlpm.x="","",_xlpm.x)) -> 强化符文显示标签 | D23: =IF(VLOOKUP($B23,augment_header!$B$2:$G$72,3,FALSE)="√","√","") -> √ | E23: =IF(VLOOKUP($B23,augment_header!$B$2:$G$72,4,FALSE)="√","√","") | F23: =_xlfn.LET(_xlpm.x,VLOOKUP($B23,augment_header!$B$2:$G$72,5,FALSE),IF(_xlpm.x="","",_xlpm.x)) | G23: 10
A24: 22 | B24: rarity | C24: =_xlfn.LET(_xlpm.x,VLOOKUP($B24,augment_header!$B$2:$G$72,2,FALSE),IF(_xlpm.x="","",_xlpm.x)) -> 稀有度 | D24: =IF(VLOOKUP($B24,augment_header!$B$2:$G$72,3,FALSE)="√","√","") -> √ | E24: =IF(VLOOKUP($B24,augment_header!$B$2:$G$72,4,FALSE)="√","√","") -> √ | F24: =_xlfn.LET(_xlpm.x,VLOOKUP($B24,augment_header!$B$2:$G$72,5,FALSE),IF(_xlpm.x="","",_xlpm.x)) | G24: 8
A25: 23 | B25: {ed593c9c} | C25: =_xlfn.LET(_xlpm.x,VLOOKUP($B25,augment_header!$B$2:$G$72,2,FALSE),IF(_xlpm.x="","",_xlpm.x)) -> 不占用栏位 | D25: =IF(VLOOKUP($B25,augment_header!$B$2:$G$72,3,FALSE)="√","√","") -> √ | E25: =IF(VLOOKUP($B25,augment_header!$B$2:$G$72,4,FALSE)="√","√","") -> √ | F25: =_xlfn.LET(_xlpm.x,VLOOKUP($B25,augment_header!$B$2:$G$72,5,FALSE),IF(_xlpm.x="","",_xlpm.x)) -> FALSE | G25: 19
A26: 24 | B26: AugmentPlatformId | C26: =_xlfn.LET(_xlpm.x,VLOOKUP($B26,augment_header!$B$2:$G$72,2,FALSE),IF(_xlpm.x="","",_xlpm.x)) -> 强化符文序号 | D26: =IF(VLOOKUP($B26,augment_header!$B$2:$G$72,3,FALSE)="√","√","") -> √ | E26: =IF(VLOOKUP($B26,augment_header!$B$2:$G$72,4,FALSE)="√","√","") | F26: =_xlfn.LET(_xlpm.x,VLOOKUP($B26,augment_header!$B$2:$G$72,5,FALSE),IF(_xlpm.x="","",_xlpm.x)) -> -1 | G26: 2
A27: 25 | B27: QuestData Quest | C27: =_xlfn.LET(_xlpm.x,VLOOKUP($B27,augment_header!$B$2:$G$72,2,FALSE),IF(_xlpm.x="","",_xlpm.x)) -> 任务线主键 | D27: =IF(VLOOKUP($B27,augment_header!$B$2:$G$72,3,FALSE)="√","√","") -> √ | E27: =IF(VLOOKUP($B27,augment_header!$B$2:$G$72,4,FALSE)="√","√","") -> √ | F27: =_xlfn.LET(_xlpm.x,VLOOKUP($B27,augment_header!$B$2:$G$72,5,FALSE),IF(_xlpm.x="","",_xlpm.x)) | G27: 52
A28: 26 | B28: {e3a02eac} | C28: =_xlfn.LET(_xlpm.x,VLOOKUP($B28,augment_header!$B$2:$G$72,2,FALSE),IF(_xlpm.x="","",_xlpm.x)) -> 技能重载 | D28: =IF(VLOOKUP($B28,augment_header!$B$2:$G$72,3,FALSE)="√","√","") -> √ | E28: =IF(VLOOKUP($B28,augment_header!$B$2:$G$72,4,FALSE)="√","√","") -> √ | F28: =_xlfn.LET(_xlpm.x,VLOOKUP($B28,augment_header!$B$2:$G$72,5,FALSE),IF(_xlpm.x="","",_xlpm.x)) -> FALSE | G28: 20
A29: 27 | B29: ResourceResolver | C29: =_xlfn.LET(_xlpm.x,VLOOKUP($B29,augment_header!$B$2:$G$72,2,FALSE),IF(_xlpm.x="","",_xlpm.x)) -> 资源解析器主键 | D29: =IF(VLOOKUP($B29,augment_header!$B$2:$G$72,3,FALSE)="√","√","") -> √ | E29: =IF(VLOOKUP($B29,augment_header!$B$2:$G$72,4,FALSE)="√","√","") -> √ | F29: =_xlfn.LET(_xlpm.x,VLOOKUP($B29,augment_header!$B$2:$G$72,5,FALSE),IF(_xlpm.x="","",_xlpm.x)) | G29: 54
A30: 28 | B30: NameTra_content_zh | C30: =_xlfn.LET(_xlpm.x,VLOOKUP($B30,augment_header!$B$2:$G$72,2,FALSE),IF(_xlpm.x="","",_xlpm.x)) -> 名称（中文） | D30: =IF(VLOOKUP($B30,augment_header!$B$2:$G$72,3,FALSE)="√","√","") | E30: =IF(VLOOKUP($B30,augment_header!$B$2:$G$72,4,FALSE)="√","√","") | F30: =_xlfn.LET(_xlpm.x,VLOOKUP($B30,augment_header!$B$2:$G$72,5,FALSE),IF(_xlpm.x="","",_xlpm.x)) | G30: 5
A31: 29 | B31: NameTra_content_en | C31: =_xlfn.LET(_xlpm.x,VLOOKUP($B31,augment_header!$B$2:$G$72,2,FALSE),IF(_xlpm.x="","",_xlpm.x)) -> 名称（英文） | D31: =IF(VLOOKUP($B31,augment_header!$B$2:$G$72,3,FALSE)="√","√","") | E31: =IF(VLOOKUP($B31,augment_header!$B$2:$G$72,4,FALSE)="√","√","") | F31: =_xlfn.LET(_xlpm.x,VLOOKUP($B31,augment_header!$B$2:$G$72,5,FALSE),IF(_xlpm.x="","",_xlpm.x)) | G31: 6
A32: 30 | B32: DescriptionTra_content_zh | C32: =_xlfn.LET(_xlpm.x,VLOOKUP($B32,augment_header!$B$2:$G$72,2,FALSE),IF(_xlpm.x="","",_xlpm.x)) -> 简介（中文） | D32: =IF(VLOOKUP($B32,augment_header!$B$2:$G$72,3,FALSE)="√","√","") | E32: =IF(VLOOKUP($B32,augment_header!$B$2:$G$72,4,FALSE)="√","√","") | F32: =_xlfn.LET(_xlpm.x,VLOOKUP($B32,augment_header!$B$2:$G$72,5,FALSE),IF(_xlpm.x="","",_xlpm.x)) | G32: 24
A33: 31 | B33: DescriptionTra_content_zh_burn | C33: =_xlfn.LET(_xlpm.x,VLOOKUP($B33,augment_header!$B$2:$G$72,2,FALSE),IF(_xlpm.x="","",_xlpm.x)) -> 简介（中文/数值转换） | D33: =IF(VLOOKUP($B33,augment_header!$B$2:$G$72,3,FALSE)="√","√","") | E33: =IF(VLOOKUP($B33,augment_header!$B$2:$G$72,4,FALSE)="√","√","") | F33: =_xlfn.LET(_xlpm.x,VLOOKUP($B33,augment_header!$B$2:$G$72,5,FALSE),IF(_xlpm.x="","",_xlpm.x)) | G33: 25
A34: 32 | B34: DescriptionTra_content_en | C34: =_xlfn.LET(_xlpm.x,VLOOKUP($B34,augment_header!$B$2:$G$72,2,FALSE),IF(_xlpm.x="","",_xlpm.x)) -> 简介（英文） | D34: =IF(VLOOKUP($B34,augment_header!$B$2:$G$72,3,FALSE)="√","√","") | E34: =IF(VLOOKUP($B34,augment_header!$B$2:$G$72,4,FALSE)="√","√","") | F34: =_xlfn.LET(_xlpm.x,VLOOKUP($B34,augment_header!$B$2:$G$72,5,FALSE),IF(_xlpm.x="","",_xlpm.x)) | G34: 26
... A47: 45 | B47: {3696d198} {231af825}_content_en_burn | C47: =_xlfn.LET(_xlpm.x,VLOOKUP($B47,augment_header!$B$2:$G$72,2,FALSE),IF(_xlpm.x="","",_xlpm.x)) -> 强化符文详细信息追踪部分（英文/数值转换） | D47: =IF(VLOOKUP($B47,augment_header!$B$2:$G$72,3,FALSE)="√","√","") | E47: =IF(VLOOKUP($B47,augment_header!$B$2:$G$72,4,FALSE)="√","√","") | F47: =_xlfn.LET(_xlpm.x,VLOOKUP($B47,augment_header!$B$2:$G$72,5,FALSE),IF(_xlpm.x="","",_xlpm.x)) | G47: 42
A48: 46 | B48: {791eb92e} {5753a320} {c98a82ca}_content_zh | C48: =_xlfn.LET(_xlpm.x,VLOOKUP($B48,augment_header!$B$2:$G$72,2,FALSE),IF(_xlpm.x="","",_xlpm.x)) -> 满级效果简介（中文） | D48: =IF(VLOOKUP($B48,augment_header!$B$2:$G$72,3,FALSE)="√","√","") | E48: =IF(VLOOKUP($B48,augment_header!$B$2:$G$72,4,FALSE)="√","√","") | F48: =_xlfn.LET(_xlpm.x,VLOOKUP($B48,augment_header!$B$2:$G$72,5,FALSE),IF(_xlpm.x="","",_xlpm.x))
A49: 47 | B49: {791eb92e} {5753a320} {c98a82ca}_content_zh_burn | C49: =_xlfn.LET(_xlpm.x,VLOOKUP($B49,augment_header!$B$2:$G$72,2,FALSE),IF(_xlpm.x="","",_xlpm.x)) -> 满级效果简介（中文/数值转换） | D49: =IF(VLOOKUP($B49,augment_header!$B$2:$G$72,3,FALSE)="√","√","") | E49: =IF(VLOOKUP($B49,augment_header!$B$2:$G$72,4,FALSE)="√","√","") | F49: =_xlfn.LET(_xlpm.x,VLOOKUP($B49,augment_header!$B$2:$G$72,5,FALSE),IF(_xlpm.x="","",_xlpm.x))
A50: 48 | B50: {791eb92e} {5753a320} {c98a82ca}_content_en | C50: =_xlfn.LET(_xlpm.x,VLOOKUP($B50,augment_header!$B$2:$G$72,2,FALSE),IF(_xlpm.x="","",_xlpm.x)) -> 满级效果简介（英文） | D50: =IF(VLOOKUP($B50,augment_header!$B$2:$G$72,3,FALSE)="√","√","") | E50: =IF(VLOOKUP($B50,augment_header!$B$2:$G$72,4,FALSE)="√","√","") | F50: =_xlfn.LET(_xlpm.x,VLOOKUP($B50,augment_header!$B$2:$G$72,5,FALSE),IF(_xlpm.x="","",_xlpm.x))
A51: 49 | B51: {791eb92e} {5753a320} {c98a82ca}_content_en_burn | C51: =_xlfn.LET(_xlpm.x,VLOOKUP($B51,augment_header!$B$2:$G$72,2,FALSE),IF(_xlpm.x="","",_xlpm.x)) -> 满级效果简介（英文/数值转换） | D51: =IF(VLOOKUP($B51,augment_header!$B$2:$G$72,3,FALSE)="√","√","") | E51: =IF(VLOOKUP($B51,augment_header!$B$2:$G$72,4,FALSE)="√","√","") | F51: =_xlfn.LET(_xlpm.x,VLOOKUP($B51,augment_header!$B$2:$G$72,5,FALSE),IF(_xlpm.x="","",_xlpm.x))
A52: 50 | B52: {791eb92e} {5753a320} {05835d27}_content_zh | C52: =_xlfn.LET(_xlpm.x,VLOOKUP($B52,augment_header!$B$2:$G$72,2,FALSE),IF(_xlpm.x="","",_xlpm.x)) -> 满级效果详细信息（中文） | D52: =IF(VLOOKUP($B52,augment_header!$B$2:$G$72,3,FALSE)="√","√","") | E52: =IF(VLOOKUP($B52,augment_header!$B$2:$G$72,4,FALSE)="√","√","") | F52: =_xlfn.LET(_xlpm.x,VLOOKUP($B52,augment_header!$B$2:$G$72,5,FALSE),IF(_xlpm.x="","",_xlpm.x))
A53: 51 | B53: {791eb92e} {5753a320} {05835d27}_content_zh_burn | C53: =_xlfn.LET(_xlpm.x,VLOOKUP($B53,augment_header!$B$2:$G$72,2,FALSE),IF(_xlpm.x="","",_xlpm.x)) -> 满级效果详细信息（中文/数值转换） | D53: =IF(VLOOKUP($B53,augment_header!$B$2:$G$72,3,FALSE)="√","√","") | E53: =IF(VLOOKUP($B53,augment_header!$B$2:$G$72,4,FALSE)="√","√","") | F53: =_xlfn.LET(_xlpm.x,VLOOKUP($B53,augment_header!$B$2:$G$72,5,FALSE),IF(_xlpm.x="","",_xlpm.x))
A54: 52 | B54: {791eb92e} {5753a320} {05835d27}_content_en | C54: =_xlfn.LET(_xlpm.x,VLOOKUP($B54,augment_header!$B$2:$G$72,2,FALSE),IF(_xlpm.x="","",_xlpm.x)) -> 满级效果详细信息（英文） | D54: =IF(VLOOKUP($B54,augment_header!$B$2:$G$72,3,FALSE)="√","√","") | E54: =IF(VLOOKUP($B54,augment_header!$B$2:$G$72,4,FALSE)="√","√","") | F54: =_xlfn.LET(_xlpm.x,VLOOKUP($B54,augment_header!$B$2:$G$72,5,FALSE),IF(_xlpm.x="","",_xlpm.x))
A55: 53 | B55: {791eb92e} {5753a320} {05835d27}_content_en_burn | C55: =_xlfn.LET(_xlpm.x,VLOOKUP($B55,augment_header!$B$2:$G$72,2,FALSE),IF(_xlpm.x="","",_xlpm.x)) -> 满级效果详细信息（英文/数值转换） | D55: =IF(VLOOKUP($B55,augment_header!$B$2:$G$72,3,FALSE)="√","√","") | E55: =IF(VLOOKUP($B55,augment_header!$B$2:$G$72,4,FALSE)="√","√","") | F55: =_xlfn.LET(_xlpm.x,VLOOKUP($B55,augment_header!$B$2:$G$72,5,FALSE),IF(_xlpm.x="","",_xlpm.x))
A56: 54 | B56: AugmentDisplayTags_content | C56: =_xlfn.LET(_xlpm.x,VLOOKUP($B56,augment_header!$B$2:$G$72,2,FALSE),IF(_xlpm.x="","",_xlpm.x)) -> 强化符文显示标签内容 | D56: =IF(VLOOKUP($B56,augment_header!$B$2:$G$72,3,FALSE)="√","√","") | E56: =IF(VLOOKUP($B56,augment_header!$B$2:$G$72,4,FALSE)="√","√","") | F56: =_xlfn.LET(_xlpm.x,VLOOKUP($B56,augment_header!$B$2:$G$72,5,FALSE),IF(_xlpm.x="","",_xlpm.x)) | G56: 11
A57: 55 | B57: rarityValue | C57: =_xlfn.LET(_xlpm.x,VLOOKUP($B57,augment_header!$B$2:$G$72,2,FALSE),IF(_xlpm.x="","",_xlpm.x)) -> 位阶 | D57: =IF(VLOOKUP($B57,augment_header!$B$2:$G$72,3,FALSE)="√","√","") | E57: =IF(VLOOKUP($B57,augment_header!$B$2:$G$72,4,FALSE)="√","√","") -> √ | F57: =_xlfn.LET(_xlpm.x,VLOOKUP($B57,augment_header!$B$2:$G$72,5,FALSE),IF(_xlpm.x="","",_xlpm.x)) | G57: 9
A58: 56 | B58: RootSpellObject | C58: =_xlfn.LET(_xlpm.x,VLOOKUP($B58,augment_header!$B$2:$G$72,2,FALSE),IF(_xlpm.x="","",_xlpm.x)) -> 根指令对象 | D58: =IF(VLOOKUP($B58,augment_header!$B$2:$G$72,3,FALSE)="√","√","") -> √ | E58: =IF(VLOOKUP($B58,augment_header!$B$2:$G$72,4,FALSE)="√","√","") | F58: =_xlfn.LET(_xlpm.x,VLOOKUP($B58,augment_header!$B$2:$G$72,5,FALSE),IF(_xlpm.x="","",_xlpm.x)) | G58: 49
A59: 57 | B59: AdditionalSpells_Object | C59: =_xlfn.LET(_xlpm.x,VLOOKUP($B59,augment_header!$B$2:$G$72,2,FALSE),IF(_xlpm.x="","",_xlpm.x)) -> 其它指令对象 | D59: =IF(VLOOKUP($B59,augment_header!$B$2:$G$72,3,FALSE)="√","√","") -> √ | E59: =IF(VLOOKUP($B59,augment_header!$B$2:$G$72,4,FALSE)="√","√","") | F59: =_xlfn.LET(_xlpm.x,VLOOKUP($B59,augment_header!$B$2:$G$72,5,FALSE),IF(_xlpm.x="","",_xlpm.x)) | G59: 51
A60: 58 | B60: RootSpell mSpell DataValues MaxLevel | C60: =_xlfn.LET(_xlpm.x,VLOOKUP($B60,augment_header!$B$2:$G$72,2,FALSE),IF(_xlpm.x="","",_xlpm.x)) -> 最大等级 | D60: =IF(VLOOKUP($B60,augment_header!$B$2:$G$72,3,FALSE)="√","√","") -> √ | E60: =IF(VLOOKUP($B60,augment_header!$B$2:$G$72,4,FALSE)="√","√","") | F60: =_xlfn.LET(_xlpm.x,VLOOKUP($B60,augment_header!$B$2:$G$72,5,FALSE),IF(_xlpm.x="","",_xlpm.x))
A61: 59 | B61: ResourceResolver resourceMap | C61: =_xlfn.LET(_xlpm.x,VLOOKUP($B61,augment_header!$B$2:$G$72,2,FALSE),IF(_xlpm.x="","",_xlpm.x)) -> 资源解析器映射字典 | D61: =IF(VLOOKUP($B61,augment_header!$B$2:$G$72,3,FALSE)="√","√","") -> √ | E61: =IF(VLOOKUP($B61,augment_header!$B$2:$G$72,4,FALSE)="√","√","") | F61: =_xlfn.LET(_xlpm.x,VLOOKUP($B61,augment_header!$B$2:$G$72,5,FALSE),IF(_xlpm.x="","",_xlpm.x)) | G61: 55
A62: 60 | B62: questline {bc1b3d88} | C62: =_xlfn.LET(_xlpm.x,VLOOKUP($B62,augment_header!$B$2:$G$72,2,FALSE),IF(_xlpm.x="","",_xlpm.x)) | D62: =IF(VLOOKUP($B62,augment_header!$B$2:$G$72,3,FALSE)="√","√","") -> √ | E62: =IF(VLOOKUP($B62,augment_header!$B$2:$G$72,4,FALSE)="√","√","") | F62: =_xlfn.LET(_xlpm.x,VLOOKUP($B62,augment_header!$B$2:$G$72,5,FALSE),IF(_xlpm.x="","",_xlpm.x)) | G62: 15
A63: 61 | B63: questline QuestName | C63: =_xlfn.LET(_xlpm.x,VLOOKUP($B63,augment_header!$B$2:$G$72,2,FALSE),IF(_xlpm.x="","",_xlpm.x)) -> 任务线代码 | D63: =IF(VLOOKUP($B63,augment_header!$B$2:$G$72,3,FALSE)="√","√","") -> √ | E63: =IF(VLOOKUP($B63,augment_header!$B$2:$G$72,4,FALSE)="√","√","") | F63: =_xlfn.LET(_xlpm.x,VLOOKUP($B63,augment_header!$B$2:$G$72,5,FALSE),IF(_xlpm.x="","",_xlpm.x)) | G63: 16
A64: 62 | B64: questline {4796bf5f} | C64: =_xlfn.LET(_xlpm.x,VLOOKUP($B64,augment_header!$B$2:$G$72,2,FALSE),IF(_xlpm.x="","",_xlpm.x)) -> 任务线名称键 | D64: =IF(VLOOKUP($B64,augment_header!$B$2:$G$72,3,FALSE)="√","√","") | E64: =IF(VLOOKUP($B64,augment_header!$B$2:$G$72,4,FALSE)="√","√","") | F64: =_xlfn.LET(_xlpm.x,VLOOKUP($B64,augment_header!$B$2:$G$72,5,FALSE),IF(_xlpm.x="","",_xlpm.x))
A65: 63 | B65: questline {c88f1a9b} | C65: =_xlfn.LET(_xlpm.x,VLOOKUP($B65,augment_header!$B$2:$G$72,2,FALSE),IF(_xlpm.x="","",_xlpm.x)) -> 任务完成描述键 | D65: =IF(VLOOKUP($B65,augment_header!$B$2:$G$72,3,FALSE)="√","√","") -> √ | E65: =IF(VLOOKUP($B65,augment_header!$B$2:$G$72,4,FALSE)="√","√","") | F65: =_xlfn.LET(_xlpm.x,VLOOKUP($B65,augment_header!$B$2:$G$72,5,FALSE),IF(_xlpm.x="","",_xlpm.x)) | G65: 43
A66: 64 | B66: questline {06b06978} texturePath | C66: =_xlfn.LET(_xlpm.x,VLOOKUP($B66,augment_header!$B$2:$G$72,2,FALSE),IF(_xlpm.x="","",_xlpm.x)) -> 任务栏位图标纹理路径 | D66: =IF(VLOOKUP($B66,augment_header!$B$2:$G$72,3,FALSE)="√","√","") -> √ | E66: =IF(VLOOKUP($B66,augment_header!$B$2:$G$72,4,FALSE)="√","√","") | F66: =_xlfn.LET(_xlpm.x,VLOOKUP($B66,augment_header!$B$2:$G$72,5,FALSE),IF(_xlpm.x="","",_xlpm.x)) | G66: 58
A67: 65 | B67: questline {ee2e0dbc} | C67: =_xlfn.LET(_xlpm.x,VLOOKUP($B67,augment_header!$B$2:$G$72,2,FALSE),IF(_xlpm.x="","",_xlpm.x)) | D67: =IF(VLOOKUP($B67,augment_header!$B$2:$G$72,3,FALSE)="√","√","") -> √ | E67: =IF(VLOOKUP($B67,augment_header!$B$2:$G$72,4,FALSE)="√","√","") -> √ | F67: =_xlfn.LET(_xlpm.x,VLOOKUP($B67,augment_header!$B$2:$G$72,5,FALSE),IF(_xlpm.x="","",_xlpm.x)) -> FALSE | G67: 21
A68: 66 | B68: questline Milestones | C68: =_xlfn.LET(_xlpm.x,VLOOKUP($B68,augment_header!$B$2:$G$72,2,FALSE),IF(_xlpm.x="","",_xlpm.x)) -> 任务线里程信息 | D68: =IF(VLOOKUP($B68,augment_header!$B$2:$G$72,3,FALSE)="√","√","") | E68: =IF(VLOOKUP($B68,augment_header!$B$2:$G$72,4,FALSE)="√","√","") | F68: =_xlfn.LET(_xlpm.x,VLOOKUP($B68,augment_header!$B$2:$G$72,5,FALSE),IF(_xlpm.x="","",_xlpm.x))
A69: 67 | B69: questline {09d67381} | C69: =_xlfn.LET(_xlpm.x,VLOOKUP($B69,augment_header!$B$2:$G$72,2,FALSE),IF(_xlpm.x="","",_xlpm.x)) -> 任务线相关强化符文 | D69: =IF(VLOOKUP($B69,augment_header!$B$2:$G$72,3,FALSE)="√","√","") -> √ | E69: =IF(VLOOKUP($B69,augment_header!$B$2:$G$72,4,FALSE)="√","√","") | F69: =_xlfn.LET(_xlpm.x,VLOOKUP($B69,augment_header!$B$2:$G$72,5,FALSE),IF(_xlpm.x="","",_xlpm.x)) | G69: 53
A70: 68 | B70: questline {c504ece0} | C70: =_xlfn.LET(_xlpm.x,VLOOKUP($B70,augment_header!$B$2:$G$72,2,FALSE),IF(_xlpm.x="","",_xlpm.x)) | D70: =IF(VLOOKUP($B70,augment_header!$B$2:$G$72,3,FALSE)="√","√","") -> √ | E70: =IF(VLOOKUP($B70,augment_header!$B$2:$G$72,4,FALSE)="√","√","") | F70: =_xlfn.LET(_xlpm.x,VLOOKUP($B70,augment_header!$B$2:$G$72,5,FALSE),IF(_xlpm.x="","",_xlpm.x)) -> FALSE | G70: 22
A71: 69 | B71: questline {4796bf5f}_content_zh | C71: =_xlfn.LET(_xlpm.x,VLOOKUP($B71,augment_header!$B$2:$G$72,2,FALSE),IF(_xlpm.x="","",_xlpm.x)) -> 任务线对应强化符文名称（中文） | D71: =IF(VLOOKUP($B71,augment_header!$B$2:$G$72,3,FALSE)="√","√","") | E71: =IF(VLOOKUP($B71,augment_header!$B$2:$G$72,4,FALSE)="√","√","") | F71: =_xlfn.LET(_xlpm.x,VLOOKUP($B71,augment_header!$B$2:$G$72,5,FALSE),IF(_xlpm.x="","",_xlpm.x))
A72: 70 | B72: questline {4796bf5f}_content_en | C72: =_xlfn.LET(_xlpm.x,VLOOKUP($B72,augment_header!$B$2:$G$72,2,FALSE),IF(_xlpm.x="","",_xlpm.x)) -> 任务线对应强化符文名称（英文） | D72: =IF(VLOOKUP($B72,augment_header!$B$2:$G$72,3,FALSE)="√","√","") | E72: =IF(VLOOKUP($B72,augment_header!$B$2:$G$72,4,FALSE)="√","√","") | F72: =_xlfn.LET(_xlpm.x,VLOOKUP($B72,augment_header!$B$2:$G$72,5,FALSE),IF(_xlpm.x="","",_xlpm.x))
A73: 71 | B73: questline {c88f1a9b}_content_zh | C73: =_xlfn.LET(_xlpm.x,VLOOKUP($B73,augment_header!$B$2:$G$72,2,FALSE),IF(_xlpm.x="","",_xlpm.x)) -> 任务完成描述（中文） | D73: =IF(VLOOKUP($B73,augment_header!$B$2:$G$72,3,FALSE)="√","√","") | E73: =IF(VLOOKUP($B73,augment_header!$B$2:$G$72,4,FALSE)="√","√","") | F73: =_xlfn.LET(_xlpm.x,VLOOKUP($B73,augment_header!$B$2:$G$72,5,FALSE),IF(_xlpm.x="","",_xlpm.x)) | G73: 44
A74: 72 | B74: questline {c88f1a9b}_content_zh_burn | C74: =_xlfn.LET(_xlpm.x,VLOOKUP($B74,augment_header!$B$2:$G$72,2,FALSE),IF(_xlpm.x="","",_xlpm.x)) -> 任务完成描述（中文/数值转换） | D74: =IF(VLOOKUP($B74,augment_header!$B$2:$G$72,3,FALSE)="√","√","") | E74: =IF(VLOOKUP($B74,augment_header!$B$2:$G$72,4,FALSE)="√","√","") | F74: =_xlfn.LET(_xlpm.x,VLOOKUP($B74,augment_header!$B$2:$G$72,5,FALSE),IF(_xlpm.x="","",_xlpm.x)) | G74: 45
A75: 73 | B75: questline {c88f1a9b}_content_en | C75: =_xlfn.LET(_xlpm.x,VLOOKUP($B75,augment_header!$B$2:$G$72,2,FALSE),IF(_xlpm.x="","",_xlpm.x)) -> 任务完成描述（英文） | D75: =IF(VLOOKUP($B75,augment_header!$B$2:$G$72,3,FALSE)="√","√","") | E75: =IF(VLOOKUP($B75,augment_header!$B$2:$G$72,4,FALSE)="√","√","") | F75: =_xlfn.LET(_xlpm.x,VLOOKUP($B75,augment_header!$B$2:$G$72,5,FALSE),IF(_xlpm.x="","",_xlpm.x)) | G75: 46
A76: 74 | B76: questline {c88f1a9b}_content_en_burn | C76: =_xlfn.LET(_xlpm.x,VLOOKUP($B76,augment_header!$B$2:$G$72,2,FALSE),IF(_xlpm.x="","",_xlpm.x)) -> 任务完成描述（英文/数值转换） | D76: =IF(VLOOKUP($B76,augment_header!$B$2:$G$72,3,FALSE)="√","√","") | E76: =IF(VLOOKUP($B76,augment_header!$B$2:$G$72,4,FALSE)="√","√","") | F76: =_xlfn.LET(_xlpm.x,VLOOKUP($B76,augment_header!$B$2:$G$72,5,FALSE),IF(_xlpm.x="","",_xlpm.x)) | G76: 47

Sheet KiwiAugmentSet_header
A1: Index | B1: Key | C1: Value | D1: DirectlyImport? | E1: Flexible | F1: OutputOrder
A2: 0 | B2: key | C2: 主键 | D2: √ | F2: 0
A3: 1 | B3: {3a942548} | C3: 套装代码 | D3: √ | F3: 1
A4: 2 | B4: {4217d741} | C4: 套装缩略图路径 | D4: √ | F4: 25
A5: 3 | B5: {0746ade9} | C5: 套装名称键 | D5: √ | F5: 2
A6: 4 | B6: {97e82990} | C6: 套装描述键 | D6: √ | F6: 5
A7: 5 | B7: augments | C7: 强化符文列表 | D7: √ | F7: 15
A8: 6 | B8: {96b4b430} | C8: 根指令 | D8: √ | F8: 18
A9: 7 | B9: {01d14504} | C9: 资源解析器 | D9: √ | E9: √ | F9: 22
A10: 8 | B10: TierData | C10: 位阶数据 | D10: √ | E10: √ | F10: 24
A11: 9 | B11: AdditionalSpells | C11: 其它指令 | D11: √ | F11: 20
A12: 10 | B12: {0746ade9}_content_zh | C12: 套装名称（中文） | F12: 3
A13: 11 | B13: {0746ade9}_content_en | C13: 套装名称（英文） | F13: 4
A14: 12 | B14: {97e82990}_content_zh | C14: 套装描述（中文） | F14: 6
A15: 13 | B15: {97e82990}_content_zh_burn | C15: 套装描述（中文/数值转换） | F15: 7
A16: 14 | B16: {97e82990}_content_en | C16: 套装描述（英文） | F16: 8
A17: 15 | B17: {97e82990}_content_en_burn | C17: 套装描述（英文/数值转换） | F17: 9
A18: 16 | B18: augments nameTra_contents_zh | C18: 强化符文名称列表（中文） | F18: 16
A19: 17 | B19: augments nameTra_contents_en | C19: 强化符文名称列表（英文） | F19: 17
A20: 18 | B20: {96b4b430}_object | C20: 根指令对象 | F20: 19
A21: 19 | B21: {96b4b430}_object keyTooltip | C21: 套装说明文本键 | F21: 10
A22: 20 | B22: {96b4b430}_object keyTooltip_content_zh | C22: 套装说明文本（中文） | F22: 11
A23: 21 | B23: {96b4b430}_object keyTooltip_content_zh_burn | C23: 套装说明文本（中文/数值转换） | F23: 12
... A26: 24 | B26: AdditionalSpells_object | C26: 其它指令对象 | F26: 21
A27: 25 | B27: {01d14504} resourceMap | C27: 资源解析器映射字典 | D27: √ | E27: √ | F27: 23

Sheet KiwiQuestline_header
A1: Index | B1: Key | C1: Value | D1: DirectlyImport? | E1: Flexible | F1: defaultValue | G1: OutputOrder
A2: 0 | B2: key | C2: 主键 | D2: √ | G2: 0
A3: 1 | B3: {bc1b3d88} | D3: √
A4: 2 | B4: QuestName | C4: 任务代码 | D4: √ | G4: 2
A5: 3 | B5: {4796bf5f} | C5: 任务线名称键 | D5: √ | G5: 3
A6: 4 | B6: {c88f1a9b} | C6: 任务完成描述键 | D6: √
A7: 5 | B7: {06b06978} texturePath | C7: 任务栏位图标纹理路径 | D7: √
A8: 6 | B8: {ee2e0dbc} | D8: √ | E8: √ | F8: FALSE
A9: 7 | B9: {09d67381} | C9: 相关强化符文 | D9: √
A10: 8 | B10: {c504ece0} | D10: √ | F10: FALSE
A11: 9 | B11: {4796bf5f}_content_zh | C11: 任务线名称（中文） | G11: 4
A12: 10 | B12: {4796bf5f}_content_en | C12: 任务线名称（英文） | G12: 5
A13: 11 | B13: {c88f1a9b}_content_zh | C13: 任务完成描述（中文）
A14: 12 | B14: {c88f1a9b}_content_zh_burn | C14: 任务完成描述（中文/数值转换）
A15: 13 | B15: {c88f1a9b}_content_en | C15: 任务完成描述（英文）
A16: 14 | B16: {c88f1a9b}_content_en_burn | C16: 任务完成描述（英文/数值转换）
A17: 15 | B17: Milestone_index | C17: 里程序号 | D17: √ | G17: 6
A18: 16 | B18: Milestone {7fec0982} | C18: 里程点 | D18: √ | G18: 7
A19: 17 | B19: Milestone {03d6a5a2} | C19: 里程说明文本键 | D19: √ | G19: 8
A20: 18 | B20: Milestone {03d6a5a2}_content_zh | C20: 里程说明文本（中文） | G20: 9
A21: 19 | B21: Milestone {03d6a5a2}_content_zh_burn | C21: 里程说明文本（中文/数值转换） | G21: 10
A22: 20 | B22: Milestone {03d6a5a2}_content_en | C22: 里程说明文本（英文） | G22: 11
A23: 21 | B23: Milestone {03d6a5a2}_content_en_burn | C23: 里程说明文本（英文/数值转换） | G23: 12
A24: 22 | B24: augment AugmentPlatformId | C24: 强化符文序号 | D24: √ | G24: 1

Sheet KiwiJadeAugment_header
A1: Index | B1: Key | C1: Value | D1: DirectlyImport? | E1: Flexible | F1: defaultValue | G1: OutputOrder
A2: 0 | B2: isCurrent | C2: 存在于现代版 | G2: 7
A3: 1 | B3: key | C3: =_xlfn.LET(_xlpm.x,VLOOKUP($B3,augment_header!$B$2:$G$72,2,FALSE),IF(_xlpm.x="","",_xlpm.x)) -> 主键 | D3: =IF(VLOOKUP($B3,augment_header!$B$2:$G$72,3,FALSE)="√","√","") -> √ | E3: =IF(VLOOKUP($B3,augment_header!$B$2:$G$72,4,FALSE)="√","√","") | F3: =_xlfn.LET(_xlpm.x,VLOOKUP($B3,augment_header!$B$2:$G$72,5,FALSE),IF(_xlpm.x="","",_xlpm.x)) | G3: 0
A4: 2 | B4: AugmentNameId | C4: =_xlfn.LET(_xlpm.x,VLOOKUP($B4,augment_header!$B$2:$G$72,2,FALSE),IF(_xlpm.x="","",_xlpm.x)) -> 强化符文代码 | D4: =IF(VLOOKUP($B4,augment_header!$B$2:$G$72,3,FALSE)="√","√","") -> √ | E4: =IF(VLOOKUP($B4,augment_header!$B$2:$G$72,4,FALSE)="√","√","") | F4: =_xlfn.LET(_xlpm.x,VLOOKUP($B4,augment_header!$B$2:$G$72,5,FALSE),IF(_xlpm.x="","",_xlpm.x)) | G4: 1
A5: 3 | B5: Enabled | C5: =_xlfn.LET(_xlpm.x,VLOOKUP($B5,augment_header!$B$2:$G$72,2,FALSE),IF(_xlpm.x="","",_xlpm.x)) -> 可用性 | D5: =IF(VLOOKUP($B5,augment_header!$B$2:$G$72,3,FALSE)="√","√","") -> √ | E5: =IF(VLOOKUP($B5,augment_header!$B$2:$G$72,4,FALSE)="√","√","") -> √ | F5: =_xlfn.LET(_xlpm.x,VLOOKUP($B5,augment_header!$B$2:$G$72,5,FALSE),IF(_xlpm.x="","",_xlpm.x)) -> TRUE | G5: 3
A6: 4 | B6: NameTra | C6: =_xlfn.LET(_xlpm.x,VLOOKUP($B6,augment_header!$B$2:$G$72,2,FALSE),IF(_xlpm.x="","",_xlpm.x)) -> 名称键 | D6: =IF(VLOOKUP($B6,augment_header!$B$2:$G$72,3,FALSE)="√","√","") -> √ | E6: =IF(VLOOKUP($B6,augment_header!$B$2:$G$72,4,FALSE)="√","√","") | F6: =_xlfn.LET(_xlpm.x,VLOOKUP($B6,augment_header!$B$2:$G$72,5,FALSE),IF(_xlpm.x="","",_xlpm.x)) | G6: 4
A7: 5 | B7: DescriptionTra | C7: =_xlfn.LET(_xlpm.x,VLOOKUP($B7,augment_header!$B$2:$G$72,2,FALSE),IF(_xlpm.x="","",_xlpm.x)) -> 简介键 | D7: =IF(VLOOKUP($B7,augment_header!$B$2:$G$72,3,FALSE)="√","√","") -> √ | E7: =IF(VLOOKUP($B7,augment_header!$B$2:$G$72,4,FALSE)="√","√","") | F7: =_xlfn.LET(_xlpm.x,VLOOKUP($B7,augment_header!$B$2:$G$72,5,FALSE),IF(_xlpm.x="","",_xlpm.x)) | G7: 20
A8: 6 | B8: AugmentTooltipTra | C8: =_xlfn.LET(_xlpm.x,VLOOKUP($B8,augment_header!$B$2:$G$72,2,FALSE),IF(_xlpm.x="","",_xlpm.x)) -> 强化符文详细信息键 | D8: =IF(VLOOKUP($B8,augment_header!$B$2:$G$72,3,FALSE)="√","√","") -> √ | E8: =IF(VLOOKUP($B8,augment_header!$B$2:$G$72,4,FALSE)="√","√","") | F8: =_xlfn.LET(_xlpm.x,VLOOKUP($B8,augment_header!$B$2:$G$72,5,FALSE),IF(_xlpm.x="","",_xlpm.x)) | G8: 25
A9: 7 | B9: RootSpell | C9: =_xlfn.LET(_xlpm.x,VLOOKUP($B9,augment_header!$B$2:$G$72,2,FALSE),IF(_xlpm.x="","",_xlpm.x)) -> 根指令主键 | D9: =IF(VLOOKUP($B9,augment_header!$B$2:$G$72,3,FALSE)="√","√","") -> √ | E9: =IF(VLOOKUP($B9,augment_header!$B$2:$G$72,4,FALSE)="√","√","") | F9: =_xlfn.LET(_xlpm.x,VLOOKUP($B9,augment_header!$B$2:$G$72,5,FALSE),IF(_xlpm.x="","",_xlpm.x)) | G9: 45
A10: 8 | B10: AdditionalSpells | C10: =_xlfn.LET(_xlpm.x,VLOOKUP($B10,augment_header!$B$2:$G$72,2,FALSE),IF(_xlpm.x="","",_xlpm.x)) -> 其它指令主键列表 | D10: =IF(VLOOKUP($B10,augment_header!$B$2:$G$72,3,FALSE)="√","√","") -> √ | E10: =IF(VLOOKUP($B10,augment_header!$B$2:$G$72,4,FALSE)="√","√","") | F10: =_xlfn.LET(_xlpm.x,VLOOKUP($B10,augment_header!$B$2:$G$72,5,FALSE),IF(_xlpm.x="","",_xlpm.x)) | G10: 47
A11: 9 | B11: mAugmentTags | C11: =_xlfn.LET(_xlpm.x,VLOOKUP($B11,augment_header!$B$2:$G$72,2,FALSE),IF(_xlpm.x="","",_xlpm.x)) -> 强化符文标签 | D11: =IF(VLOOKUP($B11,augment_header!$B$2:$G$72,3,FALSE)="√","√","") -> √ | E11: =IF(VLOOKUP($B11,augment_header!$B$2:$G$72,4,FALSE)="√","√","") -> √ | F11: =_xlfn.LET(_xlpm.x,VLOOKUP($B11,augment_header!$B$2:$G$72,5,FALSE),IF(_xlpm.x="","",_xlpm.x)) | G11: 14
A12: 10 | B12: mBuildTags | C12: =_xlfn.LET(_xlpm.x,VLOOKUP($B12,augment_header!$B$2:$G$72,2,FALSE),IF(_xlpm.x="","",_xlpm.x)) -> 构建标签 | D12: =IF(VLOOKUP($B12,augment_header!$B$2:$G$72,3,FALSE)="√","√","") -> √ | E12: =IF(VLOOKUP($B12,augment_header!$B$2:$G$72,4,FALSE)="√","√","") -> √ | F12: =_xlfn.LET(_xlpm.x,VLOOKUP($B12,augment_header!$B$2:$G$72,5,FALSE),IF(_xlpm.x="","",_xlpm.x)) | G12: 15
A13: 11 | B13: {3696d198} {c4182067} | C13: =_xlfn.LET(_xlpm.x,VLOOKUP($B13,augment_header!$B$2:$G$72,2,FALSE),IF(_xlpm.x="","",_xlpm.x)) -> 强化符文详细信息描述部分键 | D13: =IF(VLOOKUP($B13,augment_header!$B$2:$G$72,3,FALSE)="√","√","") -> √ | E13: =IF(VLOOKUP($B13,augment_header!$B$2:$G$72,4,FALSE)="√","√","") | F13: =_xlfn.LET(_xlpm.x,VLOOKUP($B13,augment_header!$B$2:$G$72,5,FALSE),IF(_xlpm.x="","",_xlpm.x)) | G13: 30
A14: 12 | B14: {3696d198} {231af825} | C14: =_xlfn.LET(_xlpm.x,VLOOKUP($B14,augment_header!$B$2:$G$72,2,FALSE),IF(_xlpm.x="","",_xlpm.x)) -> 强化符文详细信息追踪部分键 | D14: =IF(VLOOKUP($B14,augment_header!$B$2:$G$72,3,FALSE)="√","√","") -> √ | E14: =IF(VLOOKUP($B14,augment_header!$B$2:$G$72,4,FALSE)="√","√","") -> √ | F14: =_xlfn.LET(_xlpm.x,VLOOKUP($B14,augment_header!$B$2:$G$72,5,FALSE),IF(_xlpm.x="","",_xlpm.x)) | G14: 35
A15: 13 | B15: {791eb92e} {5753a320} {c98a82ca} | C15: =_xlfn.LET(_xlpm.x,VLOOKUP($B15,augment_header!$B$2:$G$72,2,FALSE),IF(_xlpm.x="","",_xlpm.x)) -> 满级效果简介键 | D15: =IF(VLOOKUP($B15,augment_header!$B$2:$G$72,3,FALSE)="√","√","") -> √ | E15: =IF(VLOOKUP($B15,augment_header!$B$2:$G$72,4,FALSE)="√","√","") | F15: =_xlfn.LET(_xlpm.x,VLOOKUP($B15,augment_header!$B$2:$G$72,5,FALSE),IF(_xlpm.x="","",_xlpm.x))
A16: 14 | B16: {791eb92e} {5753a320} {05835d27} | C16: =_xlfn.LET(_xlpm.x,VLOOKUP($B16,augment_header!$B$2:$G$72,2,FALSE),IF(_xlpm.x="","",_xlpm.x)) -> 满级效果详细信息键 | D16: =IF(VLOOKUP($B16,augment_header!$B$2:$G$72,3,FALSE)="√","√","") -> √ | E16: =IF(VLOOKUP($B16,augment_header!$B$2:$G$72,4,FALSE)="√","√","") | F16: =_xlfn.LET(_xlpm.x,VLOOKUP($B16,augment_header!$B$2:$G$72,5,FALSE),IF(_xlpm.x="","",_xlpm.x))
A17: 15 | B17: AugmentLargeIconPath | C17: =_xlfn.LET(_xlpm.x,VLOOKUP($B17,augment_header!$B$2:$G$72,2,FALSE),IF(_xlpm.x="","",_xlpm.x)) -> 强化符文大图标路径 | D17: =IF(VLOOKUP($B17,augment_header!$B$2:$G$72,3,FALSE)="√","√","") -> √ | E17: =IF(VLOOKUP($B17,augment_header!$B$2:$G$72,4,FALSE)="√","√","") | F17: =_xlfn.LET(_xlpm.x,VLOOKUP($B17,augment_header!$B$2:$G$72,5,FALSE),IF(_xlpm.x="","",_xlpm.x)) | G17: 53
A18: 16 | B18: AugmentSmallIconPath | C18: =_xlfn.LET(_xlpm.x,VLOOKUP($B18,augment_header!$B$2:$G$72,2,FALSE),IF(_xlpm.x="","",_xlpm.x)) -> 强化符文小图标路径 | D18: =IF(VLOOKUP($B18,augment_header!$B$2:$G$72,3,FALSE)="√","√","") -> √ | E18: =IF(VLOOKUP($B18,augment_header!$B$2:$G$72,4,FALSE)="√","√","") | F18: =_xlfn.LET(_xlpm.x,VLOOKUP($B18,augment_header!$B$2:$G$72,5,FALSE),IF(_xlpm.x="","",_xlpm.x)) | G18: 54
A19: 17 | B19: {815dad28} | C19: =_xlfn.LET(_xlpm.x,VLOOKUP($B19,augment_header!$B$2:$G$72,2,FALSE),IF(_xlpm.x="","",_xlpm.x)) -> 次级稀有度 | D19: =IF(VLOOKUP($B19,augment_header!$B$2:$G$72,3,FALSE)="√","√","") -> √ | E19: =IF(VLOOKUP($B19,augment_header!$B$2:$G$72,4,FALSE)="√","√","") -> √ | F19: =_xlfn.LET(_xlpm.x,VLOOKUP($B19,augment_header!$B$2:$G$72,5,FALSE),IF(_xlpm.x="","",_xlpm.x))
A20: 18 | B20: AugmentDisplayTags | C20: =_xlfn.LET(_xlpm.x,VLOOKUP($B20,augment_header!$B$2:$G$72,2,FALSE),IF(_xlpm.x="","",_xlpm.x)) -> 强化符文显示标签 | D20: =IF(VLOOKUP($B20,augment_header!$B$2:$G$72,3,FALSE)="√","√","") -> √ | E20: =IF(VLOOKUP($B20,augment_header!$B$2:$G$72,4,FALSE)="√","√","") | F20: =_xlfn.LET(_xlpm.x,VLOOKUP($B20,augment_header!$B$2:$G$72,5,FALSE),IF(_xlpm.x="","",_xlpm.x)) | G20: 10
A21: 19 | B21: rarity | C21: =_xlfn.LET(_xlpm.x,VLOOKUP($B21,augment_header!$B$2:$G$72,2,FALSE),IF(_xlpm.x="","",_xlpm.x)) -> 稀有度 | D21: =IF(VLOOKUP($B21,augment_header!$B$2:$G$72,3,FALSE)="√","√","") -> √ | E21: =IF(VLOOKUP($B21,augment_header!$B$2:$G$72,4,FALSE)="√","√","") -> √ | F21: =_xlfn.LET(_xlpm.x,VLOOKUP($B21,augment_header!$B$2:$G$72,5,FALSE),IF(_xlpm.x="","",_xlpm.x)) | G21: 8
A22: 20 | B22: {ed593c9c} | C22: =_xlfn.LET(_xlpm.x,VLOOKUP($B22,augment_header!$B$2:$G$72,2,FALSE),IF(_xlpm.x="","",_xlpm.x)) -> 不占用栏位 | D22: =IF(VLOOKUP($B22,augment_header!$B$2:$G$72,3,FALSE)="√","√","") -> √ | E22: =IF(VLOOKUP($B22,augment_header!$B$2:$G$72,4,FALSE)="√","√","") -> √ | F22: =_xlfn.LET(_xlpm.x,VLOOKUP($B22,augment_header!$B$2:$G$72,5,FALSE),IF(_xlpm.x="","",_xlpm.x)) -> FALSE | G22: 16
A23: 21 | B23: AugmentPlatformId | C23: =_xlfn.LET(_xlpm.x,VLOOKUP($B23,augment_header!$B$2:$G$72,2,FALSE),IF(_xlpm.x="","",_xlpm.x)) -> 强化符文序号 | D23: =IF(VLOOKUP($B23,augment_header!$B$2:$G$72,3,FALSE)="√","√","") -> √ | E23: =IF(VLOOKUP($B23,augment_header!$B$2:$G$72,4,FALSE)="√","√","") | F23: =_xlfn.LET(_xlpm.x,VLOOKUP($B23,augment_header!$B$2:$G$72,5,FALSE),IF(_xlpm.x="","",_xlpm.x)) -> -1 | G23: 2
A24: 22 | B24: QuestData Quest | C24: =_xlfn.LET(_xlpm.x,VLOOKUP($B24,augment_header!$B$2:$G$72,2,FALSE),IF(_xlpm.x="","",_xlpm.x)) -> 任务线主键 | D24: =IF(VLOOKUP($B24,augment_header!$B$2:$G$72,3,FALSE)="√","√","") -> √ | E24: =IF(VLOOKUP($B24,augment_header!$B$2:$G$72,4,FALSE)="√","√","") -> √ | F24: =_xlfn.LET(_xlpm.x,VLOOKUP($B24,augment_header!$B$2:$G$72,5,FALSE),IF(_xlpm.x="","",_xlpm.x)) | G24: 49
A25: 23 | B25: {e3a02eac} | C25: =_xlfn.LET(_xlpm.x,VLOOKUP($B25,augment_header!$B$2:$G$72,2,FALSE),IF(_xlpm.x="","",_xlpm.x)) -> 技能重载 | D25: =IF(VLOOKUP($B25,augment_header!$B$2:$G$72,3,FALSE)="√","√","") -> √ | E25: =IF(VLOOKUP($B25,augment_header!$B$2:$G$72,4,FALSE)="√","√","") -> √ | F25: =_xlfn.LET(_xlpm.x,VLOOKUP($B25,augment_header!$B$2:$G$72,5,FALSE),IF(_xlpm.x="","",_xlpm.x)) -> FALSE | G25: 17
A26: 24 | B26: ResourceResolver | C26: =_xlfn.LET(_xlpm.x,VLOOKUP($B26,augment_header!$B$2:$G$72,2,FALSE),IF(_xlpm.x="","",_xlpm.x)) -> 资源解析器主键 | D26: =IF(VLOOKUP($B26,augment_header!$B$2:$G$72,3,FALSE)="√","√","") -> √ | E26: =IF(VLOOKUP($B26,augment_header!$B$2:$G$72,4,FALSE)="√","√","") -> √ | F26: =_xlfn.LET(_xlpm.x,VLOOKUP($B26,augment_header!$B$2:$G$72,5,FALSE),IF(_xlpm.x="","",_xlpm.x)) | G26: 51
A27: 25 | B27: NameTra_content_zh | C27: =_xlfn.LET(_xlpm.x,VLOOKUP($B27,augment_header!$B$2:$G$72,2,FALSE),IF(_xlpm.x="","",_xlpm.x)) -> 名称（中文） | D27: =IF(VLOOKUP($B27,augment_header!$B$2:$G$72,3,FALSE)="√","√","") | E27: =IF(VLOOKUP($B27,augment_header!$B$2:$G$72,4,FALSE)="√","√","") | F27: =_xlfn.LET(_xlpm.x,VLOOKUP($B27,augment_header!$B$2:$G$72,5,FALSE),IF(_xlpm.x="","",_xlpm.x)) | G27: 5
A28: 26 | B28: NameTra_content_en | C28: =_xlfn.LET(_xlpm.x,VLOOKUP($B28,augment_header!$B$2:$G$72,2,FALSE),IF(_xlpm.x="","",_xlpm.x)) -> 名称（英文） | D28: =IF(VLOOKUP($B28,augment_header!$B$2:$G$72,3,FALSE)="√","√","") | E28: =IF(VLOOKUP($B28,augment_header!$B$2:$G$72,4,FALSE)="√","√","") | F28: =_xlfn.LET(_xlpm.x,VLOOKUP($B28,augment_header!$B$2:$G$72,5,FALSE),IF(_xlpm.x="","",_xlpm.x)) | G28: 6
A29: 27 | B29: DescriptionTra_content_zh | C29: =_xlfn.LET(_xlpm.x,VLOOKUP($B29,augment_header!$B$2:$G$72,2,FALSE),IF(_xlpm.x="","",_xlpm.x)) -> 简介（中文） | D29: =IF(VLOOKUP($B29,augment_header!$B$2:$G$72,3,FALSE)="√","√","") | E29: =IF(VLOOKUP($B29,augment_header!$B$2:$G$72,4,FALSE)="√","√","") | F29: =_xlfn.LET(_xlpm.x,VLOOKUP($B29,augment_header!$B$2:$G$72,5,FALSE),IF(_xlpm.x="","",_xlpm.x)) | G29: 21
A30: 28 | B30: DescriptionTra_content_zh_burn | C30: =_xlfn.LET(_xlpm.x,VLOOKUP($B30,augment_header!$B$2:$G$72,2,FALSE),IF(_xlpm.x="","",_xlpm.x)) -> 简介（中文/数值转换） | D30: =IF(VLOOKUP($B30,augment_header!$B$2:$G$72,3,FALSE)="√","√","") | E30: =IF(VLOOKUP($B30,augment_header!$B$2:$G$72,4,FALSE)="√","√","") | F30: =_xlfn.LET(_xlpm.x,VLOOKUP($B30,augment_header!$B$2:$G$72,5,FALSE),IF(_xlpm.x="","",_xlpm.x)) | G30: 22
A31: 29 | B31: DescriptionTra_content_en | C31: =_xlfn.LET(_xlpm.x,VLOOKUP($B31,augment_header!$B$2:$G$72,2,FALSE),IF(_xlpm.x="","",_xlpm.x)) -> 简介（英文） | D31: =IF(VLOOKUP($B31,augment_header!$B$2:$G$72,3,FALSE)="√","√","") | E31: =IF(VLOOKUP($B31,augment_header!$B$2:$G$72,4,FALSE)="√","√","") | F31: =_xlfn.LET(_xlpm.x,VLOOKUP($B31,augment_header!$B$2:$G$72,5,FALSE),IF(_xlpm.x="","",_xlpm.x)) | G31: 23
... A44: 42 | B44: {3696d198} {231af825}_content_en_burn | C44: =_xlfn.LET(_xlpm.x,VLOOKUP($B44,augment_header!$B$2:$G$72,2,FALSE),IF(_xlpm.x="","",_xlpm.x)) -> 强化符文详细信息追踪部分（英文/数值转换） | D44: =IF(VLOOKUP($B44,augment_header!$B$2:$G$72,3,FALSE)="√","√","") | E44: =IF(VLOOKUP($B44,augment_header!$B$2:$G$72,4,FALSE)="√","√","") | F44: =_xlfn.LET(_xlpm.x,VLOOKUP($B44,augment_header!$B$2:$G$72,5,FALSE),IF(_xlpm.x="","",_xlpm.x)) | G44: 39
A45: 43 | B45: {791eb92e} {5753a320} {c98a82ca}_content_zh | C45: =_xlfn.LET(_xlpm.x,VLOOKUP($B45,augment_header!$B$2:$G$72,2,FALSE),IF(_xlpm.x="","",_xlpm.x)) -> 满级效果简介（中文） | D45: =IF(VLOOKUP($B45,augment_header!$B$2:$G$72,3,FALSE)="√","√","") | E45: =IF(VLOOKUP($B45,augment_header!$B$2:$G$72,4,FALSE)="√","√","") | F45: =_xlfn.LET(_xlpm.x,VLOOKUP($B45,augment_header!$B$2:$G$72,5,FALSE),IF(_xlpm.x="","",_xlpm.x))
A46: 44 | B46: {791eb92e} {5753a320} {c98a82ca}_content_zh_burn | C46: =_xlfn.LET(_xlpm.x,VLOOKUP($B46,augment_header!$B$2:$G$72,2,FALSE),IF(_xlpm.x="","",_xlpm.x)) -> 满级效果简介（中文/数值转换） | D46: =IF(VLOOKUP($B46,augment_header!$B$2:$G$72,3,FALSE)="√","√","") | E46: =IF(VLOOKUP($B46,augment_header!$B$2:$G$72,4,FALSE)="√","√","") | F46: =_xlfn.LET(_xlpm.x,VLOOKUP($B46,augment_header!$B$2:$G$72,5,FALSE),IF(_xlpm.x="","",_xlpm.x))
A47: 45 | B47: {791eb92e} {5753a320} {c98a82ca}_content_en | C47: =_xlfn.LET(_xlpm.x,VLOOKUP($B47,augment_header!$B$2:$G$72,2,FALSE),IF(_xlpm.x="","",_xlpm.x)) -> 满级效果简介（英文） | D47: =IF(VLOOKUP($B47,augment_header!$B$2:$G$72,3,FALSE)="√","√","") | E47: =IF(VLOOKUP($B47,augment_header!$B$2:$G$72,4,FALSE)="√","√","") | F47: =_xlfn.LET(_xlpm.x,VLOOKUP($B47,augment_header!$B$2:$G$72,5,FALSE),IF(_xlpm.x="","",_xlpm.x))
A48: 46 | B48: {791eb92e} {5753a320} {c98a82ca}_content_en_burn | C48: =_xlfn.LET(_xlpm.x,VLOOKUP($B48,augment_header!$B$2:$G$72,2,FALSE),IF(_xlpm.x="","",_xlpm.x)) -> 满级效果简介（英文/数值转换） | D48: =IF(VLOOKUP($B48,augment_header!$B$2:$G$72,3,FALSE)="√","√","") | E48: =IF(VLOOKUP($B48,augment_header!$B$2:$G$72,4,FALSE)="√","√","") | F48: =_xlfn.LET(_xlpm.x,VLOOKUP($B48,augment_header!$B$2:$G$72,5,FALSE),IF(_xlpm.x="","",_xlpm.x))
A49: 47 | B49: {791eb92e} {5753a320} {05835d27}_content_zh | C49: =_xlfn.LET(_xlpm.x,VLOOKUP($B49,augment_header!$B$2:$G$72,2,FALSE),IF(_xlpm.x="","",_xlpm.x)) -> 满级效果详细信息（中文） | D49: =IF(VLOOKUP($B49,augment_header!$B$2:$G$72,3,FALSE)="√","√","") | E49: =IF(VLOOKUP($B49,augment_header!$B$2:$G$72,4,FALSE)="√","√","") | F49: =_xlfn.LET(_xlpm.x,VLOOKUP($B49,augment_header!$B$2:$G$72,5,FALSE),IF(_xlpm.x="","",_xlpm.x))
A50: 48 | B50: {791eb92e} {5753a320} {05835d27}_content_zh_burn | C50: =_xlfn.LET(_xlpm.x,VLOOKUP($B50,augment_header!$B$2:$G$72,2,FALSE),IF(_xlpm.x="","",_xlpm.x)) -> 满级效果详细信息（中文/数值转换） | D50: =IF(VLOOKUP($B50,augment_header!$B$2:$G$72,3,FALSE)="√","√","") | E50: =IF(VLOOKUP($B50,augment_header!$B$2:$G$72,4,FALSE)="√","√","") | F50: =_xlfn.LET(_xlpm.x,VLOOKUP($B50,augment_header!$B$2:$G$72,5,FALSE),IF(_xlpm.x="","",_xlpm.x))
A51: 49 | B51: {791eb92e} {5753a320} {05835d27}_content_en | C51: =_xlfn.LET(_xlpm.x,VLOOKUP($B51,augment_header!$B$2:$G$72,2,FALSE),IF(_xlpm.x="","",_xlpm.x)) -> 满级效果详细信息（英文） | D51: =IF(VLOOKUP($B51,augment_header!$B$2:$G$72,3,FALSE)="√","√","") | E51: =IF(VLOOKUP($B51,augment_header!$B$2:$G$72,4,FALSE)="√","√","") | F51: =_xlfn.LET(_xlpm.x,VLOOKUP($B51,augment_header!$B$2:$G$72,5,FALSE),IF(_xlpm.x="","",_xlpm.x))
A52: 50 | B52: {791eb92e} {5753a320} {05835d27}_content_en_burn | C52: =_xlfn.LET(_xlpm.x,VLOOKUP($B52,augment_header!$B$2:$G$72,2,FALSE),IF(_xlpm.x="","",_xlpm.x)) -> 满级效果详细信息（英文/数值转换） | D52: =IF(VLOOKUP($B52,augment_header!$B$2:$G$72,3,FALSE)="√","√","") | E52: =IF(VLOOKUP($B52,augment_header!$B$2:$G$72,4,FALSE)="√","√","") | F52: =_xlfn.LET(_xlpm.x,VLOOKUP($B52,augment_header!$B$2:$G$72,5,FALSE),IF(_xlpm.x="","",_xlpm.x))
A53: 51 | B53: AugmentDisplayTags_content | C53: =_xlfn.LET(_xlpm.x,VLOOKUP($B53,augment_header!$B$2:$G$72,2,FALSE),IF(_xlpm.x="","",_xlpm.x)) -> 强化符文显示标签内容 | D53: =IF(VLOOKUP($B53,augment_header!$B$2:$G$72,3,FALSE)="√","√","") | E53: =IF(VLOOKUP($B53,augment_header!$B$2:$G$72,4,FALSE)="√","√","") | F53: =_xlfn.LET(_xlpm.x,VLOOKUP($B53,augment_header!$B$2:$G$72,5,FALSE),IF(_xlpm.x="","",_xlpm.x)) | G53: 11
A54: 52 | B54: rarityValue | C54: =_xlfn.LET(_xlpm.x,VLOOKUP($B54,augment_header!$B$2:$G$72,2,FALSE),IF(_xlpm.x="","",_xlpm.x)) -> 位阶 | D54: =IF(VLOOKUP($B54,augment_header!$B$2:$G$72,3,FALSE)="√","√","") | E54: =IF(VLOOKUP($B54,augment_header!$B$2:$G$72,4,FALSE)="√","√","") -> √ | F54: =_xlfn.LET(_xlpm.x,VLOOKUP($B54,augment_header!$B$2:$G$72,5,FALSE),IF(_xlpm.x="","",_xlpm.x)) | G54: 9
A55: 53 | B55: RootSpellObject | C55: =_xlfn.LET(_xlpm.x,VLOOKUP($B55,augment_header!$B$2:$G$72,2,FALSE),IF(_xlpm.x="","",_xlpm.x)) -> 根指令对象 | D55: =IF(VLOOKUP($B55,augment_header!$B$2:$G$72,3,FALSE)="√","√","") -> √ | E55: =IF(VLOOKUP($B55,augment_header!$B$2:$G$72,4,FALSE)="√","√","") | F55: =_xlfn.LET(_xlpm.x,VLOOKUP($B55,augment_header!$B$2:$G$72,5,FALSE),IF(_xlpm.x="","",_xlpm.x)) | G55: 46
A56: 54 | B56: AdditionalSpells_Object | C56: =_xlfn.LET(_xlpm.x,VLOOKUP($B56,augment_header!$B$2:$G$72,2,FALSE),IF(_xlpm.x="","",_xlpm.x)) -> 其它指令对象 | D56: =IF(VLOOKUP($B56,augment_header!$B$2:$G$72,3,FALSE)="√","√","") -> √ | E56: =IF(VLOOKUP($B56,augment_header!$B$2:$G$72,4,FALSE)="√","√","") | F56: =_xlfn.LET(_xlpm.x,VLOOKUP($B56,augment_header!$B$2:$G$72,5,FALSE),IF(_xlpm.x="","",_xlpm.x)) | G56: 48
A57: 55 | B57: RootSpell mSpell DataValues MaxLevel | C57: =_xlfn.LET(_xlpm.x,VLOOKUP($B57,augment_header!$B$2:$G$72,2,FALSE),IF(_xlpm.x="","",_xlpm.x)) -> 最大等级 | D57: =IF(VLOOKUP($B57,augment_header!$B$2:$G$72,3,FALSE)="√","√","") -> √ | E57: =IF(VLOOKUP($B57,augment_header!$B$2:$G$72,4,FALSE)="√","√","") | F57: =_xlfn.LET(_xlpm.x,VLOOKUP($B57,augment_header!$B$2:$G$72,5,FALSE),IF(_xlpm.x="","",_xlpm.x))
A58: 56 | B58: ResourceResolver resourceMap | C58: =_xlfn.LET(_xlpm.x,VLOOKUP($B58,augment_header!$B$2:$G$72,2,FALSE),IF(_xlpm.x="","",_xlpm.x)) -> 资源解析器映射字典 | D58: =IF(VLOOKUP($B58,augment_header!$B$2:$G$72,3,FALSE)="√","√","") -> √ | E58: =IF(VLOOKUP($B58,augment_header!$B$2:$G$72,4,FALSE)="√","√","") | F58: =_xlfn.LET(_xlpm.x,VLOOKUP($B58,augment_header!$B$2:$G$72,5,FALSE),IF(_xlpm.x="","",_xlpm.x)) | G58: 52
A59: 57 | B59: questline {bc1b3d88} | C59: =_xlfn.LET(_xlpm.x,VLOOKUP($B59,augment_header!$B$2:$G$72,2,FALSE),IF(_xlpm.x="","",_xlpm.x)) | D59: =IF(VLOOKUP($B59,augment_header!$B$2:$G$72,3,FALSE)="√","√","") -> √ | E59: =IF(VLOOKUP($B59,augment_header!$B$2:$G$72,4,FALSE)="√","√","") | F59: =_xlfn.LET(_xlpm.x,VLOOKUP($B59,augment_header!$B$2:$G$72,5,FALSE),IF(_xlpm.x="","",_xlpm.x)) | G59: 12
A60: 58 | B60: questline QuestName | C60: =_xlfn.LET(_xlpm.x,VLOOKUP($B60,augment_header!$B$2:$G$72,2,FALSE),IF(_xlpm.x="","",_xlpm.x)) -> 任务线代码 | D60: =IF(VLOOKUP($B60,augment_header!$B$2:$G$72,3,FALSE)="√","√","") -> √ | E60: =IF(VLOOKUP($B60,augment_header!$B$2:$G$72,4,FALSE)="√","√","") | F60: =_xlfn.LET(_xlpm.x,VLOOKUP($B60,augment_header!$B$2:$G$72,5,FALSE),IF(_xlpm.x="","",_xlpm.x)) | G60: 13
A61: 59 | B61: questline {4796bf5f} | C61: =_xlfn.LET(_xlpm.x,VLOOKUP($B61,augment_header!$B$2:$G$72,2,FALSE),IF(_xlpm.x="","",_xlpm.x)) -> 任务线名称键 | D61: =IF(VLOOKUP($B61,augment_header!$B$2:$G$72,3,FALSE)="√","√","") | E61: =IF(VLOOKUP($B61,augment_header!$B$2:$G$72,4,FALSE)="√","√","") | F61: =_xlfn.LET(_xlpm.x,VLOOKUP($B61,augment_header!$B$2:$G$72,5,FALSE),IF(_xlpm.x="","",_xlpm.x))
A62: 60 | B62: questline {c88f1a9b} | C62: =_xlfn.LET(_xlpm.x,VLOOKUP($B62,augment_header!$B$2:$G$72,2,FALSE),IF(_xlpm.x="","",_xlpm.x)) -> 任务完成描述键 | D62: =IF(VLOOKUP($B62,augment_header!$B$2:$G$72,3,FALSE)="√","√","") -> √ | E62: =IF(VLOOKUP($B62,augment_header!$B$2:$G$72,4,FALSE)="√","√","") | F62: =_xlfn.LET(_xlpm.x,VLOOKUP($B62,augment_header!$B$2:$G$72,5,FALSE),IF(_xlpm.x="","",_xlpm.x)) | G62: 40
A63: 61 | B63: questline {06b06978} texturePath | C63: =_xlfn.LET(_xlpm.x,VLOOKUP($B63,augment_header!$B$2:$G$72,2,FALSE),IF(_xlpm.x="","",_xlpm.x)) -> 任务栏位图标纹理路径 | D63: =IF(VLOOKUP($B63,augment_header!$B$2:$G$72,3,FALSE)="√","√","") -> √ | E63: =IF(VLOOKUP($B63,augment_header!$B$2:$G$72,4,FALSE)="√","√","") | F63: =_xlfn.LET(_xlpm.x,VLOOKUP($B63,augment_header!$B$2:$G$72,5,FALSE),IF(_xlpm.x="","",_xlpm.x)) | G63: 55
A64: 62 | B64: questline {ee2e0dbc} | C64: =_xlfn.LET(_xlpm.x,VLOOKUP($B64,augment_header!$B$2:$G$72,2,FALSE),IF(_xlpm.x="","",_xlpm.x)) | D64: =IF(VLOOKUP($B64,augment_header!$B$2:$G$72,3,FALSE)="√","√","") -> √ | E64: =IF(VLOOKUP($B64,augment_header!$B$2:$G$72,4,FALSE)="√","√","") -> √ | F64: =_xlfn.LET(_xlpm.x,VLOOKUP($B64,augment_header!$B$2:$G$72,5,FALSE),IF(_xlpm.x="","",_xlpm.x)) -> FALSE | G64: 18
A65: 63 | B65: questline Milestones | C65: =_xlfn.LET(_xlpm.x,VLOOKUP($B65,augment_header!$B$2:$G$72,2,FALSE),IF(_xlpm.x="","",_xlpm.x)) -> 任务线里程信息 | D65: =IF(VLOOKUP($B65,augment_header!$B$2:$G$72,3,FALSE)="√","√","") | E65: =IF(VLOOKUP($B65,augment_header!$B$2:$G$72,4,FALSE)="√","√","") | F65: =_xlfn.LET(_xlpm.x,VLOOKUP($B65,augment_header!$B$2:$G$72,5,FALSE),IF(_xlpm.x="","",_xlpm.x))
A66: 64 | B66: questline {09d67381} | C66: =_xlfn.LET(_xlpm.x,VLOOKUP($B66,augment_header!$B$2:$G$72,2,FALSE),IF(_xlpm.x="","",_xlpm.x)) -> 任务线相关强化符文 | D66: =IF(VLOOKUP($B66,augment_header!$B$2:$G$72,3,FALSE)="√","√","") -> √ | E66: =IF(VLOOKUP($B66,augment_header!$B$2:$G$72,4,FALSE)="√","√","") | F66: =_xlfn.LET(_xlpm.x,VLOOKUP($B66,augment_header!$B$2:$G$72,5,FALSE),IF(_xlpm.x="","",_xlpm.x)) | G66: 50
A67: 65 | B67: questline {c504ece0} | C67: =_xlfn.LET(_xlpm.x,VLOOKUP($B67,augment_header!$B$2:$G$72,2,FALSE),IF(_xlpm.x="","",_xlpm.x)) | D67: =IF(VLOOKUP($B67,augment_header!$B$2:$G$72,3,FALSE)="√","√","") -> √ | E67: =IF(VLOOKUP($B67,augment_header!$B$2:$G$72,4,FALSE)="√","√","") | F67: =_xlfn.LET(_xlpm.x,VLOOKUP($B67,augment_header!$B$2:$G$72,5,FALSE),IF(_xlpm.x="","",_xlpm.x)) -> FALSE | G67: 19
A68: 66 | B68: questline {4796bf5f}_content_zh | C68: =_xlfn.LET(_xlpm.x,VLOOKUP($B68,augment_header!$B$2:$G$72,2,FALSE),IF(_xlpm.x="","",_xlpm.x)) -> 任务线对应强化符文名称（中文） | D68: =IF(VLOOKUP($B68,augment_header!$B$2:$G$72,3,FALSE)="√","√","") | E68: =IF(VLOOKUP($B68,augment_header!$B$2:$G$72,4,FALSE)="√","√","") | F68: =_xlfn.LET(_xlpm.x,VLOOKUP($B68,augment_header!$B$2:$G$72,5,FALSE),IF(_xlpm.x="","",_xlpm.x))
A69: 67 | B69: questline {4796bf5f}_content_en | C69: =_xlfn.LET(_xlpm.x,VLOOKUP($B69,augment_header!$B$2:$G$72,2,FALSE),IF(_xlpm.x="","",_xlpm.x)) -> 任务线对应强化符文名称（英文） | D69: =IF(VLOOKUP($B69,augment_header!$B$2:$G$72,3,FALSE)="√","√","") | E69: =IF(VLOOKUP($B69,augment_header!$B$2:$G$72,4,FALSE)="√","√","") | F69: =_xlfn.LET(_xlpm.x,VLOOKUP($B69,augment_header!$B$2:$G$72,5,FALSE),IF(_xlpm.x="","",_xlpm.x))
A70: 68 | B70: questline {c88f1a9b}_content_zh | C70: =_xlfn.LET(_xlpm.x,VLOOKUP($B70,augment_header!$B$2:$G$72,2,FALSE),IF(_xlpm.x="","",_xlpm.x)) -> 任务完成描述（中文） | D70: =IF(VLOOKUP($B70,augment_header!$B$2:$G$72,3,FALSE)="√","√","") | E70: =IF(VLOOKUP($B70,augment_header!$B$2:$G$72,4,FALSE)="√","√","") | F70: =_xlfn.LET(_xlpm.x,VLOOKUP($B70,augment_header!$B$2:$G$72,5,FALSE),IF(_xlpm.x="","",_xlpm.x)) | G70: 41
A71: 69 | B71: questline {c88f1a9b}_content_zh_burn | C71: =_xlfn.LET(_xlpm.x,VLOOKUP($B71,augment_header!$B$2:$G$72,2,FALSE),IF(_xlpm.x="","",_xlpm.x)) -> 任务完成描述（中文/数值转换） | D71: =IF(VLOOKUP($B71,augment_header!$B$2:$G$72,3,FALSE)="√","√","") | E71: =IF(VLOOKUP($B71,augment_header!$B$2:$G$72,4,FALSE)="√","√","") | F71: =_xlfn.LET(_xlpm.x,VLOOKUP($B71,augment_header!$B$2:$G$72,5,FALSE),IF(_xlpm.x="","",_xlpm.x)) | G71: 42
A72: 70 | B72: questline {c88f1a9b}_content_en | C72: =_xlfn.LET(_xlpm.x,VLOOKUP($B72,augment_header!$B$2:$G$72,2,FALSE),IF(_xlpm.x="","",_xlpm.x)) -> 任务完成描述（英文） | D72: =IF(VLOOKUP($B72,augment_header!$B$2:$G$72,3,FALSE)="√","√","") | E72: =IF(VLOOKUP($B72,augment_header!$B$2:$G$72,4,FALSE)="√","√","") | F72: =_xlfn.LET(_xlpm.x,VLOOKUP($B72,augment_header!$B$2:$G$72,5,FALSE),IF(_xlpm.x="","",_xlpm.x)) | G72: 43
A73: 71 | B73: questline {c88f1a9b}_content_en_burn | C73: =_xlfn.LET(_xlpm.x,VLOOKUP($B73,augment_header!$B$2:$G$72,2,FALSE),IF(_xlpm.x="","",_xlpm.x)) -> 任务完成描述（英文/数值转换） | D73: =IF(VLOOKUP($B73,augment_header!$B$2:$G$72,3,FALSE)="√","√","") | E73: =IF(VLOOKUP($B73,augment_header!$B$2:$G$72,4,FALSE)="√","√","") | F73: =_xlfn.LET(_xlpm.x,VLOOKUP($B73,augment_header!$B$2:$G$72,5,FALSE),IF(_xlpm.x="","",_xlpm.x)) | G73: 44

Sheet augmentModifier_header
A1: Index | B1: Key | C1: Value | D1: DirectlyImport? | E1: Flexible | F1: OutputOrder
A2: 0 | B2: key | C2: 主键 | D2: √ | F2: 0
A3: 1 | B3: belonging_mapId | C3: 所属地图序号 | F3: 2
A4: 2 | B4: ModifierId | C4: 修饰名称 | D4: √ | E4: √ | F4: 1
A5: 3 | B5: {30b1d74a} | D5: √ | E5: √ | F5: 3
A6: 4 | B6: {ab0ba193} | C6: 抬头键 | D6: √ | E6: √ | F6: 5
A7: 5 | B7: {9346bce8} | D7: √ | E7: √ | F7: 4
A8: 6 | B8: {629a3429} | C8: 附加文本键 | D8: √ | E8: √ | F8: 10
A9: 7 | B9: {6fd14d4c} | C9: 修饰水印路径 | D9: √ | E9: √ | F9: 15
A10: 8 | B10: {ab0ba193}_content_zh | C10: 抬头（中文） | E10: √ | F10: 6
A11: 9 | B11: {ab0ba193}_content_zh_burn | C11: 抬头（中文/去格式化） | E11: √ | F11: 7
A12: 10 | B12: {ab0ba193}_content_en | C12: 抬头（英文） | E12: √ | F12: 8
A13: 11 | B13: {ab0ba193}_content_en_burn | C13: 抬头（英文/去格式化） | E13: √ | F13: 9
A14: 12 | B14: {629a3429}_content_zh | C14: 附加文本（中文） | E14: √ | F14: 11
A15: 13 | B15: {629a3429}_content_zh_burn | C15: 附加文本（中文/去格式化） | E15: √ | F15: 12
A16: 14 | B16: {629a3429}_content_en | C16: 附加文本（英文） | E16: √ | F16: 13
A17: 15 | B17: {629a3429}_content_en_burn | C17: 附加文本（英文/去格式化） | E17: √ | F17: 14

Sheet anvil_header
A1: Index | B1: Key | C1: Value | D1: DirectlyImport? | E1: Flexible | F1: defaultValue | G1: OutputOrder
A2: 0 | B2: key | C2: 主键 | D2: √ | G2: 0
A3: 1 | B3: AugmentNameId | C3: 锻造器代码 | D3: √ | G3: 1
A4: 2 | B4: Enabled | C4: 可用性 | D4: √ | E4: √ | F4: TRUE | G4: 3
A5: 3 | B5: NameTra | C5: 名称键 | D5: √ | G5: 4
A6: 4 | B6: DescriptionTra | C6: 简介键 | D6: √ | G6: 13
A7: 5 | B7: AugmentTooltipTra | C7: 锻造器详细信息键 | D7: √ | G7: 18
A8: 6 | B8: RootSpell | C8: 根指令 | D8: √ | G8: 23
A9: 7 | B9: mAugmentTags | C9: 锻造器标签 | D9: √ | E9: √ | G9: 11
A10: 8 | B10: mBuildTags | C10: 构建标签 | D10: √ | E10: √ | G10: 12
A11: 9 | B11: AugmentLargeIconPath | C11: 锻造器大图标路径 | D11: √ | G11: 25
A12: 10 | B12: AugmentSmallIconPath | C12: 锻造器小图标路径 | D12: √ | G12: 26
A13: 11 | B13: AugmentDisplayTags | C13: 锻造器显示标签 | D13: √ | G13: 9
A14: 12 | B14: AnvilTypes | C14: 锻造器类型 | D14: √ | E14: √ | G14: 7
A15: 13 | B15: ItemLink | C15: 装备链接 | D15: √ | G15: 2
A16: 14 | B16: NameTra_content_zh | C16: 名称（中文） | G16: 5
A17: 15 | B17: NameTra_content_en | C17: 名称（英文） | G17: 6
A18: 16 | B18: DescriptionTra_content_zh | C18: 简介（中文） | G18: 14
A19: 17 | B19: DescriptionTra_content_zh_burn | C19: 简介（中文/数值转换） | G19: 15
A20: 18 | B20: DescriptionTra_content_en | C20: 简介（英文） | G20: 16
A21: 19 | B21: DescriptionTra_content_en_burn | C21: 简介（英文/数值转换） | G21: 17
A22: 20 | B22: AugmentTooltipTra_content_zh | C22: 锻造器详细信息（中文） | G22: 19
A23: 21 | B23: AugmentTooltipTra_content_zh_burn | C23: 锻造器详细信息（中文/数值转换） | G23: 20
A24: 22 | B24: AugmentTooltipTra_content_en | C24: 锻造器详细信息（英文） | G24: 21
A25: 23 | B25: AugmentTooltipTra_content_en_burn | C25: 锻造器详细信息（英文/数值转换） | G25: 22
A26: 24 | B26: AugmentDisplayTags_content | C26: 锻造器显示标签内容 | G26: 10
A27: 25 | B27: anvilRarities | C27: 锻造器位阶 | E27: √ | G27: 8
A28: 26 | B28: RootSpellObject | C28: 根指令对象 | D28: √ | G28: 24

Sheet progressTrack_header
A1: Index | B1: Key | C1: Value | D1: DirectlyImport? | E1: Flexible | F1: defaultValue | G1: OutputOrder
A2: 0 | B2: key | C2: 主键 | D2: √ | G2: 0
A3: 1 | B3: ID | C3: 识别码 | D3: √ | G3: 2
A4: 2 | B4: name | C4: 代码 | D4: √ | G4: 1
A5: 3 | B5: CounterDefinitions | C5: 计数器定义主键列表 | D5: √ | G5: 3
A6: 4 | B6: CounterDefinitions_content | C6: 计数器定义列表 | G6: 4
A7: 5 | B7: MilestoneDefinition_index | C7: 里程碑定义序号 | D7: √ | G7: 5
A8: 6 | B8: MilestoneDefinition_key | C8: 里程碑定义主键 | D8: √ | G8: 6
A9: 7 | B9: MilestoneDefinition ID | C9: 里程碑识别码 | D9: √ | G9: 8
A10: 8 | B10: MilestoneDefinition name | C10: 里程碑代码 | D10: √ | G10: 7
A11: 9 | B11: MilestoneDefinition TriggerValue | C11: 里程碑触发值 | D11: √ | G11: 9
A12: 10 | B12: MilestoneDefinition Counter | C12: 里程碑计数器主键 | D12: √ | G12: 10
A13: 11 | B13: MilestoneDefinition properties | C13: 里程碑属性主键列表 | D13: √ | G13: 13
A14: 12 | B14: MilestoneDefinition properties LocalizedName_content_zh | C14: 奖励分组名称（中文） | G14: 14
A15: 13 | B15: MilestoneDefinition properties LocalizedName_content_en | C15: 奖励分组名称（英文） | G15: 15
A16: 14 | B16: MilestoneDefinition properties rewards {d35466b8}_content_zh | C16: 里程碑奖励（中文） | G16: 16
A17: 15 | B17: MilestoneDefinition properties rewards {d35466b8}_content_en | C17: 里程碑奖励（英文） | G17: 17
A18: 16 | B18: MilestoneDefinition Counter ID | C18: 里程碑计数器识别码 | D18: √ | G18: 12
A19: 17 | B19: MilestoneDefinition Counter name | C19: 里程碑计数器代码 | D19: √ | G19: 11

Sheet KiwiProgressTrack_header
A1: Index | B1: Key | C1: Value | D1: DirectlyImport? | E1: Flexible | F1: defaultValue | G1: OutputOrder
A2: 0 | B2: progression_key | C2: 进度主键 | D2: √ | G2: 0
A3: 1 | B3: key | C3: =_xlfn.LET(_xlpm.x,VLOOKUP($B3,progressTrack_header!$B$2:$G$19,2,FALSE),IF(_xlpm.x="","",_xlpm.x)) -> 主键 | D3: =IF(VLOOKUP($B3,progressTrack_header!$B$2:$G$19,3,FALSE)="√","√","") -> √ | E3: =IF(VLOOKUP($B3,progressTrack_header!$B$2:$G$19,4,FALSE)="√","√","") | F3: =_xlfn.LET(_xlpm.x,VLOOKUP($B3,progressTrack_header!$B$2:$G$19,5,FALSE),IF(_xlpm.x="","",_xlpm.x)) | G3: 1
A4: 2 | B4: ID | C4: =_xlfn.LET(_xlpm.x,VLOOKUP($B4,progressTrack_header!$B$2:$G$19,2,FALSE),IF(_xlpm.x="","",_xlpm.x)) -> 识别码 | D4: =IF(VLOOKUP($B4,progressTrack_header!$B$2:$G$19,3,FALSE)="√","√","") -> √ | G4: 3
A5: 3 | B5: name | C5: =_xlfn.LET(_xlpm.x,VLOOKUP($B5,progressTrack_header!$B$2:$G$19,2,FALSE),IF(_xlpm.x="","",_xlpm.x)) -> 代码 | D5: =IF(VLOOKUP($B5,progressTrack_header!$B$2:$G$19,3,FALSE)="√","√","") -> √ | G5: 2
A6: 4 | B6: CounterDefinitions | C6: =_xlfn.LET(_xlpm.x,VLOOKUP($B6,progressTrack_header!$B$2:$G$19,2,FALSE),IF(_xlpm.x="","",_xlpm.x)) -> 计数器定义主键列表 | D6: =IF(VLOOKUP($B6,progressTrack_header!$B$2:$G$19,3,FALSE)="√","√","") -> √ | G6: 4
A7: 5 | B7: CounterDefinitions_content | C7: =_xlfn.LET(_xlpm.x,VLOOKUP($B7,progressTrack_header!$B$2:$G$19,2,FALSE),IF(_xlpm.x="","",_xlpm.x)) -> 计数器定义列表 | D7: =IF(VLOOKUP($B7,progressTrack_header!$B$2:$G$19,3,FALSE)="√","√","") | G7: 5
A8: 6 | B8: MilestoneDefinition_index | C8: =_xlfn.LET(_xlpm.x,VLOOKUP($B8,progressTrack_header!$B$2:$G$19,2,FALSE),IF(_xlpm.x="","",_xlpm.x)) -> 里程碑定义序号 | D8: =IF(VLOOKUP($B8,progressTrack_header!$B$2:$G$19,3,FALSE)="√","√","") -> √ | G8: 6
A9: 7 | B9: MilestoneDefinition_key | C9: =_xlfn.LET(_xlpm.x,VLOOKUP($B9,progressTrack_header!$B$2:$G$19,2,FALSE),IF(_xlpm.x="","",_xlpm.x)) -> 里程碑定义主键 | D9: =IF(VLOOKUP($B9,progressTrack_header!$B$2:$G$19,3,FALSE)="√","√","") -> √ | G9: 7
A10: 8 | B10: MilestoneDefinition ID | C10: =_xlfn.LET(_xlpm.x,VLOOKUP($B10,progressTrack_header!$B$2:$G$19,2,FALSE),IF(_xlpm.x="","",_xlpm.x)) -> 里程碑识别码 | D10: =IF(VLOOKUP($B10,progressTrack_header!$B$2:$G$19,3,FALSE)="√","√","") -> √ | G10: 9
A11: 9 | B11: MilestoneDefinition name | C11: =_xlfn.LET(_xlpm.x,VLOOKUP($B11,progressTrack_header!$B$2:$G$19,2,FALSE),IF(_xlpm.x="","",_xlpm.x)) -> 里程碑代码 | D11: =IF(VLOOKUP($B11,progressTrack_header!$B$2:$G$19,3,FALSE)="√","√","") -> √ | G11: 8
A12: 10 | B12: MilestoneDefinition TriggerValue | C12: =_xlfn.LET(_xlpm.x,VLOOKUP($B12,progressTrack_header!$B$2:$G$19,2,FALSE),IF(_xlpm.x="","",_xlpm.x)) -> 里程碑触发值 | D12: =IF(VLOOKUP($B12,progressTrack_header!$B$2:$G$19,3,FALSE)="√","√","") -> √ | G12: 10
A13: 11 | B13: MilestoneDefinition Counter | C13: =_xlfn.LET(_xlpm.x,VLOOKUP($B13,progressTrack_header!$B$2:$G$19,2,FALSE),IF(_xlpm.x="","",_xlpm.x)) -> 里程碑计数器主键 | D13: =IF(VLOOKUP($B13,progressTrack_header!$B$2:$G$19,3,FALSE)="√","√","") -> √ | G13: 11
A14: 12 | B14: MilestoneDefinition properties | C14: =_xlfn.LET(_xlpm.x,VLOOKUP($B14,progressTrack_header!$B$2:$G$19,2,FALSE),IF(_xlpm.x="","",_xlpm.x)) -> 里程碑属性主键列表 | D14: =IF(VLOOKUP($B14,progressTrack_header!$B$2:$G$19,3,FALSE)="√","√","") -> √ | G14: 14
A15: 13 | B15: MilestoneDefinition properties LocalizedName_content_zh | C15: =_xlfn.LET(_xlpm.x,VLOOKUP($B15,progressTrack_header!$B$2:$G$19,2,FALSE),IF(_xlpm.x="","",_xlpm.x)) -> 奖励分组名称（中文） | D15: =IF(VLOOKUP($B15,progressTrack_header!$B$2:$G$19,3,FALSE)="√","√","") | G15: 15
... A20: 18 | B20: MilestoneDefinition Counter name | C20: =_xlfn.LET(_xlpm.x,VLOOKUP($B20,progressTrack_header!$B$2:$G$19,2,FALSE),IF(_xlpm.x="","",_xlpm.x)) -> 里程碑计数器代码 | D20: =IF(VLOOKUP($B20,progressTrack_header!$B$2:$G$19,3,FALSE)="√","√","") -> √ | G20: 12

Sheet rewardGroup_header
A1: Index | B1: Key | C1: Value | D1: DirectlyImport? | E1: Flexible | F1: defaultValue | G1: OutputOrder
A2: 0 | B2: key | C2: 主键 | D2: √ | G2: 0
A3: 1 | B3: ID | C3: 识别码 | G3: 5
A4: 2 | B4: internalName | C4: 内置名 | G4: 4
A5: 3 | B5: LocalizedName | C5: 名称键 | E5: √ | G5: 1
A6: 4 | B6: rewardStrategy | C6: 奖励策略 | E6: √ | G6: 6
A7: 5 | B7: celebrationType | C7: 庆祝类型 | E7: √ | G7: 7
A8: 6 | B8: selectionStrategyConfig minSelectionsAllowed | C8: 最小选择数量 | G8: 8
A9: 7 | B9: selectionStrategyConfig maxSelectionsAllowed | C9: 最大选择数量 | G9: 9
A10: 8 | B10: LocalizedName_content_zh | C10: 名称（中文） | G10: 2
A11: 9 | B11: LocalizedName_content_en | C11: 名称（英文） | G11: 3
A12: 10 | B12: reward_index | C12: 奖励序号 | G12: 10
A13: 11 | B13: reward {31c5f01c} | C13: 奖励名称键 | G13: 12
A14: 12 | B14: reward {d35466b8} | C14: 奖励描述键 | G14: 18
A15: 13 | B15: reward quantity | C15: 奖励数量 | E15: √ | G15: 16
A16: 14 | B16: reward itemID | C16: 奖励道具识别码 | E16: √ | G16: 15
A17: 15 | B17: reward {0ba947a2} | E17: √ | G17: 17
A18: 16 | B18: reward {00fa4f01} | C18: 奖励货币主键 | E18: √ | G18: 21
A19: 17 | B19: reward __type | C19: 奖励类型 | G19: 11
A20: 18 | B20: reward media image | C20: 奖励缩略图路径（小写）
A21: 19 | B21: reward media {15c4c3cb} | C21: 奖励缩略图路径 | E21: √ | G21: 23
A22: 20 | B22: reward {00fa4f01} mInternalName | C22: 奖励货币内置名 | G22: 22
A23: 21 | B23: reward {31c5f01c}_content_zh | C23: 奖励名称（中文） | G23: 13
A24: 22 | B24: reward {31c5f01c}_content_en | C24: 奖励名称（英文） | G24: 14
A25: 23 | B25: reward {d35466b8}_content_zh | C25: 奖励描述（中文） | G25: 19
A26: 24 | B26: reward {d35466b8}_content_en | C26: 奖励描述（英文） | G26: 20

Sheet KiwiReward_header
A1: Index | B1: Key | C1: Value | D1: DirectlyImport? | E1: Flexible | F1: defaultValue | G1: OutputOrder
A2: 0 | B2: key | C2: 主键 | D2: √ | G2: 1
A3: 1 | B3: seriesId | C3: 序列识别码 | G3: 2
A4: 2 | B4: {50c23533} | C4: 赛季代号 | G4: 3
A5: 3 | B5: progression_key | C5: 进度主键 | G5: 0
A6: 4 | B6: quest_index | C6: 大型任务序号 | G6: 4
A7: 5 | B7: quest_key | C7: 大型任务主键 | G7: 5
A8: 6 | B8: quest {7fad8491} | G8: 6
A9: 7 | B9: quest {8ff60339} | C9: 小型任务主键 | G9: 10
A10: 8 | B10: quest rewards | C10: 奖励主键 | G10: 8
A11: 9 | B11: quest {7fad8491} {8d7928e4} | G11: 7
A12: 10 | B12: quest {90e39fce} {8ff60339} | C12: 前驱小型任务列表 | E12: √ | G12: 11
A13: 11 | B13: quest rewards Items | C13: 奖励道具 | G13: 9

Sheet KiwiQuest_header
A1: Index | B1: Key | C1: Value | D1: DirectlyImport? | E1: Flexible | F1: defaultValue | G1: OutputOrder
A2: 0 | B2: key | C2: 主键 | D2: √ | G2: 8
A3: 1 | B3: {1ba4e4a5} | D3: √ | G3: 9
A4: 2 | B4: TitleTra | C4: 标题键 | D4: √ | G4: 13
A5: 3 | B5: DescriptionTra | C5: 描述键 | D5: √ | G5: 19
A6: 4 | B6: missions | C6: 小型任务主键列表 | D6: √ | G6: 26
A7: 5 | B7: {0f400dc1} | C7: 进阶大型任务主键 | D7: √ | E7: √ | G7: 25
A8: 6 | B8: QuestData QuestNameTra | C8: 名称键 | D8: √ | G8: 16
A9: 7 | B9: QuestData {c88f1a9b} | C9: 简介键 | D9: √ | G9: 22
A10: 8 | B10: QuestData {ee2e0dbc} | D10: √ | F10: FALSE | G10: 10
A11: 9 | B11: QuestData {c504ece0} | D11: √ | F11: FALSE | G11: 11
A12: 10 | B12: QuestData {fafa4664} | C12: 统计指标 | D12: √ | G12: 12
A13: 11 | B13: TitleTra_content_zh | C13: 标题（中文） | G13: 14
A14: 12 | B14: TitleTra_content_en | C14: 标题（英文） | G14: 15
A15: 13 | B15: DescriptionTra_content_zh | C15: 描述（中文） | G15: 20
A16: 14 | B16: DescriptionTra_content_en | C16: 描述（英文） | G16: 21
A17: 15 | B17: QuestData QuestNameTra_content_zh | C17: 名称（中文） | G17: 17
A18: 16 | B18: QuestData QuestNameTra_content_en | C18: 名称（英文） | G18: 18
A19: 17 | B19: QuestData {c88f1a9b}_content_zh | C19: 简介（中文） | G19: 23
A20: 18 | B20: QuestData {c88f1a9b}_content_en | C20: 简介（英文） | G20: 24
A21: 19 | B21: level | C21: 层级 | G21: 7
A22: 20 | B22: parent_questGroup_key | C22: 所属大型任务分组主键 | G22: 3
A23: 21 | B23: questGroup Locked | C23: 大型任务分组已锁定 | D23: √ | E23: √ | F23: FALSE | G23: 4
A24: 22 | B24: questGroup {5e7167cd} | D24: √ | E24: √ | G24: 5
A25: 23 | B25: quest_index | C25: 大型任务序号 | D25: √ | G25: 6
A26: 24 | B26: parent_questEvent_key | C26: 所属大型任务事件主键 | G26: 1
A27: 25 | B27: questGroup_index | C27: 大型任务分组序号 | D27: √ | G27: 2
A28: 26 | B28: parent_progression_key | C28: 所属进度主键 | D28: √ | G28: 0

Sheet KiwiMission_header
A1: Index | B1: Key | C1: Value | D1: DirectlyImport? | E1: Flexible | F1: defaultValue | G1: OutputOrder
A2: 0 | B2: key | C2: 主键 | D2: √ | G2: 12
A3: 1 | B3: missionId | C3: 小型任务代码 | D3: √ | G3: 13
A4: 2 | B4: {7fad8491} | C4: 小型任务奖励类型主键 | D4: √ | G4: 14
A5: 3 | B5: {7fad8491} {8d7928e4} | C5: 小型任务奖励类型识别码 | G5: 15
A6: 4 | B6: objective_index | C6: 目标序号 | D6: √ | G6: 16
A7: 5 | B7: objective statId | C7: 目标统计指标 | D7: √ | G7: 20
A8: 6 | B8: objective {166f6876} | C8: 目标完成条件 | D8: √ | E8: √ | G8: 21
A9: 7 | B9: objective DescriptionTraKey | C9: 目标描述键 | D9: √ | G9: 17
A10: 8 | B10: objective DescriptionTraKey_content_zh | C10: 目标描述（中文） | G10: 18
A11: 9 | B11: objective DescriptionTraKey_content_en | C11: 目标描述（英文） | G11: 19
A12: 10 | B12: parent_quest_key | C12: 所属大型任务主键 | G12: 7
A13: 11 | B13: quest TitleTra_content_zh | C13: 大型任务标题（中文） | G13: 8
A14: 12 | B14: quest TitleTra_content_en | C14: 大型任务标题（英文） | G14: 9
A15: 13 | B15: quest level | C15: 大型任务等级 | G15: 10
A16: 14 | B16: mission_index | C16: 小型任务序号 | G16: 11
A17: 15 | B17: parent_questGroup_key | C17: 所属大型任务分组主键 | G17: 3
A18: 16 | B18: questGroup Locked | C18: 大型任务分组已锁定 | D18: √ | E18: √ | F18: FALSE | G18: 4
A19: 17 | B19: questGroup {5e7167cd} | D19: √ | E19: √ | G19: 5
A20: 18 | B20: quest_index | C20: 大型任务序号 | D20: √ | G20: 6
A21: 19 | B21: parent_questEvent_key | C21: 所属大型任务事件主键 | G21: 1
A22: 20 | B22: questGroup_index | C22: 大型任务分组序号 | D22: √ | G22: 2
A23: 21 | B23: parent_progression_key | C23: 所属进度主键 | D23: √ | G23: 0

Sheet KiwiQuestMilestone_header
A1: Index | B1: Key | C1: Value | D1: DirectlyImport? | E1: Flexible | F1: defaultValue | G1: OutputOrder
A2: 0 | B2: key | C2: 大型任务主键 | D2: √ | G2: 8
A3: 1 | B3: TitleTra_content_zh | C3: 大型任务标题（中文） | G3: 9
A4: 2 | B4: TitleTra_content_en | C4: 大型任务标题（英文） | G4: 10
A5: 3 | B5: level | C5: 大型任务等级 | G5: 7
A6: 4 | B6: milestone_index | C6: 里程碑序号 | D6: √ | G6: 11
A7: 5 | B7: milestone {7fec0982} | C7: 里程碑数据 | D7: √ | G7: 15
A8: 6 | B8: milestone MilestoneDescriptionTra | C8: 里程碑描述键 | D8: √ | G8: 12
A9: 7 | B9: milestone MilestoneDescriptionTra_content_zh | C9: 里程碑描述（中文） | G9: 13
A10: 8 | B10: milestone MilestoneDescriptionTra_content_en | C10: 里程碑描述（英文） | G10: 14
A11: 9 | B11: parent_questGroup_key | C11: 所属大型任务分组主键 | G11: 3
A12: 10 | B12: questGroup Locked | C12: 大型任务分组已锁定 | D12: √ | E12: √ | F12: FALSE | G12: 4
A13: 11 | B13: questGroup {5e7167cd} | D13: √ | E13: √ | G13: 5
A14: 12 | B14: quest_index | C14: 大型任务序号 | D14: √ | G14: 6
A15: 13 | B15: parent_questEvent_key | C15: 所属大型任务事件主键 | G15: 1
A16: 14 | B16: questGroup_index | C16: 大型任务分组序号 | D16: √ | G16: 2
A17: 15 | B17: parent_progression_key | C17: 所属进度主键 | G17: 0

Sheet CherryGoH_header
A1: Index | B1: Key | C1: Value | D1: DirectlyImport? | E1: Flexible | F1: defaultValue | G1: OutputOrder
A2: 0 | B2: GoHKey | C2: 嘉宾主键 | G2: 0
A3: 1 | B3: name | C3: 名称 | D3: √ | G3: 2
A4: 2 | B4: Character | C4: 角色文件夹 | D4: √ | G4: 3
A5: 3 | B5: Enabled | C5: 可用性 | D5: √ | E5: √ | F5: TRUE | G5: 4
A6: 4 | B6: SkinID | C6: 皮肤序号 | D6: √ | E6: √ | G6: 12
A7: 5 | B7: {b0f32561} | C7: 可用回合 | D7: √ | G7: 5
A8: 6 | B8: {e7879fb5} | C8: 互斥荣誉嘉宾 | D8: √ | E8: √ | G8: 21
A9: 7 | B9: eventKey | C9: 事件主键 | G9: 1
A10: 8 | B10: DefaultTra title | C10: 事件键 | D10: √ | G10: 6
A11: 9 | B11: DefaultTra Subtitle | C11: 姓名键 | D11: √ | G11: 9
A12: 10 | B12: DefaultTra {bff2f361} | C12: 简述键 | D12: √ | G12: 13
A13: 11 | B13: DefaultTra {3b7aa707} | C13: 详细信息键 | D13: √ | G13: 16
A14: 12 | B14: EventIcon | C14: 事件图标主键 | D14: √ | G14: 24
A15: 13 | B15: EventIconPath | C15: 事件缩略图路径 | D15: √ | G15: 25
A16: 14 | B16: DefaultTra title_content_zh | C16: 事件（中文） | G16: 7
A17: 15 | B17: DefaultTra title_content_en | C17: 事件（英文） | G17: 8
A18: 16 | B18: DefaultTra Subtitle_content_zh | C18: 姓名（中文） | G18: 10
A19: 17 | B19: DefaultTra Subtitle_content_en | C19: 姓名（英文） | G19: 11
A20: 18 | B20: DefaultTra {bff2f361}_content_zh | C20: 简述（中文） | G20: 14
A21: 19 | B21: DefaultTra {bff2f361}_content_en | C21: 简述（英文） | G21: 15
A22: 20 | B22: DefaultTra {3b7aa707}_content_zh | C22: 详细信息（中文） | G22: 17
A23: 21 | B23: DefaultTra {3b7aa707}_content_en | C23: 详细信息（英文） | G23: 19
A24: 22 | B24: DefaultTra {3b7aa707}_content_zh_burn | C24: 详细信息（中文/去格式化） | G24: 18
A25: 23 | B25: DefaultTra {3b7aa707}_content_en_burn | C25: 详细信息（英文/去格式化） | G25: 20
A26: 24 | B26: {e7879fb5} Subtitle_contents_zh | C26: 互斥荣誉嘉宾姓名（中文） | G26: 22
A27: 25 | B27: {e7879fb5} Subtitle_contents_en | C27: 互斥荣誉嘉宾姓名（英文） | G27: 23

Sheet KiwiGoH_header
A1: Index | B1: Key | C1: Value | D1: DirectlyImport? | E1: Flexible | F1: defaultValue | G1: OutputOrder
A2: 0 | B2: GoHKey | C2: 嘉宾主键 | G2: 0
A3: 1 | B3: name | C3: 名称 | D3: √ | G3: 2
A4: 2 | B4: {fb33ef71} | C4: 代号 | D4: √ | G4: 3
A5: 3 | B5: {b0f32561} | C5: 可用回合 | D5: √ | G5: 4
A6: 4 | B6: ResourceResolver resourceMap | C6: 视觉特效资源映射字典 | D6: √ | G6: 21
A7: 5 | B7: eventKey | C7: 事件主键 | G7: 1
A8: 6 | B8: DefaultTra title | C8: 事件键 | D8: √ | G8: 5
A9: 7 | B9: DefaultTra Subtitle | C9: 姓名键 | D9: √ | G9: 8
A10: 8 | B10: DefaultTra {bff2f361} | C10: 简述键 | D10: √ | G10: 11
A11: 9 | B11: DefaultTra {3b7aa707} | C11: 详细信息键 | D11: √ | G11: 14
A12: 10 | B12: EventIcon | C12: 事件图标主键 | D12: √ | G12: 19
A13: 11 | B13: EventIconPath | C13: 事件缩略图路径 | D13: √ | G13: 20
A14: 12 | B14: DefaultTra title_content_zh | C14: 事件（中文） | G14: 6
A15: 13 | B15: DefaultTra title_content_en | C15: 事件（英文） | G15: 7
A16: 14 | B16: DefaultTra Subtitle_content_zh | C16: 姓名（中文） | G16: 9
A17: 15 | B17: DefaultTra Subtitle_content_en | C17: 姓名（英文） | G17: 10
A18: 16 | B18: DefaultTra {bff2f361}_content_zh | C18: 简述（中文） | G18: 12
A19: 17 | B19: DefaultTra {bff2f361}_content_en | C19: 简述（英文） | G19: 13
A20: 18 | B20: DefaultTra {3b7aa707}_content_zh | C20: 详细信息（中文） | G20: 15
A21: 19 | B21: DefaultTra {3b7aa707}_content_en | C21: 详细信息（英文） | G21: 17
A22: 20 | B22: DefaultTra {3b7aa707}_content_zh_burn | C22: 详细信息（中文/去格式化） | G22: 16
A23: 21 | B23: DefaultTra {3b7aa707}_content_en_burn | C23: 详细信息（英文/去格式化） | G23: 18

Sheet cameo_header
A1: Index | B1: Key | C1: Value | D1: DirectlyImport? | E1: defaultValue | F1: OutputOrder
A2: 0 | B2: key | C2: 主键 | D2: √ | F2: 0
A3: 1 | B3: championName | C3: 英雄文件夹 | D3: √ | F3: 1
A4: 2 | B4: ChampionNameHash | C4: 英雄文件夹加密字符串 | D4: √
A5: 3 | B5: Enabled | C5: 可用性 | D5: √ | E5: TRUE | F5: 2
A6: 4 | B6: {be8164b4} | C6: 事件键 | D6: √ | F6: 3
A7: 5 | B7: {3942d706} | C7: 简述键 | D7: √ | F7: 6
A8: 6 | B8: {f426fde9} | C8: 详细信息键 | D8: √ | F8: 9
A9: 7 | B9: {be8164b4}_content_zh | C9: 事件（中文） | F9: 4
A10: 8 | B10: {be8164b4}_content_en | C10: 事件（英文） | F10: 5
A11: 9 | B11: {3942d706}_content_zh | C11: 简述（中文） | F11: 7
A12: 10 | B12: {3942d706}_content_en | C12: 简述（英文） | F12: 8
A13: 11 | B13: {f426fde9}_content_zh | C13: 详细信息（中文） | F13: 10
A14: 12 | B14: {f426fde9}_content_en | C14: 详细信息（英文） | F14: 12
A15: 13 | B15: {f426fde9}_content_zh_burn | C15: 详细信息（中文/去格式化） | F15: 11
A16: 14 | B16: {f426fde9}_content_en_burn | C16: 详细信息（英文/去格式化） | F16: 13

Sheet CherryRoundList_header
A1: Index | B1: Key | C1: Value | D1: DirectlyImport? | E1: Flexible | F1: OutputOrder
A2: 0 | B2: key | C2: 方案主键 | D2: √ | F2: 0
A3: 1 | B3: {37e6e53a} | C3: 旗标 | D3: √
A4: 2 | B4: roundNumber | C4: 回合数 | D4: √ | F4: 1
A5: 3 | B5: roundKey | C5: 回合主键 | D5: √ | F5: 2
A6: 4 | B6: round_phaseNames_content_zh | C6: 回合阶段名称（中文） | F6: 3
A7: 5 | B7: round_phaseNames_content_en | C7: 回合阶段名称（英文） | F7: 4

Sheet CherryRound_header
A1: Index | B1: Key | C1: Value | D1: DirectlyImport? | E1: Flexible | F1: OutputOrder
A2: 0 | B2: key | C2: 主键 | D2: √ | F2: 0
A3: 1 | B3: Phases | C3: 阶段主键列表 | D3: √ | F3: 1
A4: 2 | B4: Phases_names_content_zh | C4: 阶段名称（中文） | D4: √ | F4: 2
A5: 3 | B5: Phases_names_content_en | C5: 阶段名称（英文） | D5: √ | F5: 3

Sheet CherryPhase_header
A1: Index | B1: Key | C1: Value | D1: DirectlyImport? | E1: Flexible | F1: OutputOrder
A2: 0 | B2: key | C2: 主键 | D2: √ | F2: 0
A3: 1 | B3: type | C3: 回合类型 | D3: √ | E3: √ | F3: 4
A4: 2 | B4: DisplayNameTra | C4: 显示名键 | D4: √ | F4: 1
A5: 3 | B5: {7011dd78} | C5: 即将到来的事件缩略图路径 | D5: √ | F5: 11
A6: 4 | B6: {44bdfcf8} | C6: 正在发生的事件缩略图路径 | D6: √ | F6: 12
A7: 5 | B7: {bafc35cb} | C7: 已经完成的事件缩略图路径 | D7: √ | F7: 13
A8: 6 | B8: DisplayNameTra_content_zh | C8: 显示名（中文） | F8: 2
A9: 7 | B9: DisplayNameTra_content_en | C9: 显示名（英文） | F9: 3
A10: 8 | B10: subPhase number | C10: 子阶段序号 | D10: √ | F10: 5
A11: 9 | B11: subPhase type | C11: 子阶段类型 | D11: √ | E11: √ | F11: 6
A12: 10 | B12: subPhase duration | C12: 子阶段持续时间（秒） | D12: √ | F12: 7
A13: 11 | B13: subPhase FlashOnTimeRemaining | C13: 第一次闪烁倒计时 | D13: √ | E13: √ | F13: 8
A14: 12 | B14: subPhase SecondFlashOnTimeRemaining | C14: 第二次闪烁倒计时 | D14: √ | E14: √ | F14: 9
A15: 13 | B15: subPhase TimerBarDefaultColor | C15: 时间轴默认颜色方案 | D15: √ | E15: √ | F15: 10

Sheet CherryRoundPhase_header
A1: Index | B1: Key | C1: Value | D1: DirectlyImport? | E1: Flexible | F1: OutputOrder
A2: 0 | B2: key | C2: 方案主键 | D2: √ | F2: 0
A3: 1 | B3: {37e6e53a} | C3: 旗标 | D3: √
A4: 2 | B4: roundNumber | C4: 回合数 | D4: √ | F4: 1
A5: 3 | B5: roundKey | C5: 回合主键 | D5: √ | F5: 2
A6: 4 | B6: PhaseNumber | C6: 阶段数 | F6: 3
A7: 5 | B7: PhaseKey | C7: 阶段主键 | F7: 4
A8: 6 | B8: type | C8: 回合类型 | D8: √ | E8: √ | F8: 8
A9: 7 | B9: DisplayNameTra | C9: 显示名键 | F9: 5
A10: 8 | B10: {7011dd78} | C10: 即将到来的事件缩略图路径 | F10: 15
A11: 9 | B11: {44bdfcf8} | C11: 正在发生的事件缩略图路径 | F11: 16
A12: 10 | B12: {bafc35cb} | C12: 已经完成的事件缩略图路径 | F12: 17
A13: 11 | B13: DisplayNameTra_content_zh | C13: 显示名（中文） | F13: 6
A14: 12 | B14: DisplayNameTra_content_en | C14: 显示名（英文） | F14: 7
A15: 13 | B15: subPhase number | C15: 子阶段序号 | F15: 9
A16: 14 | B16: subPhase type | C16: 子阶段类型 | F16: 10
A17: 15 | B17: subPhase duration | C17: 子阶段持续时间（秒） | F17: 11
A18: 16 | B18: subPhase FlashOnTimeRemaining | C18: 第一次闪烁倒计时 | F18: 12
A19: 17 | B19: subPhase SecondFlashOnTimeRemaining | C19: 第二次闪烁倒计时 | F19: 13
A20: 18 | B20: subPhase TimerBarDefaultColor | C20: 时间轴默认颜色方案 | F20: 14

Sheet TFTSet_header
A1: Index | B1: Key | C1: Value | D1: DirectlyImport? | E1: Flexible | F1: defaultValue | G1: OutputOrder
A2: 0 | B2: key | C2: 主键 | G2: 0
A3: 1 | B3: name | C3: 赛季代码 | D3: √ | G3: 1
A4: 2 | B4: CoreName | C4: 核心代码 | D4: √ | G4: 2
A5: 3 | B5: displayName | C5: 显示名键 | D5: √ | G5: 4
A6: 4 | B6: TftGameType | C6: 云顶之弈游戏类型代号 | D6: √ | E6: √ | G6: 7
A7: 5 | B7: number | C7: 赛季号 | D7: √ | E7: √ | G7: 3
A8: 6 | B8: AugmentContainerTexture | C8: 强化符文容器纹理 | D8: √ | G8: 220
A9: 7 | B9: AugmentContainerName | C9: 强化符文容器名称 | D9: √ | G9: 221
A10: 8 | B10: {46413d37} | D10: √ | G10: 236
A11: 9 | B11: {ecb7a24b} | D11: √ | E11: √ | G11: 237
A12: 10 | B12: DebugCharacterLists | C12: 调试角色列表 | D12: √ | E12: √ | G12: 9
A13: 11 | B13: characterLists | C13: 地图角色列表 | D13: √ | E13: √ | G13: 11
A14: 12 | B14: tftCharacterLists | C14: 云顶之弈角色列表 | D14: √ | G14: 13
A15: 13 | B15: itemLists | C15: 装备列表 | D15: √ | E15: √ | G15: 15
A16: 14 | B16: TraitLists | C16: 羁绊列表 | D16: √ | E16: √ | G16: 20
A17: 15 | B17: {0a8ae70b} | C17: 羁绊变异列表 | D17: √ | E17: √ | G17: 21
A18: 16 | B18: {8d56bbf6} | C18: 其它装备列表 | D18: √ | E18: √ | G18: 25
A19: 17 | B19: ShopDataLists | C19: 商店数据列表 | D19: √ | G19: 27
A20: 18 | B20: DropRateTables | C20: 掉率列表 | D20: √ | E20: √ | G20: 33
A21: 19 | B21: ShopContentData | C21: 商店内容键 | D21: √ | E21: √ | G21: 31
A22: 20 | B22: TeamPlannerSetData | C22: 小队规划器 | D22: √ | E22: √ | G22: 171
A23: 21 | B23: ScriptData | C23: 指令数据 | D23: √ | E23: √ | G23: 153
A24: 22 | B24: StageRoundData | C24: 回合阶段键 | D24: √ | E24: √ | G24: 34
A25: 23 | B25: {34e20808} | D25: √ | E25: √ | G25: 238
A26: 24 | B26: {fc63519e} | C26: 特殊回合阶段键 | D26: √ | E26: √ | G26: 36
A27: 25 | B27: RegionPortalList | C27: 传送门列表键 | D27: √ | E27: √ | G27: 69
A28: 26 | B28: {44933d76} | C28: 强化符文规则名称 | D28: √ | E28: √ | G28: 37
A29: 27 | B29: EncounterList | C29: 奇遇事件列表键 | D29: √ | E29: √ | G29: 73
A30: 28 | B30: {e6c62bd9} | D30: √ | E30: √ | G30: 239
A31: 29 | B31: {8e557b7b} | C31: 六费卡指令列表 | D31: √ | E31: √ | G31: 154
A32: 30 | B32: {032ade10} | C32: 赛博装备列表 | D32: √ | E32: √ | G32: 16
A33: 31 | B33: VfxResourceResolver | C33: 视觉特效资源解析器 | D33: √ | E33: √ | G33: 216
A34: 32 | B34: {f99705af} | C34: 其它资源解析器列表 | D34: √ | E34: √ | G34: 218
A35: 33 | B35: AudioFeature | C35: 音频特征 | D35: √ | E35: √ | G35: 235
A36: 34 | B36: CustomShopTooltip | C36: 六费卡指令说明键 | D36: √ | E36: √ | G36: 155
A37: 35 | B37: {4bf0e5a9} | C37: 六费单位属性键 | D37: √ | E37: √ | G37: 168
A38: 36 | B38: AdditionalBankUnits | C38: 六费单位音效键 | D38: √ | E38: √ | G38: 169
A39: 37 | B39: InfoNubData TitleKey | C39: 特定赛季提示标题键 | D39: √ | E39: √ | G39: 177
A40: 38 | B40: InfoNubData BodyKey | C40: 特定赛季提示主体键 | D40: √ | E40: √ | G40: 180
A41: 39 | B41: InfoNubData Trait | C41: 特定赛季羁绊键 | E41: √ | G41: 185
A42: 40 | B42: InfoNubData {eb74e3c6} | C42: 特定赛季掉率信息路径 | E42: √ | G42: 188
A43: 41 | B43: InfoNubData ActiveTitleKey | C43: 特定赛季活动提示标题键 | E43: √ | G43: 189
A44: 42 | B44: InfoNubData ActiveBodyKey | C44: 特定赛季活动提示主体键 | E44: √ | G44: 192
A45: 43 | B45: InfoNubData InactiveTitleKey | C45: 特定赛季非活动提示标题键 | E45: √ | G45: 197
A46: 44 | B46: InfoNubData InactiveBodyKey | C46: 特定赛季非活动提示主体键 | E46: √ | G46: 200
A47: 45 | B47: InfoNubData UnitProperty | C47: 特定赛季单位属性键 | E47: √ | G47: 205
A48: 46 | B48: InfoNubData __type | C48: 特定赛季数据类型 | G48: 176
A49: 47 | B49: GameStartSequenceOverride | C49: 游戏开始序列覆盖 | D49: √ | E49: √ | G49: 207
A50: 48 | B50: AugmentUiOverride BaseLoadable | C50: 强化符文PC端显示界面 | D50: √ | E50: √ | G50: 222
A51: 49 | B51: AugmentUiOverride MobileLoadable | C51: 强化符文移动端显示界面 | D51: √ | E51: √ | G51: 223
A52: 50 | B52: UnitShopUiOverride BaseLoadable | C52: 弈子PC端商店显示界面 | D52: √ | E52: √ | G52: 224
A53: 51 | B53: UnitShopUiOverride MobileLoadable | C53: 弈子移动端商店显示界面 | D53: √ | E53: √ | G53: 225
A54: 52 | B54: {0f5c7941} BaseLoadable | D54: √ | E54: √ | G54: 226
A55: 53 | B55: {0f5c7941} MobileLoadable | D55: √ | E55: √ | G55: 227
A56: 54 | B56: {1d43802b} BaseLoadable | D56: √ | E56: √ | G56: 228
A57: 55 | B57: {1d43802b} MobileLoadable | D57: √ | E57: √ | G57: 229
A58: 56 | B58: {9370f055} BaseLoadable | D58: √ | E58: √ | G58: 230
A59: 57 | B59: {9370f055} MobileLoadable | D59: √ | E59: √ | G59: 231
A60: 58 | B60: {dacd2fc1} {07e29603} | D60: √ | E60: √ | G60: 240
A61: 59 | B61: {dacd2fc1} {a211c44d} | D61: √ | E61: √ | F61: TRUE | G61: 241
A62: 60 | B62: {dacd2fc1} {27c5053e} | D62: √ | E62: √ | G62: 242
A63: 61 | B63: ItemTagData {24d36c27} TRAKey | D63: √ | E63: √ | G63: 38
A64: 62 | B64: ItemTagData {ee609993} TRAKey | D64: √ | G64: 41
A65: 63 | B65: ItemTagData {8fba48a3} TRAKey | D65: √ | G65: 44
A66: 64 | B66: ItemTagData {382a7131} TRAKey | D66: √ | G66: 47
A67: 65 | B67: ItemTagData {8e758f9d} TRAKey | D67: √ | G67: 50
A68: 66 | B68: ItemTagData {a7b22c38} TRAKey | D68: √ | G68: 53
A69: 67 | B69: ItemTagData {3754d0ae} TRAKey | D69: √ | G69: 56
A70: 68 | B70: ItemTagData {807eed8a} TRAKey | D70: √ | G70: 59
A71: 69 | B71: {ee70bdd4} | C71: 二进制容器路径 | D71: √ | E71: √ | G71: 172
A72: 70 | B72: {40d2e7e6} | C72: 通告键 | D72: √ | E72: √ | G72: 152
A73: 71 | B73: {47f76f2b} | C73: 装备边框配置 | D73: √ | E73: √ | G73: 232
A74: 72 | B74: {a91dafb1} | C74: 特殊弈子和羁绊 | D74: √ | E74: √ | G74: 26
A75: 73 | B75: {912b57cb} | D75: √ | E75: √ | G75: 243
A76: 74 | B76: CarouselMapSkin | C76: 默认棋盘皮肤键 | D76: √ | E76: √ | G76: 62
A77: 75 | B77: {416ab5f5} | D77: √ | E77: √ | G77: 244
A78: 76 | B78: CompanionHealthPerTickMark | C78: 小小英雄生命值分度值 | D78: √ | E78: √ | G78: 215
A79: 77 | B79: {412bcd03} | C79: 推荐阵容 | D79: √ | E79: √ | G79: 208
A80: 78 | B80: BotSkillData | C80: 电脑玩家难度等级 | D80: √ | E80: √ | G80: 209
A81: 79 | B81: {22cc712f} | C81: 弈子解锁里程 | D81: √ | E81: √ | G81: 206
A82: 80 | B82: {bdb41827} | D82: √ | E82: √ | F82: TRUE | G82: 245
A83: 81 | B83: {8876469a} | C83: 独特玩法名称键 | D83: √ | E83: √ | G83: 173
A84: 82 | B84: {876a220d} | C84: 签名格键 | D84: √ | E84: √ | G84: 23
A85: 83 | B85: {c58ff569} | C85: 加农炮击键 | D85: √ | E85: √ | G85: 76
A86: 84 | B86: PveData | C86: 人机对战敌方单位配置键 | D86: √ | E86: √ | G86: 211
A87: 85 | B87: {37ed6c58} | C87: 子赛季列表 | D87: √ | E87: √ | G87: 8
A88: 86 | B88: {08dad7b8} | D88: √ | E88: √ | G88: 246
A89: 87 | B89: {0d042916} | D89: √ | E89: √ | G89: 247
A90: 88 | B90: {1743f77c} | C90: 背景颗粒键名 | D90: √ | E90: √ | G90: 234
A91: 89 | B91: displayName_content_zh | C91: 显示名（中文） | E91: √ | G91: 5
A92: 90 | B92: displayName_content_en | C92: 显示名（英文） | E92: √ | G92: 6
A93: 91 | B93: InfoNubData TitleKey_content_zh | C93: 特定赛季提示标题（中文） | E93: √ | G93: 178
A94: 92 | B94: InfoNubData TitleKey_content_en | C94: 特定赛季提示标题（英文） | E94: √ | G94: 179
A95: 93 | B95: InfoNubData BodyKey_content_zh | C95: 特定赛季提示主体（中文） | E95: √ | G95: 181
A96: 94 | B96: InfoNubData BodyKey_content_en | C96: 特定赛季提示主体（英文） | E96: √ | G96: 183
A97: 95 | B97: InfoNubData BodyKey_content_zh_burn | C97: 特定赛季提示主体（中文/数值转换） | E97: √ | G97: 182
A98: 96 | B98: InfoNubData BodyKey_content_en_burn | C98: 特定赛季提示主体（英文/数值转换） | E98: √ | G98: 184
A99: 97 | B99: InfoNubData Trait mDisplayNameTra_content_zh | C99: 特定赛季羁绊显示名（中文） | E99: √ | G99: 186
A100: 98 | B100: InfoNubData Trait mDisplayNameTra_content_en | C100: 特定赛季羁绊显示名（英文） | E100: √ | G100: 187
...

Sheet TFTShop_header
A1: Index | B1: Key | C1: Value | D1: DirectlyImport? | E1: Flexible | F1: defaultValue | G1: OutputOrder
A2: 0 | B2: key | C2: 主键 | D2: √ | G2: 0
A3: 1 | B3: mName | C3: 商品代码 | D3: √ | G3: 2
A4: 2 | B4: mRarity | C4: 稀有度 | D4: √ | E4: √ | G4: 6
A5: 3 | B5: {4d4e5cf5} | C5: 平台序号 | D5: √ | E5: √ | G5: 1
A6: 4 | B6: BaseCurrency | C6: 基础货币 | D6: √ | E6: √ | G6: 7
A7: 5 | B7: BaseCost | C7: 基础卡费 | D7: √ | E7: √ | G7: 8
A8: 6 | B8: AbilityIconPath | C8: 技能图标路径 | D8: √ | E8: √ | G8: 21
A9: 7 | B9: PcSplashPath | C9: PC端插画路径 | D9: √ | E9: √ | G9: 22
A10: 8 | B10: SquareSplashPath | C10: 方形插画路径 | D10: √ | E10: √ | G10: 23
A11: 9 | B11: TeamPlannerSplashPath | C11: 用于小队规划器的插画路径 | D11: √ | E11: √ | G11: 24
A12: 10 | B12: TeamPlannerPortraitPath | C12: 用于小队规划器的肖像路径 | D12: √ | E12: √ | G12: 25
A13: 11 | B13: mDisplayNameTra | C13: 显示名键 | D13: √ | E13: √ | G13: 3
A14: 12 | B14: mAbilityNameTra | C14: 技能名称键 | D14: √ | E14: √ | G14: 9
A15: 13 | B15: mDescriptionTra | C15: 描述键 | D15: √ | E15: √ | G15: 12
... A17: 15 | B17: {3451d6e4} | C17: 解锁图标路径 | D17: √ | E17: √ | G17: 20
A18: 16 | B18: mDisplayNameTra_content_zh | C18: 显示名（中文） | G18: 4
A19: 17 | B19: mDisplayNameTra_content_en | C19: 显示名（英文） | G19: 5
A20: 18 | B20: mAbilityNameTra_content_zh | C20: 技能名称（中文） | G20: 10
A21: 19 | B21: mAbilityNameTra_content_en | C21: 技能名称（英文） | G21: 11
A22: 20 | B22: mDescriptionTra_content_zh | C22: 描述（中文） | G22: 13
A23: 21 | B23: mDescriptionTra_content_en | C23: 描述（英文） | G23: 15
A24: 22 | B24: mDescriptionTra_content_zh_burn | C24: 描述（中文/数值转换） | G24: 14
A25: 23 | B25: mDescriptionTra_content_en_burn | C25: 描述（英文/数值转换） | G25: 16
A26: 24 | B26: SellOverwriteTra_content_zh | C26: 售卖描述（中文） | G26: 18
A27: 25 | B27: SellOverwriteTra_content_en | C27: 售卖描述（英文） | G27: 19

Sheet TFTShopContent_header
A1: Index | B1: Key | C1: Value | D1: DirectlyImport? | E1: Flexible | F1: defaultValue | G1: OutputOrder
A2: 0 | B2: key | C2: 主键 | D2: √ | G2: 0
A3: 1 | B3: TierBagIndex | C3: 星级背包索引 | G3: 1
A4: 2 | B4: TierBagEntryIndex | C4: 星级背包记录索引 | G4: 2
A5: 3 | B5: ShopData | C5: 商品键 | D5: √ | G5: 3
A6: 4 | B6: Count | C6: 数量 | D6: √ | E6: √ | G6: 6
A7: 5 | B7: ShopData mDisplayNameTra_content_zh | C7: 商品名称（中文） | G7: 4
A8: 6 | B8: ShopData mDisplayNameTra_content_en | C8: 商品名称（英文） | G8: 5

Sheet TFTDropRate_header
A1: Index | B1: Key | C1: Value | D1: DirectlyImport? | E1: Flexible | F1: defaultValue | G1: OutputOrder
A2: 0 | B2: key | C2: 主键 | D2: √ | G2: 0
A3: 1 | B3: mDropRatesByLevel Level | C3: 弈士等级 | G3: 2
A4: 2 | B4: {4f7d4b97} | C4: 卡费等第数量 | D4: √ | E4: √ | G4: 1
A5: 3 | B5: {bcf1e6a6} | C5: 卡费掉率 | D5: √ | G5: 3
A6: 4 | B6: {bcf1e6a6}_burn | C6: 卡费掉率字符串 | G6: 4

Sheet TFTStageRound_header
A1: Index | B1: Key | C1: Value | D1: DirectlyImport? | E1: Flexible | F1: defaultValue | G1: OutputOrder
A2: 0 | B2: key | C2: 主键 | D2: √ | G2: 0
A3: 1 | B3: stageIndex | C3: 阶段序号 | G3: 1
A4: 2 | B4: roundIndex | C4: 回合列表 | G4: 2
A5: 3 | B5: round_burn | C5: 回合字符串 | G5: 3
A6: 4 | B6: round | C6: 回合代码 | G6: 4
A7: 5 | B7: round mDisplayNameTra_contents_zh | C7: 回合名称（中文） | G7: 5
A8: 6 | B8: round mDisplayNameTra_contents_en | C8: 回合名称（英文） | G8: 6

Sheet TFTRound_header
A1: Index | B1: Key | C1: Value | D1: DirectlyImport? | E1: Flexible | F1: defaultValue | G1: OutputOrder
A2: 0 | B2: key | C2: 主键 | D2: √ | G2: 0
A3: 1 | B3: mName | C3: 回合代码 | D3: √ | G3: 1
A4: 2 | B4: mIconPath | C4: 缩略图路径 | D4: √ | G4: 60
A5: 3 | B5: mDisplayNameTra | C5: 回合显示名键 | D5: √ | E5: √ | G5: 2
A6: 4 | B6: mDefaultTooltipTra | C6: 默认说明文本键 | D6: √ | G6: 5
A7: 5 | B7: mStateTooltipsTra | C7: 状态说明文本键 | D7: √ | E7: √ | G7: 8
A8: 6 | B8: mRoundUpcomingIconPath | C8: 即将到来的回合缩略图路径 | D8: √ | G8: 61
A9: 7 | B9: mRoundActiveIconPath | C9: 当前回合缩略图路径 | D9: √ | G9: 62
A10: 8 | B10: mRoundResultNoneIconPath | C10: 无回合结果缩略图路径 | D10: √ | G10: 63
A11: 9 | B11: mRoundResultWinIconPath | C11: 回合胜利缩略图路径 | D11: √ | E11: √ | G11: 64
A12: 10 | B12: mRoundResultLossIconPath | C12: 回合失败缩略图路径 | D12: √ | E12: √ | G12: 65
A13: 11 | B13: mRoundResultDrawIconPath | C13: 平局缩略图路径 | D13: √ | E13: √ | G13: 66
A14: 12 | B14: mDraftArrival mEnabled | C14: 选秀准备阶段可用性 | D14: √ | E14: √ | F14: FALSE | G14: 11
A15: 13 | B15: mDraftArrival mDuration | C15: 选秀准备阶段持续时间 | D15: √ | E15: √ | G15: 15
A16: 14 | B16: mDraftArrival mDisplay | C16: 选秀准备阶段显示设置 | D16: √ | E16: √ | G16: 16
A17: 15 | B17: mDraftArrival mLabel | C17: 选秀准备阶段标签键 | D17: √ | E17: √ | G17: 12
A18: 16 | B18: mDraft mEnabled | C18: 选秀阶段可用性 | D18: √ | E18: √ | F18: FALSE | G18: 17
A19: 17 | B19: mDraft mDuration | C19: 选秀阶段持续时间 | D19: √ | E19: √ | G19: 18
A20: 18 | B20: mDraft mDisplay | C20: 选秀阶段显示设置 | D20: √ | E20: √ | G20: 19
A21: 19 | B21: mDraftDeparture mEnabled | C21: 选秀离开阶段可用性 | D21: √ | E21: √ | F21: FALSE | G21: 20
A22: 20 | B22: mDraftDeparture mDuration | C22: 选秀离开阶段持续时间 | D22: √ | E22: √ | G22: 21
A23: 21 | B23: mPlanningArrival Enabled | C23: 备战准备阶段可用性 | D23: √ | E23: √ | F23: FALSE | G23: 22
A24: 22 | B24: mPlanning mEnabled | C24: 备战阶段可用性 | D24: √ | E24: √ | F24: FALSE | G24: 23
A25: 23 | B25: mPlanning mDuration | C25: 备战阶段持续时间 | D25: √ | E25: √ | G25: 27
A26: 24 | B26: mPlanning mDisplay | C26: 备战阶段显示设置 | D26: √ | E26: √ | G26: 28
A27: 25 | B27: mPlanning mLabel | C27: 备战阶段标签键 | D27: √ | E27: √ | G27: 24
A28: 26 | B28: mPlanning mAnnouncementData | C28: 备战阶段通告键 | D28: √ | E28: √ | G28: 29
A29: 27 | B29: mPlanningDeparture mEnabled | C29: 备战离开阶段可用性 | D29: √ | E29: √ | F29: FALSE | G29: 30
A30: 28 | B30: mPlanningDeparture mDuration | C30: 备战离开阶段持续时间 | D30: √ | E30: √ | G30: 34
A31: 29 | B31: mPlanningDeparture mDisplay | C31: 备战离开阶段显示设置 | D31: √ | E31: √ | G31: 35
A32: 30 | B32: mPlanningDeparture mLabel | C32: 备战离开阶段标签键 | D32: √ | E32: √ | G32: 31
A33: 31 | B33: mCombatArrival mEnabled | C33: 战斗开始阶段可用性 | D33: √ | E33: √ | F33: FALSE | G33: 36
A34: 32 | B34: mCombatArrival mDuration | C34: 战斗开始阶段持续时间 | D34: √ | E34: √ | G34: 40
A35: 33 | B35: mCombatArrival mDisplay | C35: 战斗开始阶段显示设置 | D35: √ | E35: √ | G35: 41
A36: 34 | B36: mCombatArrival mLabel | C36: 战斗开始阶段标签键 | D36: √ | E36: √ | G36: 37
A37: 35 | B37: mCombatArrival mAnnouncementData | C37: 战斗开始阶段通告键 | D37: √ | E37: √ | G37: 42
A38: 36 | B38: mCombat mEnabled | C38: 战斗阶段可用性 | D38: √ | E38: √ | F38: FALSE | G38: 43
A39: 37 | B39: mCombat mDuration | C39: 战斗阶段持续时间 | D39: √ | E39: √ | G39: 47
A40: 38 | B40: mCombat mDisplay | C40: 战斗阶段显示设置 | D40: √ | E40: √ | G40: 48
A41: 39 | B41: mCombat mLabel | C41: 战斗阶段标签键 | D41: √ | E41: √ | G41: 44
A42: 40 | B42: CombatArtCleanup mEnabled | C42: 战后清场阶段可用性 | D42: √ | E42: √ | F42: FALSE | G42: 49
A43: 41 | B43: CombatArtCleanup mLabel | C43: 战后清场阶段标签键 | D43: √ | E43: √ | G43: 50
A44: 42 | B44: mCombatDeparture mEnabled | C44: 战斗离开阶段可用性 | D44: √ | E44: √ | F44: FALSE | G44: 53
A45: 43 | B45: mCombatDeparture mDuration | C45: 战斗离开阶段持续时间 | D45: √ | E45: √ | G45: 57
A46: 44 | B46: mCombatDeparture mDisplay | C46: 战斗离开阶段显示设置 | D46: √ | E46: √ | G46: 58
A47: 45 | B47: mCombatDeparture mLabel | C47: 战斗离开阶段标签键 | D47: √ | E47: √ | G47: 54
A48: 46 | B48: mScriptData | C48: 指令数据 | D48: √ | G48: 59
